Workbook

Sheet DataOld
A1: FECHA ASIGNACION | B1: NRO_SS | C1: Column2 | D1: CONTACTO | E1: Column4 | F1: Column42 | G1: Column3 | H1: NRO_ID | I1: Column5 | J1: NOMBRE_DE_OFICINA | K1: PMS | L1: DESCRIPCION_AMPLIADA | M1: PROVINCIA | N1: MUNICIPIO | O1: DISTRITO_MUNICIPIAL | P1: SECTOR | Q1: CALLE | R1: NUMERO | S1: EMPRESA_EDIFICIO | T1: DEPTO_APTO | U1: REFERENCIA | V1: TIPO_TEL_1 | W1: TEL_1 | X1: EXT_TEL_1 | Y1: TIPO_TEL_2 | Z1: TEL_2 | AA1: EXT_TEL_2 | AB1: TIPO_TEL_3 | AC1: TEL_3 | AD1: EXT_TEL_3 | AE1: FECHA_CREACION | AF1: MOTIVO_DEL_CIERRE | AG1: ESTATUS | AH1: COMENTARIO | AI1: QUIEN RECIBE | AJ1: INFO TERCERO | AK1: FECHA DE ENTREGA2 | AL1: Comentario BPD | AM1: COLUMNA PARA INGRESAR DIRECCIONES PINNIT | AN1: Column1
A2: 45883 | B2: 4-12189084312 | C2: 45883 | D2: ANGELICA YINNAIDA CUSTODIO BAEZ | E2: =VLOOKUP(DataOld!$B2,DATA!B:H,7,FALSE) -> #N/A | F2: =DataOld!$D2=DataOld!$E2 -> #N/A | G2: =VLOOKUP(DataOld!$B2,DATA!B:G,6,FALSE) -> #N/A | H2: 01300505086 | I2: =DataOld!$H2=DataOld!$G2 -> #N/A | J2: 159-OFICINA BANI I | K2: DISTRITO NACIONAL;SANTO DOMINGO;Altos de arroyo hond | L2: DISTRITO NACIONAL-SANTO DOMINGO-SANTO DOMINGO DE GUZMAN-Altos de arroyo hond-Avenida Monumental-0-Resid Nuevas Terrazas-AJ102-Resid Frente a Indomaca-C-8095057328-0-R-8099082845-0-C-0-0 | M2: DISTRITO NACIONAL | N2: SANTO DOMINGO | O2: SANTO DOMINGO DE GUZMAN | P2: Altos de arroyo hond | Q2: Avenida Monumental | R2: 0 | S2: Resid Nuevas Terrazas | T2: AJ102 | U2: Resid Frente a Indomaca | V2: C | W2: 8095057328 | X2: 0 | Y2: R | Z2: 8099082845 | AA2: 0 | AB2: C | AC2: 0 | AD2: 0 | AE2: 45883.604 | AG2: TD- ENTREGADO
A3: 45883 | B3: 4-12188798622 | C3: 45883 | D3: VIRGINIA ELIZABETH HERNANDEZ CARABALLO | E3: =VLOOKUP(DataOld!$B3,DATA!B:H,7,FALSE) -> #N/A | F3: =DataOld!$D3=DataOld!$E3 -> #N/A | G3: =VLOOKUP(DataOld!$B3,DATA!B:G,6,FALSE) -> #N/A | H3: 40214962066 | I3: =DataOld!$H3=DataOld!$G3 -> #N/A | J3: 303-OFICINA SAMBIL | K3: DISTRITO NACIONAL;SANTO DOMINGO;Arroyo hondo III | L3: Distrito Nacional-Santo Domingo-Santo Domingo De Guzman-Arroyo hondo III-Repblica de Colombia-302-Villa Graciela Manzana E-Edificio 7-Frente al bravo apto 302-C-8299604126-0-C-8299612752-0-0-0 | M3: DISTRITO NACIONAL | N3: SANTO DOMINGO | O3: SANTO DOMINGO DE GUZMAN | P3: Arroyo hondo III | Q3: Repblica de Colombia | R3: 302 | S3: Villa Graciela Manzana E | T3: Edificio 7 | U3: Frente al bravo apto 302 | V3: C | W3: 8299604126 | X3: 0 | Y3: C | Z3: 8299612752 | AA3: 0 | AB3: 0 | AC3: 0 | AE3: 45883.575 | AG3: TD- ENTREGADO
A4: 45883 | B4: 4-12188910712 | C4: 45883 | D4: KARLA MARIEL ARIAS CABRERA | E4: =VLOOKUP(DataOld!$B4,DATA!B:H,7,FALSE) -> #N/A | F4: =DataOld!$D4=DataOld!$E4 -> #N/A | G4: =VLOOKUP(DataOld!$B4,DATA!B:G,6,FALSE) -> #N/A | H4: 40222131134 | I4: =DataOld!$H4=DataOld!$G4 -> #N/A | J4: 144-OFICINA HERRERA | K4: DISTRITO NACIONAL;SANTO DOMINGO;Bayona | L4: DISTRITO NACIONAL-SANTO DOMINGO-SANTO DOMINGO DE GUZMAN-Bayona-Anastasio Tronil-52-0-0-casa 52-R-8493573029-0-C-8093306209-0-C-0-0 | M4: DISTRITO NACIONAL | N4: SANTO DOMINGO | O4: SANTO DOMINGO DE GUZMAN | P4: Bayona | Q4: Anastasio Tronil | R4: 52 | S4: 0 | T4: 0 | U4: casa 52 | V4: R | W4: 8493573029 | X4: 0 | Y4: C | Z4: 8093306209 | AA4: 0 | AB4: C | AC4: 0 | AD4: 0 | AE4: 45883.588 | AG4: TD- ENTREGADO
A5: 45883 | B5: 4-12188828862 | C5: 45883 | D5: ELIAN BUENO UBRI | E5: =VLOOKUP(DataOld!$B5,DATA!B:H,7,FALSE) -> #N/A | F5: =DataOld!$D5=DataOld!$E5 -> #N/A | G5: =VLOOKUP(DataOld!$B5,DATA!B:G,6,FALSE) -> #N/A | H5: 40232370011 | I5: =DataOld!$H5=DataOld!$G5 -> #N/A | J5: 137-OFICINA WINSTON CHURCHILL | K5: DISTRITO NACIONAL;SANTO DOMINGO;Bella vista | L5: DISTRITO NACIONAL-SANTO DOMINGO-SANTO DOMINGO DE GUZMAN-Bella vista-sarasota-62-ccc papeleria-2do nivel-dentro de almacenes unidos-C-8299137334-0-T-8295576507-0000-C-0-0 | M5: DISTRITO NACIONAL | N5: SANTO DOMINGO | O5: SANTO DOMINGO DE GUZMAN | P5: Bella vista | Q5: sarasota | R5: 62 | S5: ccc papeleria | T5: 2do nivel | U5: dentro de almacenes unidos | V5: C | W5: 8299137334 | X5: 0 | Y5: T | Z5: 8295576507 | AA5: 0000 | AB5: C | AC5: 0 | AD5: 0 | AE5: 45883.582 | AG5: TD- ENTREGADO
A6: 45883 | B6: 4-12189276732 | C6: 45883 | D6: DANIEL GUZMAN TORREZ | E6: =VLOOKUP(DataOld!$B6,DATA!B:H,7,FALSE) -> #N/A | F6: =DataOld!$D6=DataOld!$E6 -> #N/A | G6: =VLOOKUP(DataOld!$B6,DATA!B:G,6,FALSE) -> #N/A | H6: 00117882977 | I6: =DataOld!$H6=DataOld!$G6 -> #N/A | J6: 150-OFICINA PLAZA COMERCIAL PARQUE HABITAT | K6: DISTRITO NACIONAL;SANTO DOMINGO;cuesta hermosas 2 | L6: DISTRITO NACIONAL-SANTO DOMINGO-SANTO DOMINGO DE GUZMAN-cuesta hermosas 2-3ra del rios-31-jardineros-casa 31-trabajo dosmetico desde 2008-C-8493792031-0-T-8095653018-0-C-8097292133-0 | M6: DISTRITO NACIONAL | N6: SANTO DOMINGO | O6: SANTO DOMINGO DE GUZMAN | P6: cuesta hermosas 2 | Q6: 3ra del rios | R6: 31 | S6: jardineros | T6: casa 31 | U6: trabajo dosmetico desde 2008 | V6: C | W6: 8493792031 | X6: 0 | Y6: T | Z6: 8095653018 | AA6: 0 | AB6: C | AC6: 8097292133 | AD6: 0 | AE6: 45883.632 | AG6: TD- ENTREGADO
A7: 45883 | B7: 4-12189239872 | C7: 45883 | D7: ALIMER LOPEZ DE LOS SANTOS | E7: =VLOOKUP(DataOld!$B7,DATA!B:H,7,FALSE) -> #N/A | F7: =DataOld!$D7=DataOld!$E7 -> #N/A | G7: =VLOOKUP(DataOld!$B7,DATA!B:G,6,FALSE) -> #N/A | H7: 40209048608 | I7: =DataOld!$H7=DataOld!$G7 -> #N/A | J7: 464-OCCIDENTALL MALL | K7: DISTRITO NACIONAL;SANTO DOMINGO;Ensanche Kennedy | L7: Distrito Nacional-Santo Domingo-Santo Domingo De Guzman-Ensanche Kennedy -Av John F Kennedy-1-Humano Seguros -Sac Inter-Alimer Lpez-C-8098017677-0-C-8293233001-0-0-0 | M7: DISTRITO NACIONAL | N7: SANTO DOMINGO | O7: SANTO DOMINGO DE GUZMAN | P7: Ensanche Kennedy | Q7: Av John F Kennedy | R7: 1 | S7: Humano Seguros | T7: Sac Inter | U7: Alimer Lpez | V7: C | W7: 8098017677 | X7: 0 | Y7: C | Z7: 8293233001 | AA7: 0 | AB7: 0 | AC7: 0 | AE7: 45883.633 | AG7: TD- ENTREGADO | AL7: CLIENTE INDICA YA LA TIENE
A8: 45883 | B8: 4-12189095572 | C8: 45883 | D8: GEORGE JOSE PINA ROBLES | E8: =VLOOKUP(DataOld!$B8,DATA!B:H,7,FALSE) -> #N/A | F8: =DataOld!$D8=DataOld!$E8 -> #N/A | G8: =VLOOKUP(DataOld!$B8,DATA!B:G,6,FALSE) -> #N/A | H8: 40213113240 | I8: =DataOld!$H8=DataOld!$G8 -> #N/A | J8: 139-OFICINA NACO | K8: DISTRITO NACIONAL;SANTO DOMINGO;Ensanche luperon | L8: Distrito Nacional-Santo Domingo-Santo Domingo De Guzman-Ensanche luperon -25 este-19-Soluciones oficinas Diaz -VENTAS SOD-Preguntar por GEORGE VENTAS-C-8299643293-0-C-8293034089-0-0-0 | M8: DISTRITO NACIONAL | N8: SANTO DOMINGO | O8: SANTO DOMINGO DE GUZMAN | P8: Ensanche luperon | Q8: 25 este | R8: 19 | S8: Soluciones oficinas Diaz | T8: VENTAS SOD | U8: Preguntar por GEORGE VENTAS | V8: C | W8: 8299643293 | X8: 0 | Y8: C | Z8: 8293034089 | AA8: 0 | AB8: 0 | AC8: 0 | AE8: 45883.61 | AG8: TD- ENTREGADO
A9: 45883 | B9: 4-12187995692 | C9: 45883 | D9: JONNY EDWARD LORENZO SANCHEZ | E9: =VLOOKUP(DataOld!$B9,DATA!B:H,7,FALSE) -> #N/A | F9: =DataOld!$D9=DataOld!$E9 -> #N/A | G9: =VLOOKUP(DataOld!$B9,DATA!B:G,6,FALSE) -> #N/A | H9: 00101728046 | I9: =DataOld!$H9=DataOld!$G9 -> #N/A | J9: 137-OFICINA WINSTON CHURCHILL | K9: DISTRITO NACIONAL;SANTO DOMINGO;Evaristo Morales | L9: Distrito Nacional-Santo Domingo-Santo Domingo De Guzman-Evaristo Morales -Calle Viriato Fiallo-57-Agencia Milena Tours-Comercial-0-C-8299629262-0-T-8095666076-221-0-0 | M9: DISTRITO NACIONAL | N9: SANTO DOMINGO | O9: SANTO DOMINGO DE GUZMAN | P9: Evaristo Morales | Q9: Calle Viriato Fiallo | R9: 57 | S9: Agencia Milena Tours | T9: Comercial | U9: 0 | V9: C | W9: 8299629262 | X9: 0 | Y9: T | Z9: 8095666076 | AA9: 221 | AB9: 0 | AC9: 0 | AE9: 45883.513 | AG9: TD- ENTREGADO
A10: 45883 | B10: 4-12188179862 | C10: 45883 | D10: JOAN RAFAEL MEJIA FERREIRAS | E10: =VLOOKUP(DataOld!$B10,DATA!B:H,7,FALSE) -> #N/A | F10: =DataOld!$D10=DataOld!$E10 -> #N/A | G10: =VLOOKUP(DataOld!$B10,DATA!B:G,6,FALSE) -> #N/A | H10: 00118948504 | I10: =DataOld!$H10=DataOld!$G10 -> #N/A | J10: 137-OFICINA WINSTON CHURCHILL | K10: DISTRITO NACIONAL;SANTO DOMINGO;Evaristo Morales | L10: DISTRITO NACIONAL-SANTO DOMINGO-SANTO DOMINGO DE GUZMAN-Evaristo Morales-Luis F Thomen-104-contemega-finanzas-0-C-8295188321-0-T-8092275558-0-C-0-0 | M10: DISTRITO NACIONAL | N10: SANTO DOMINGO | O10: SANTO DOMINGO DE GUZMAN | P10: Evaristo Morales | Q10: Luis F Thomen | R10: 104 | S10: contemega | T10: finanzas | U10: 0 | V10: C | W10: 8295188321 | X10: 0 | Y10: T | Z10: 8092275558 | AA10: 0 | AB10: C | AC10: 0 | AD10: 0 | AE10: 45883.535 | AG10: TD- ENTREGADO
A11: 45883 | B11: 4-12188709602 | C11: 45883 | D11: FRANCISCO NICOLAS JOSE PEREZ | E11: =VLOOKUP(DataOld!$B11,DATA!B:H,7,FALSE) -> #N/A | F11: =DataOld!$D11=DataOld!$E11 -> #N/A | G11: =VLOOKUP(DataOld!$B11,DATA!B:G,6,FALSE) -> #N/A | H11: 40214693992 | I11: =DataOld!$H11=DataOld!$G11 -> #N/A | J11: 196-OFICINA SAN VICENTE DE PAUL | K11: DISTRITO NACIONAL;SANTO DOMINGO;Evaristo Morales | L11: Distrito Nacional-Santo Domingo-Santo Domingo De Guzman-Evaristo Morales-Max Henrinquez Urena-98-Torre Lia Kamille X-6B-0-C-8099142302-0-C-8297189305-0-0-0 | M11: DISTRITO NACIONAL | N11: SANTO DOMINGO | O11: SANTO DOMINGO DE GUZMAN | P11: Evaristo Morales | Q11: Max Henrinquez Urena | R11: 98 | S11: Torre Lia Kamille X | T11: 6B | U11: 0 | V11: C | W11: 8099142302 | X11: 0 | Y11: C | Z11: 8297189305 | AA11: 0 | AB11: 0 | AC11: 0 | AE11: 45883.564 | AG11: TD- ENTREGADO
A12: 45883 | B12: 4-12188985282 | C12: 45883 | D12: SORANGEL IVETTE ARIAS PAYANO | E12: =VLOOKUP(DataOld!$B12,DATA!B:H,7,FALSE) -> #N/A | F12: =DataOld!$D12=DataOld!$E12 -> #N/A | G12: =VLOOKUP(DataOld!$B12,DATA!B:G,6,FALSE) -> #N/A | H12: 40224783130 | I12: =DataOld!$H12=DataOld!$G12 -> #N/A | J12: 273-OFICINA CAMPUS UCE SPM | K12: DISTRITO NACIONAL;SANTO DOMINGO;Honduras del Norte | L12: DISTRITO NACIONAL-SANTO DOMINGO-SANTO DOMINGO DE GUZMAN-Honduras del Norte-Avenida Independenci-2266-SIHISA-A210-Plaza Atalaya encima GBC-C-8293498341-0-C-8493792101-0-C-0-0 | M12: DISTRITO NACIONAL | N12: SANTO DOMINGO | O12: cambita Garabitos | P12: Honduras del Norte | Q12: Avenida Independenci | R12: 2266 | S12: SIHISA | T12: A210 | U12: Plaza Atalaya encima GBC | V12: C | W12: 8293498341 | X12: 0 | Y12: C | Z12: 8493792101 | AA12: 0 | AB12: C | AC12: 0 | AD12: 0 | AE12: 45883.6 | AG12: TD- ENTREGADO
A13: 45883 | B13: 4-12188107222 | C13: 45883 | D13: CLAUDIA MIGUELINA REYES GUZMAN | E13: =VLOOKUP(DataOld!$B13,DATA!B:H,7,FALSE) -> #N/A | F13: =DataOld!$D13=DataOld!$E13 -> #N/A | G13: =VLOOKUP(DataOld!$B13,DATA!B:G,6,FALSE) -> #N/A | H13: 00117248633 | I13: =DataOld!$H13=DataOld!$G13 -> #N/A | J13: 140-OFICINA EL PORTAL | K13: DISTRITO NACIONAL;SANTO DOMINGO;Las Praderas | L13: Distrito Nacional-Santo Domingo-Santo Domingo De Guzman-Las Praderas -Libertad -41-Cuatro Cuerdas Estudio M-NA-Misma calle de Almacenes El -C-8299171304-0-T-8097407514-1-T-8095342917-02 | M13: DISTRITO NACIONAL | N13: SANTO DOMINGO | O13: SANTO DOMINGO DE GUZMAN | P13: Las Praderas | Q13: Libertad | R13: 41 | S13: Cuatro Cuerdas Estudio M | T13: NA | U13: Misma calle de Almacenes El | V13: C | W13: 8299171304 | X13: 0 | Y13: T | Z13: 8097407514 | AA13: 1 | AB13: T | AC13: 8095342917 | AD13: 02 | AE13: 45883.536 | AG13: TD- ENTREGADO
A14: 45883 | B14: 4-12188106922 | C14: 45883 | D14: PEDRO JANEL ZORRILLA ZORRILLA | E14: =VLOOKUP(DataOld!$B14,DATA!B:H,7,FALSE) -> #N/A | F14: =DataOld!$D14=DataOld!$E14 -> #N/A | G14: =VLOOKUP(DataOld!$B14,DATA!B:G,6,FALSE) -> #N/A | H14: 40209963392 | I14: =DataOld!$H14=DataOld!$G14 -> #N/A | J14: 342-OFICINA GALERIA 360 | K14: DISTRITO NACIONAL;SANTO DOMINGO;Los Frailes | L14: Distrito Nacional-Santo Domingo-Santo Domingo De Guzman-Los Frailes -Salome urena -52-0-0-Casa segundo nivel -C-8297686283-0-C-8293494825-0-0-0 | M14: DISTRITO NACIONAL | N14: SANTO DOMINGO | O14: SANTO DOMINGO DE GUZMAN | P14: Los Frailes | Q14: Salome urena | R14: 52 | S14: 0 | T14: 0 | U14: Casa segundo nivel | V14: C | W14: 8297686283 | X14: 0 | Y14: C | Z14: 8293494825 | AA14: 0 | AB14: 0 | AC14: 0 | AE14: 45883.53 | AG14: TD- NO LE INTERESA | AH14: NUMEROS NO RESPONDEN | AL14: NO LE INTERESA, ESTA FUERA DEL PAIS
A15: 45883 | B15: 4-12187850582 | C15: 45883 | D15: LUIS SADIEL GARCIA DIAZ | E15: =VLOOKUP(DataOld!$B15,DATA!B:H,7,FALSE) -> #N/A | F15: =DataOld!$D15=DataOld!$E15 -> #N/A | G15: =VLOOKUP(DataOld!$B15,DATA!B:G,6,FALSE) -> #N/A | H15: 40213726413 | I15: =DataOld!$H15=DataOld!$G15 -> #N/A | J15: 344-OFICINA OLE LOS FRAILES | K15: DISTRITO NACIONAL;SANTO DOMINGO;Los Prados | L15: Distrito Nacional-Santo Domingo-Santo Domingo De Guzman-Los prados -Av charles sumner -54-Smarbet-Local 3b-Plaza charles sumner -C-8097127429-0-C-8295564287-0-0-0 | M15: DISTRITO NACIONAL | N15: SANTO DOMINGO | O15: SANTO DOMINGO DE GUZMAN | P15: Los Prados | Q15: Av charles sumner | R15: 54 | S15: Smarbet | T15: Local 3b | U15: Plaza charles sumner | V15: C | W15: 8097127429 | X15: 0 | Y15: C | Z15: 8295564287 | AA15: 0 | AB15: 0 | AC15: 0 | AE15: 45883.495 | AG15: TD- ENTREGADO
A16: 45883 | B16: 4-12188139092 | C16: 45883 | D16: ESTEFANIA MATOS | E16: =VLOOKUP(DataOld!$B16,DATA!B:H,7,FALSE) -> #N/A | F16: =DataOld!$D16=DataOld!$E16 -> #N/A | G16: =VLOOKUP(DataOld!$B16,DATA!B:G,6,FALSE) -> #N/A | H16: 40237205907 | I16: =DataOld!$H16=DataOld!$G16 -> #N/A | J16: 139-OFICINA NACO | K16: DISTRITO NACIONAL;SANTO DOMINGO;paraiso | L16: DISTRITO NACIONAL-SANTO DOMINGO-SANTO DOMINGO DE GUZMAN-paraiso-ponzio zabater-00-farma extra-farmacia-plaza paraiso-C-8492064868-0-C-8095673919-0-C-8094049169-0 | M16: DISTRITO NACIONAL | N16: SANTO DOMINGO | O16: SANTO DOMINGO DE GUZMAN | P16: paraiso | Q16: ponzio zabater | R16: 00 | S16: farma extra | T16: farmacia | U16: plaza paraiso | V16: C | W16: 8492064868 | X16: 0 | Y16: C | Z16: 8095673919 | AA16: 0 | AB16: C | AC16: 8094049169 | AD16: 0 | AE16: 45883.534 | AG16: TD- ENTREGADO
A17: 45883 | B17: 4-12188938362 | C17: 45883 | D17: DIEGO ALEJANDRO PUMAROL CUNILLERA | E17: =VLOOKUP(DataOld!$B17,DATA!B:H,7,FALSE) -> #N/A | F17: =DataOld!$D17=DataOld!$E17 -> #N/A | G17: =VLOOKUP(DataOld!$B17,DATA!B:G,6,FALSE) -> #N/A | H17: 40230377547 | I17: =DataOld!$H17=DataOld!$G17 -> #N/A | J17: Centro Digital Popular | K17: DISTRITO NACIONAL;SANTO DOMINGO;Piantini | L17: Distrito Nacional-Santo Domingo-Santo Domingo De Guzman-Piantini-Federico Geraldino-58-Torre palmera real-301A-0-C-8098533323-0-C-8098487707-0-0-0 | M17: DISTRITO NACIONAL | N17: SANTO DOMINGO | O17: SANTO DOMINGO DE GUZMAN | P17: Piantini | Q17: Federico Geraldino | R17: 58 | S17: Torre palmera real | T17: 301A | U17: 0 | V17: C | W17: 8098533323 | X17: 0 | Y17: C | Z17: 8098487707 | AA17: 0 | AB17: 0 | AC17: 0 | AE17: 45883.589 | AG17: TD- ENTREGADO
A18: 45883 | B18: 4-12187994612 | C18: 45883 | D18: EMER JOSE TEJEDA DIONICIO | E18: =VLOOKUP(DataOld!$B18,DATA!B:H,7,FALSE) -> #N/A | F18: =DataOld!$D18=DataOld!$E18 -> #N/A | G18: =VLOOKUP(DataOld!$B18,DATA!B:G,6,FALSE) -> #N/A | H18: 00201418597 | I18: =DataOld!$H18=DataOld!$G18 -> #N/A | J18: 141-OFICINA TORRE EMPRESARIAL 27 DE FEBRERO | K18: DISTRITO NACIONAL;SANTO DOMINGO;Serralles | L18: DISTRITO NACIONAL-SANTO DOMINGO-SANTO DOMINGO DE GUZMAN-Serralles-John F Kenedy-52-Claro Dominicana-3er Piso-0-C-8096057997-0-C-8094245121-0-C-0-0 | M18: DISTRITO NACIONAL | N18: SANTO DOMINGO | O18: SANTO DOMINGO DE GUZMAN | P18: Serralles | Q18: John F Kenedy | R18: 52 | S18: Claro Dominicana | T18: 3er Piso | U18: 0 | V18: C | W18: 8096057997 | X18: 0 | Y18: C | Z18: 8094245121 | AA18: 0 | AB18: C | AC18: 0 | AD18: 0 | AE18: 45883.508 | AG18: TD- ENTREGADO
A19: 45883 | B19: 4-12189252532 | C19: 45883 | D19: ANGEL BERTINIO MATEO BERNABE | E19: =VLOOKUP(DataOld!$B19,DATA!B:H,7,FALSE) -> #N/A | F19: =DataOld!$D19=DataOld!$E19 -> #N/A | G19: =VLOOKUP(DataOld!$B19,DATA!B:G,6,FALSE) -> #N/A | H19: 01300373261 | I19: =DataOld!$H19=DataOld!$G19 -> #N/A | J19: 201-OFICINA VILLA CONSUELO | K19: DISTRITO NACIONAL;SANTO DOMINGO;villa consuelo | L19: DISTRITO NACIONAL-SANTO DOMINGO-SANTO DOMINGO DE GUZMAN-villa consuelo-calle batazar de los-114-colmado hermanos mateo-1-frente a la banca ortiz-C-8298599580-0-C-8497500226-0-C-0-0 | M19: DISTRITO NACIONAL | N19: SANTO DOMINGO | O19: SANTO DOMINGO DE GUZMAN | P19: villa consuelo | Q19: calle batazar de los | R19: 114 | S19: colmado hermanos mateo | T19: 1 | U19: frente a la banca ortiz | V19: C | W19: 8298599580 | X19: 0 | Y19: C | Z19: 8497500226 | AA19: 0 | AB19: C | AC19: 0 | AD19: 0 | AE19: 45883.624 | AG19: TD- ENTREGADO
A20: 45883 | B20: 4-12188623782 | C20: 45883 | D20: RAFAEL ANTONIO PENA BENITEZ | E20: =VLOOKUP(DataOld!$B20,DATA!B:H,7,FALSE) -> #N/A | F20: =DataOld!$D20=DataOld!$E20 -> #N/A | G20: =VLOOKUP(DataOld!$B20,DATA!B:G,6,FALSE) -> #N/A | H20: 22300543331 | I20: =DataOld!$H20=DataOld!$G20 -> #N/A | J20: 204-OFICINA MAXIMO GOMEZ | K20: DISTRITO NACIONAL;SANTO DOMINGO;villas agricolas | L20: DISTRITO NACIONAL-SANTO DOMINGO-SANTO DOMINGO DE GUZMAN-villas agricolas-Maria montez-249-seinca-local gris-Al lado del respuesto Angher-C-8292223079-0-T-8095366571-0-C-8096142127-0 | M20: DISTRITO NACIONAL | N20: SANTO DOMINGO | O20: SANTO DOMINGO DE GUZMAN | P20: villas agricolas | Q20: Maria montez | R20: 249 | S20: seinca | T20: local gris | U20: Al lado del respuesto Angher | V20: C | W20: 8292223079 | X20: 0 | Y20: T | Z20: 8095366571 | AA20: 0 | AB20: C | AC20: 8096142127 | AD20: 0 | AE20: 45883.554 | AG20: TD- ENTREGADO
A21: 45883 | B21: 4-12188798812 | C21: 45883 | D21: JUNIOR ALBERTO RODRIGUEZ ROSARIO | E21: =VLOOKUP(DataOld!$B21,DATA!B:H,7,FALSE) -> #N/A | F21: =DataOld!$D21=DataOld!$E21 -> #N/A | G21: =VLOOKUP(DataOld!$B21,DATA!B:G,6,FALSE) -> #N/A | H21: 40241135256 | I21: =DataOld!$H21=DataOld!$G21 -> #N/A | J21: 216-OFICINA IBERIA HIGUEY | K21: LA ALTAGRACIA;HIGUEY;Centro de la ciudad | L21: La Altagracia-Higuey-Higuey-Centro de la ciudad -Agustin guerrero -58-Carlos celulares -Primer pis-Al lado de David foto color -C-8498069003-0-T-8095545138-220-0-0 | M21: LA ALTAGRACIA | N21: HIGUEY | O21: Higuey | P21: Centro de la ciudad | Q21: Agustin guerrero | R21: 58 | S21: Carlos celulares | T21: Primer pis | U21: Al lado de David foto color | V21: C | W21: 8498069003 | X21: 0 | Y21: T | Z21: 8095545138 | AA21: 220 | AB21: 0 | AC21: 0 | AE21: 45883.579 | AG21: TD- ENTREGADO
A22: 45883 | B22: 4-12188710222 | C22: 45883 | D22: YULAINI VALESCA REYES OLIVO | E22: =VLOOKUP(DataOld!$B22,DATA!B:H,7,FALSE) -> #N/A | F22: =DataOld!$D22=DataOld!$E22 -> #N/A | G22: =VLOOKUP(DataOld!$B22,DATA!B:G,6,FALSE) -> #N/A | H22: 40231668597 | I22: =DataOld!$H22=DataOld!$G22 -> #N/A | J22: 234-OFICINA PUNTA CANA | K22: LA ALTAGRACIA;HIGUEY;Los rosales | L22: La Altagracia-Higuey-Higuey-Los rosales-Urania montas -32-0-0-Casa verde con antena -C-8293188639-0-C-8092995224-0-0-0 | M22: LA ALTAGRACIA | N22: HIGUEY | O22: Higuey | P22: Los rosales | Q22: Urania montas | R22: 32 | S22: 0 | T22: 0 | U22: Casa verde con antena | V22: C | W22: 8293188639 | X22: 0 | Y22: C | Z22: 8092995224 | AA22: 0 | AB22: 0 | AC22: 0 | AE22: 45883.575 | AG22: TD- ENTREGADO
A23: 45883 | B23: 4-12188036942 | C23: 45883 | D23: ALEXANDER LUIS | E23: =VLOOKUP(DataOld!$B23,DATA!B:H,7,FALSE) -> #N/A | F23: =DataOld!$D23=DataOld!$E23 -> #N/A | G23: =VLOOKUP(DataOld!$B23,DATA!B:G,6,FALSE) -> #N/A | H23: 40233244967 | I23: =DataOld!$H23=DataOld!$G23 -> #N/A | J23: 219-OFICINA DE SERVICIOS UVERO ALTO | K23: LA ALTAGRACIA;HIGUEY;Nisibon La vacama | L23: La Altagracia-Higuey-Higuey-Nisibon La vacama -Principal -8-0-0-Antes del puente La vacama -C-8493754596-0-C-8295854121-0-0-0 | M23: LA ALTAGRACIA | N23: HIGUEY | O23: Higuey | P23: Nisibon La vacama | Q23: Principal | R23: 8 | S23: 0 | T23: 0 | U23: Antes del puente La vacama | V23: C | W23: 8493754596 | X23: 0 | Y23: C | Z23: 8295854121 | AA23: 0 | AB23: 0 | AC23: 0 | AE23: 45883.518 | AG23: TD- ENTREGADO
A24: 45883 | B24: 4-12188769322 | C24: 45883 | D24: RANCELL ALEXANDERT MONTERO | E24: =VLOOKUP(DataOld!$B24,DATA!B:H,7,FALSE) -> #N/A | F24: =DataOld!$D24=DataOld!$E24 -> #N/A | G24: =VLOOKUP(DataOld!$B24,DATA!B:G,6,FALSE) -> #N/A | H24: 40226358360 | I24: =DataOld!$H24=DataOld!$G24 -> #N/A | J24: 272-OFICINA LA OTRA BANDA, HIGUEY | K24: LA ALTAGRACIA;HIGUEY;veron | L24: LA ALTAGRACIA-HIGUEY-VERON PUNTA CANA-veron-avenida barcelo km2-13-MONTILL MOTORS-Informatic-Encargado informatica-C-8097503587-0-T-8094551515-219-T-8097233768-0 | M24: LA ALTAGRACIA | N24: HIGUEY | O24: VERON PUNTA CANA | P24: veron | Q24: avenida barcelo km2 | R24: 13 | S24: MONTILL MOTORS | T24: Informatic | U24: Encargado informatica | V24: C | W24: 8097503587 | X24: 0 | Y24: T | Z24: 8094551515 | AA24: 219 | AB24: T | AC24: 8097233768 | AD24: 0 | AE24: 45883.566 | AG24: TD- ENTREGADO
A25: 45883 | B25: 4-12189289782 | C25: 45883 | D25: REYNALDO DE LOS SANTO GONZALE | E25: =VLOOKUP(DataOld!$B25,DATA!B:H,7,FALSE) -> #N/A | F25: =DataOld!$D25=DataOld!$E25 -> #N/A | G25: =VLOOKUP(DataOld!$B25,DATA!B:G,6,FALSE) -> #N/A | H25: 07900181699 | I25: =DataOld!$H25=DataOld!$G25 -> #N/A | J25: 215-OFICINA BAVARO | K25: LA ALTAGRACIA;HIGUEY;villa europa | L25: LA ALTAGRACIA-HIGUEY-VERON PUNTA CANA-villa europa-doble via de veron-1-apt ps-si-frente al drik molly-C-8298519029-0-C-8298519023-0-C-8297743157-0 | M25: LA ALTAGRACIA | N25: HIGUEY | O25: VERON PUNTA CANA | P25: villa europa | Q25: doble via de veron | R25: 1 | S25: apt ps | T25: Si | U25: frente al drik molly | V25: C | W25: 8298519029 | X25: 0 | Y25: C | Z25: 8298519023 | AA25: 0 | AB25: C | AC25: 8297743157 | AD25: 0 | AE25: 45883.63 | AG25: TD- ENTREGADO | AL25: 8298519029/-C-8297743157-EQUIVOCADO/LE ESCRIBI X WSS A ESPERA DE RESPUESTA ME ENVIO LA UBICACION X WSS A SU VES LA ENVIE A CELERITA( RAMSES Y ARMANDO
A26: 45883 | B26: 4-12188317912 | C26: 45883 | D26: FRANCELIS YULISSA SOTO SUAZO DE SOTO | E26: =VLOOKUP(DataOld!$B26,DATA!B:H,7,FALSE) -> #N/A | F26: =DataOld!$D26=DataOld!$E26 -> #N/A | G26: =VLOOKUP(DataOld!$B26,DATA!B:G,6,FALSE) -> #N/A | H26: 00301147070 | I26: =DataOld!$H26=DataOld!$G26 -> #N/A | J26: 159-OFICINA BANI I | K26: PERAVIA;BANI;Bani | L26: Peravia-Bani-Bani-Bani-Calle Snchez-29-Laboratorio Amadita -Plaza-Plaza Bani-C-8097121229-0-C-8294205958-0-0-0 | M26: PERAVIA | N26: BANI | O26: Bani | P26: Bani | Q26: Calle Snchez | R26: 29 | S26: Laboratorio amadita | T26: Plaza | U26: Plaza Bani | V26: C | W26: 8097121229 | X26: 0 | Y26: C | Z26: 8294205958 | AA26: 0 | AB26: 0 | AC26: 0 | AE26: 45883.533 | AG26: TD- ENTREGADO
A27: 45883 | B27: 4-12188661002 | C27: 45883 | D27: NIKITA LITVINOV | E27: =VLOOKUP(DataOld!$B27,DATA!B:H,7,FALSE) -> #N/A | F27: =DataOld!$D27=DataOld!$E27 -> #N/A | G27: =VLOOKUP(DataOld!$B27,DATA!B:G,6,FALSE) -> #N/A | H27: 40245185752 | I27: =DataOld!$H27=DataOld!$G27 -> #N/A | J27: 269-OFICINA CABARETE | K27: Puerto Plata;Sosua;Ocean village | L27: Puerto Plata-Sosua-Sosua-Ocean village-Ocean village -20-0-0-0-C-8298899999-0-C-8493148881-0-0-0 | M27: Puerto Plata | N27: Sosua | O27: Sosua | P27: Ocean village | Q27: Ocean village | R27: 20 | S27: 0 | T27: 0 | U27: 0 | V27: C | W27: 8298899999 | X27: 0 | Y27: C | Z27: 8493148881 | AA27: 0 | AB27: 0 | AC27: 0 | AE27: 45883.563 | AG27: TD- ENTREGADO
A28: 45883 | B28: 4-12188009622 | C28: 45883 | D28: JOSUE DIAZ RODRIGUEZ | E28: =VLOOKUP(DataOld!$B28,DATA!B:H,7,FALSE) -> #N/A | F28: =DataOld!$D28=DataOld!$E28 -> #N/A | G28: =VLOOKUP(DataOld!$B28,DATA!B:G,6,FALSE) -> #N/A | H28: 40229911199 | I28: =DataOld!$H28=DataOld!$G28 -> #N/A | J28: 158-OFICINA PIISA HAINA | K28: SAN CRISTOBAL;BAJOS DE HAINA;Cabon | L28: San Cristobal-Bajos De Haina-Bajos De Haina-Cabon-Minerva mirabal -1651-0-0-Frente a la escuela basica -C-8292192273-0-C-8492814066-0-0-0 | M28: SAN CRISTOBAL | N28: BAJOS DE HAINA | O28: BAJOS DE HAINA | P28: Cabon | Q28: Minerva mirabal | R28: 1651 | S28: 0 | T28: 0 | U28: Frente a la escuela basica | V28: C | W28: 8292192273 | X28: 0 | Y28: C | Z28: 8492814066 | AA28: 0 | AB28: 0 | AC28: 0 | AE28: 45883.511 | AG28: TD- ENTREGADO
A29: 45883 | B29: 4-12188225562 | C29: 45883 | D29: SANTA YSABEL FIGUEREO BAUTISTA | E29: =VLOOKUP(DataOld!$B29,DATA!B:H,7,FALSE) -> #N/A | F29: =DataOld!$D29=DataOld!$E29 -> #N/A | G29: =VLOOKUP(DataOld!$B29,DATA!B:G,6,FALSE) -> #N/A | H29: 40224593570 | I29: =DataOld!$H29=DataOld!$G29 -> #N/A | J29: 155-OFICINA SAN CRISTOBAL | K29: SAN CRISTOBAL;Cambita Garabitos;El cajon | L29: San Cristobal-Cambita Garabitos-Cambita Garabitos-El cajon -Primera -1-ICI-Secretara-Frente a la bomba TLC bomba-C-8493790665-0-C-8299296460-0-0-0 | M29: SAN CRISTOBAL | N29: Cambita Garabitos | O29: Cambita Garabitos | P29: El cajon | Q29: primera | R29: 1 | S29: ICI | T29: Secretara | U29: Frente a la bomba TLC bomba | V29: C | W29: 8493790665 | X29: 0 | Y29: C | Z29: 8299296460 | AA29: 0 | AB29: 0 | AC29: 0 | AE29: 45883.529 | AG29: TD- ENTREGADO
A30: 45883 | B30: 4-12188618142 | C30: 45883 | D30: WANDER MADIER CABRERA SUERO | E30: =VLOOKUP(DataOld!$B30,DATA!B:H,7,FALSE) -> #N/A | F30: =DataOld!$D30=DataOld!$E30 -> #N/A | G30: =VLOOKUP(DataOld!$B30,DATA!B:G,6,FALSE) -> #N/A | H30: 40222594232 | I30: =DataOld!$H30=DataOld!$G30 -> #N/A | J30: 158-OFICINA PIISA HAINA | K30: SAN CRISTOBAL;SAN CRISTOBAL;Pueblo Nuevo | L30: SAN CRISTOBAL-SAN CRISTOBAL-SAN CRISTOBAL-Pueblo Nuevo-Proyecto 15-1-0-0-Cerca del Colmado Los Muchac-C-8294385418-0-C-8295696616-0-C-0-0 | M30: SAN CRISTOBAL | N30: SAN CRISTOBAL | O30: SAN CRISTOBAL | P30: Pueblo Nuevo | Q30: Proyecto 15 | R30: 1 | S30: 0 | T30: 0 | U30: Cerca del Colmado Los Muchac | V30: C | W30: 8294385418 | X30: 0 | Y30: C | Z30: 8295696616 | AA30: 0 | AB30: C | AC30: 0 | AD30: 0 | AE30: 45883.556 | AG30: TD- ENTREGADO
A31: 45883 | B31: 4-12188524552 | C31: 45883 | D31: YEREINID PEGUERO RIJO | E31: =VLOOKUP(DataOld!$B31,DATA!B:H,7,FALSE) -> #N/A | F31: =DataOld!$D31=DataOld!$E31 -> #N/A | G31: =VLOOKUP(DataOld!$B31,DATA!B:G,6,FALSE) -> #N/A | H31: 40235358294 | I31: =DataOld!$H31=DataOld!$G31 -> #N/A | J31: 273-OFICINA CAMPUS UCE SPM | K31: SAN PEDRO DE MACORIS;SAN PEDRO MACORIS;hatos de san pedro | L31: SAN PEDRO DE MACORIS-SAN PEDRO MACORIS-SAN PEDRO DE MACORIS-hatos de san pedro-1ra-27-EDF Angela-4B-entrando por donde jocesito-C-8296950870-0-C-8297635918-0-C-0-0 | M31: SAN PEDRO DE MACORIS | N31: SAN PEDRO MACORIS | O31: SAN PEDRO DE MACORIS | P31: hatos de san pedro | Q31: 1ra | R31: 27 | S31: EDF Angela | T31: 4B | U31: entrando por donde jocesito | V31: C | W31: 8296950870 | X31: 0 | Y31: C | Z31: 8297635918 | AA31: 0 | AB31: C | AC31: 0 | AD31: 0 | AE31: 45883.54 | AG31: TD- ENTREGADO
A32: 45883 | B32: 4-12189026642 | C32: 45883 | D32: PAMELA MARTINEZ URENA | E32: =VLOOKUP(DataOld!$B32,DATA!B:H,7,FALSE) -> #N/A | F32: =DataOld!$D32=DataOld!$E32 -> #N/A | G32: =VLOOKUP(DataOld!$B32,DATA!B:G,6,FALSE) -> #N/A | H32: 40209123575 | I32: =DataOld!$H32=DataOld!$G32 -> #N/A | J32: Centro Digital Popular | K32: SANTIAGO;SANTIAGO;Arenoso | L32: Santiago-Santiago-Santiago-Arenoso-Calle los Rodriguez -56-0-0-Por la escuela Joseflores-C-8095048161-0-C-8099942885-0-0-0 | M32: SANTIAGO | N32: SANTIAGO | O32: SANTIAGO | P32: Arenoso | Q32: Calle los Rodriguez | R32: 56 | S32: 0 | T32: 0 | U32: Por la escuela Joseflores | V32: C | W32: 8095048161 | X32: 0 | Y32: C | Z32: 8099942885 | AA32: 0 | AB32: 0 | AC32: 0 | AE32: 45883.602 | AG32: TD- RETIRADA EN OFICINA | AH32: CLIENTA INDICO QUE DESEARIA PASAR POR EL BANCO! | AL32: 8099942885 # ES DE NICOLLE SU HERMANA LA CUAL LA VA A RECIBIR Y ME ENVIARA LA UB POR WSS / UBICACION ENVIADA
A33: 45883 | B33: 4-12189115662 | C33: 45883 | D33: JEAN LUIS ENCARNACION BAEZ | E33: =VLOOKUP(DataOld!$B33,DATA!B:H,7,FALSE) -> #N/A | F33: =DataOld!$D33=DataOld!$E33 -> #N/A | G33: =VLOOKUP(DataOld!$B33,DATA!B:G,6,FALSE) -> #N/A | H33: 40206066581 | I33: =DataOld!$H33=DataOld!$G33 -> #N/A | J33: Centro Digital Popular | K33: SANTIAGO;SANTIAGO;Cerro alto | L33: Santiago-Santiago-Santiago-Cerro alto-Calle B-20-Reaidencial Polanco -202B-La misma Calle del Colegio -C-8492725586-0-C-8096263946-0-0-0 | M33: SANTIAGO | N33: SANTIAGO | O33: SANTIAGO | P33: Cerro alto | Q33: Calle B | R33: 20 | S33: Reaidencial Polanco | T33: 202B | U33: La misma Calle del Colegio | V33: C | W33: 8492725586 | X33: 0 | Y33: C | Z33: 8096263946 | AA33: 0 | AB33: 0 | AC33: 0 | AE33: 45883.611 | AG33: TD- ENTREGADO
A34: 45883 | B34: 4-12187803972 | C34: 45883 | D34: ENMANUEL ALEXANDER PEREZ VARGAS | E34: =VLOOKUP(DataOld!$B34,DATA!B:H,7,FALSE) -> #N/A | F34: =DataOld!$D34=DataOld!$E34 -> #N/A | G34: =VLOOKUP(DataOld!$B34,DATA!B:G,6,FALSE) -> #N/A | H34: 40208835823 | I34: =DataOld!$H34=DataOld!$G34 -> #N/A | J34: 242-OFICINA LAS COLINAS, STGO. | K34: SANTIAGO;SANTIAGO;padre las casas | L34: SANTIAGO-SANTIAGO-SANTIAGO-padre las casas-penetracion-91-castro-1-llamar-C-8498169462-0-C-8492075174-0-C-0-0 | M34: SANTIAGO | N34: SANTIAGO | O34: SANTIAGO | P34: padre las casas | Q34: penetracion | R34: 91 | S34: castro | T34: 1 | U34: llamar | V34: C | W34: 8498169462 | X34: 0 | Y34: C | Z34: 8492075174 | AA34: 0 | AB34: C | AC34: 0 | AD34: 0 | AE34: 45883.497 | AG34: TD- ENTREGADO
A35: 45883 | B35: 4-12187539232 | C35: 45883 | D35: MAXIMO JAVIER HIRALDO DE LEON | E35: =VLOOKUP(DataOld!$B35,DATA!B:H,7,FALSE) -> #N/A | F35: =DataOld!$D35=DataOld!$E35 -> #N/A | G35: =VLOOKUP(DataOld!$B35,DATA!B:G,6,FALSE) -> #N/A | H35: 40211009481 | I35: =DataOld!$H35=DataOld!$G35 -> #N/A | J35: 246-OFICINA ZONA FRANCA, STGO. | K35: SANTIAGO;SANTIAGO;Santiago | L35: Santiago-Santiago-Santiago-Santiago -Principal -1-Tabacalera fuente -Lingstica-Arturo fuente -C-8293597287-0-C-8292136769-0-0-0 | M35: SANTIAGO | N35: SANTIAGO | O35: SANTIAGO | P35: Santiago | Q35: Principal | R35: 1 | S35: Tabacalera fuente | T35: Lingstica | U35: Arturo fuente | V35: C | W35: 8293597287 | X35: 0 | Y35: C | Z35: 8292136769 | AA35: 0 | AB35: 0 | AC35: 0 | AE35: 45883.518 | AG35: TD- ENTREGADO
A36: 45883 | B36: 4-12189180822 | C36: 45883 | D36: LUZ YAMEL CRUZ GERMAN | E36: =VLOOKUP(DataOld!$B36,DATA!B:H,7,FALSE) -> #N/A | F36: =DataOld!$D36=DataOld!$E36 -> #N/A | G36: =VLOOKUP(DataOld!$B36,DATA!B:G,6,FALSE) -> #N/A | H36: 40210388100 | I36: =DataOld!$H36=DataOld!$G36 -> #N/A | J36: 464-OCCIDENTALL MALL | K36: SANTO DOMINGO;SANTO DOMINGO OESTE;San Miguel | L36: Santo Domingo-Santo Domingo Oeste-Santo Domingo Oeste-San Miguel -Antonia Perez -20-0-0-Entrar por el colmado angel -C-8097853359-0-C-8296011322-0-0-0 | M36: SANTO DOMINGO | N36: SANTO DOMINGO OESTE | O36: SANTO DOMINGO OESTE | P36: San Miguel | Q36: Antonia Perez | R36: 20 | S36: 0 | T36: 0 | U36: Entrar por el colmado angel | V36: C | W36: 8097853359 | X36: 0 | Y36: C | Z36: 8296011322 | AA36: 0 | AB36: 0 | AC36: 0 | AE36: 45883.619 | AG36: TD- ENTREGADO
A37: 45883 | B37: 4-12187853772 | C37: 45883 | D37: OSVALDO SAMUEL TURBI VALDEZ | E37: =VLOOKUP(DataOld!$B37,DATA!B:H,7,FALSE) -> #N/A | F37: =DataOld!$D37=DataOld!$E37 -> #N/A | G37: =VLOOKUP(DataOld!$B37,DATA!B:G,6,FALSE) -> #N/A | H37: 40225004999 | I37: =DataOld!$H37=DataOld!$G37 -> #N/A | J37: 317-OFICINA CARREFOUR | K37: SANTO DOMINGO;SANTO DOMINGO OESTE;Pantoja | L37: SANTO DOMINGO-SANTO DOMINGO OESTE-SANTO DOMINGO OESTE-Pantoja-Don Gregorio 3 Man A-41-0-0-Entrando por el Ayuntamiento-C-8298177792-0-C-8494597792-0-C-0-0 | M37: SANTO DOMINGO | N37: SANTO DOMINGO OESTE | O37: SANTO DOMINGO OESTE | P37: Pantoja | Q37: Don Gregorio 3 Man A | R37: 41 | S37: 0 | T37: 0 | U37: Entrando por el Ayuntamiento | V37: C | W37: 8298177792 | X37: 0 | Y37: C | Z37: 8494597792 | AA37: 0 | AB37: C | AC37: 0 | AD37: 0 | AE37: 45883.5 | AG37: TD- ENTREGADO
A38: 45883 | B38: 4-12188043972 | C38: 45883 | D38: ADAMS ISMAEL ACEVEDO POLANCO | E38: =VLOOKUP(DataOld!$B38,DATA!B:H,7,FALSE) -> #N/A | F38: =DataOld!$D38=DataOld!$E38 -> #N/A | G38: =VLOOKUP(DataOld!$B38,DATA!B:G,6,FALSE) -> #N/A | H38: 40202043351 | I38: =DataOld!$H38=DataOld!$G38 -> #N/A | J38: 383-OFICINA JUMBO LUPERON | K38: SANTO DOMINGO;LOS ALCARRIZOS;barrio 24 de abril | L38: SANTO DOMINGO-LOS ALCARRIZOS-LOS ALCARRIZOS-barrio 24 de abril-calle 2 casa 24-24-0-0-alcarrizos cerca de la duart-C-8099755492-0-C-8097200939-0-C-0-0 | M38: SANTO DOMINGO | N38: LOS ALCARRIZOS | O38: LOS ALCARRIZOS | P38: barrio 24 de abril | Q38: calle 2 casa 24 | R38: 24 | S38: 0 | T38: 0 | U38: alcarrizos cerca de la duart | V38: C | W38: 8099755492 | X38: 0 | Y38: C | Z38: 8097200939 | AA38: 0 | AB38: C | AC38: 0 | AD38: 0 | AE38: 45883.516 | AG38: TD- ENTREGADO
A39: 45883 | B39: 4-12187835962 | C39: 45883 | D39: YERALDIN MILIANO DE ARIAS | E39: =VLOOKUP(DataOld!$B39,DATA!B:H,7,FALSE) -> #N/A | F39: =DataOld!$D39=DataOld!$E39 -> #N/A | G39: =VLOOKUP(DataOld!$B39,DATA!B:G,6,FALSE) -> #N/A | H39: 06800508688 | I39: =DataOld!$H39=DataOld!$G39 -> #N/A | J39: 256-OFICINA BONAO | K39: SANTO DOMINGO;PEDRO BRAND;La guayiga | L39: Santo Domingo-Pedro Brand-Pedro Brand-La guayiga-Autopista Duarte Km -13-Arion Dominicana-Recepcin-Frente Res Pablo Mella-C-8099965543-0-T-8093383747-0000-0-0 | M39: SANTO DOMINGO | N39: PEDRO BRAND | O39: PEDRO BRAND | P39: La guayiga | Q39: Autopista Duarte Km | R39: 13 | S39: Arion Dominicana | T39: Recepcin | U39: Frente Res Pablo Mella | V39: C | W39: 8099965543 | X39: 0 | Y39: T | Z39: 8093383747 | AA39: 0000 | AB39: 0 | AC39: 0 | AE39: 45883.496 | AG39: TD- ENTREGADO
A40: 45883 | B40: 4-12189114782 | C40: 45883 | D40: JOSE MIGUEL CAMPUSANO ARIAS | E40: =VLOOKUP(DataOld!$B40,DATA!B:H,7,FALSE) -> #N/A | F40: =DataOld!$D40=DataOld!$E40 -> #N/A | G40: =VLOOKUP(DataOld!$B40,DATA!B:G,6,FALSE) -> #N/A | H40: 00119318913 | I40: =DataOld!$H40=DataOld!$G40 -> #N/A | J40: 140-OFICINA EL PORTAL | K40: SANTO DOMINGO;PEDRO BRAND;parque industrial | L40: SANTO DOMINGO-PEDRO BRAND-PEDRO BRAND-parque industrial-duarte-2-frito lay-logistica-mixing center-C-8498158576-0-T-8492483608-0-C-0-0 | M40: SANTO DOMINGO | N40: PEDRO BRAND | O40: PEDRO BRAND | P40: parque industrial | Q40: duarte | R40: 2 | S40: frito lay | T40: logistica | U40: mixing center | V40: C | W40: 8498158576 | X40: 0 | Y40: T | Z40: 8492483608 | AA40: 0 | AB40: C | AC40: 0 | AD40: 0 | AE40: 45883.611 | AG40: TD- ENTREGADO
A41: 45883 | B41: 4-12189147072 | C41: 45883 | D41: TEODORO JIRON MATIA | E41: =VLOOKUP(DataOld!$B41,DATA!B:H,7,FALSE) -> #N/A | F41: =DataOld!$D41=DataOld!$E41 -> #N/A | G41: =VLOOKUP(DataOld!$B41,DATA!B:G,6,FALSE) -> #N/A | H41: 00118667229 | I41: =DataOld!$H41=DataOld!$G41 -> #N/A | J41: 141-OFICINA TORRE EMPRESARIAL 27 DE FEBRERO | K41: SANTO DOMINGO;SANTO DOMINGO ESTE;Borojol San Isidro | L41: SANTO DOMINGO-SANTO DOMINGO ESTE-SAN LUIS-Borojol San Isidro-Carretera Mella km18-0-CD Plaza Lama-CD01-Frente al control de autobus-C-8094340827-0-C-8498282908-0-C-0-0 | M41: SANTO DOMINGO | N41: SANTO DOMINGO ESTE | O41: SAN LUIS | P41: Borojol San Isidro | Q41: Carretera Mella km18 | R41: 0 | S41: CD Plaza Lama | T41: CD01 | U41: Frente al control de autobus | V41: C | W41: 8094340827 | X41: 0 | Y41: C | Z41: 8498282908 | AA41: 0 | AB41: C | AC41: 0 | AD41: 0 | AE41: 45883.618 | AG41: TD- ENTREGADO
A42: 45883 | B42: 4-12189147272 | C42: 45883 | D42: VISAYRA ELISABETH PERALTA VILLEGAS | E42: =VLOOKUP(DataOld!$B42,DATA!B:H,7,FALSE) -> #N/A | F42: =DataOld!$D42=DataOld!$E42 -> #N/A | G42: =VLOOKUP(DataOld!$B42,DATA!B:G,6,FALSE) -> #N/A | H42: 02601444298 | I42: =DataOld!$H42=DataOld!$G42 -> #N/A | J42: 182-OFICINA CORAL MALL | K42: SANTO DOMINGO;SANTO DOMINGO ESTE;Alma Rosa II | L42: Santo Domingo-Santo Domingo Este-Santo Domingo Este-Alma Rosa II-Club de leones 196-196-BSG computer y electronic-Gerente-Entre la 20 y la san vicente-C-8094133258-0-C-8099044417-0-0-0 | M42: SANTO DOMINGO | N42: SANTO DOMINGO ESTE | O42: SANTO DOMINGO ESTE | P42: Alma Rosa II | Q42: Club de leones 196 | R42: 196 | S42: BSG computer y electronic | T42: Gerente | U42: Entre la 20 y la san vicente | V42: C | W42: 8094133258 | X42: 0 | Y42: C | Z42: 8099044417 | AA42: 0 | AB42: 0 | AC42: 0 | AE42: 45883.62 | AG42: TD- ENTREGADO
A43: 45883 | B43: 4-12188613592 | C43: 45883 | D43: ROBERTO CARLOS NUNEZ JIMENEZ | E43: =VLOOKUP(DataOld!$B43,DATA!B:H,7,FALSE) -> #N/A | F43: =DataOld!$D43=DataOld!$E43 -> #N/A | G43: =VLOOKUP(DataOld!$B43,DATA!B:G,6,FALSE) -> #N/A | H43: 40229964669 | I43: =DataOld!$H43=DataOld!$G43 -> #N/A | J43: Centro Digital Popular | K43: SANTO DOMINGO;SANTO DOMINGO ESTE;Alma Rosa segunda | L43: Santo Domingo-Santo Domingo Este-Santo Domingo Este-Alma Rosa segunda -Costa Rica 299-500-0-0-Entra en callejon part atras-R-8095967916-0-C-8092854638-0-0-0 | M43: SANTO DOMINGO | N43: SANTO DOMINGO ESTE | O43: SANTO DOMINGO ESTE | P43: Alma Rosa segunda | Q43: Costa Rica 299 | R43: 500 | S43: 0 | T43: 0 | U43: Entra en callejon part atras | V43: R | W43: 8095967916 | X43: 0 | Y43: C | Z43: 8092854638 | AA43: 0 | AB43: 0 | AC43: 0 | AE43: 45883.55 | AG43: TD- ENTREGADO
A44: 45883 | B44: 4-12188913262 | C44: 45883 | D44: CRISTOPHER JESUS JESUS CALDERON | E44: =VLOOKUP(DataOld!$B44,DATA!B:H,7,FALSE) -> #N/A | F44: =DataOld!$D44=DataOld!$E44 -> #N/A | G44: =VLOOKUP(DataOld!$B44,DATA!B:G,6,FALSE) -> #N/A | H44: 40224343265 | I44: =DataOld!$H44=DataOld!$G44 -> #N/A | J44: 141-OFICINA TORRE EMPRESARIAL 27 DE FEBRERO | K44: SANTO DOMINGO;SANTO DOMINGO ESTE;Invicea | L44: Santo Domingo-Santo Domingo Este-Santo Domingo Este-Invicea-Av la pista -10-5-202-Residencial Lorett -C-8298038281-0-C-8496517227-0-0-0 | M44: SANTO DOMINGO | N44: SANTO DOMINGO ESTE | O44: SANTO DOMINGO ESTE | P44: Invicea | Q44: Av la pista | R44: 10 | S44: 5 | T44: 202 | U44: Residencial Lorett | V44: C | W44: 8298038281 | X44: 0 | Y44: C | Z44: 8496517227 | AA44: 0 | AB44: 0 | AC44: 0 | AE44: 45883.595 | AG44: TD- ENTREGADO
A45: 45883 | B45: 4-12188489152 | C45: 45883 | D45: KEILA DE OLEO | E45: =VLOOKUP(DataOld!$B45,DATA!B:H,7,FALSE) -> #N/A | F45: =DataOld!$D45=DataOld!$E45 -> #N/A | G45: =VLOOKUP(DataOld!$B45,DATA!B:G,6,FALSE) -> #N/A | H45: 40227218449 | I45: =DataOld!$H45=DataOld!$G45 -> #N/A | J45: 202-OFICINA MELLA | K45: SANTO DOMINGO;SANTO DOMINGO ESTE;los mina sur | L45: Santo Domingo-Santo Domingo Este-Santo Domingo Este-Los mina sur -Altagracia-106-Ana Isabel II-302-Colmado Soto-C-8498448407-0-R-8095915410-0-0-0 | M45: SANTO DOMINGO | N45: SANTO DOMINGO ESTE | O45: SANTO DOMINGO ESTE | P45: los mina sur | Q45: Altagracia | R45: 106 | S45: Ana Isabel II | T45: 302 | U45: Colmado Soto | V45: C | W45: 8498448407 | X45: 0 | Y45: R | Z45: 8095915410 | AA45: 0 | AB45: 0 | AC45: 0 | AE45: 45883.545 | AG45: TD- ENTREGADO
A46: 45883 | B46: 4-12188743802 | C46: 45883 | D46: YAFREISE RAMONA DUARTE TAVERAS | E46: =VLOOKUP(DataOld!$B46,DATA!B:H,7,FALSE) -> #N/A | F46: =DataOld!$D46=DataOld!$E46 -> #N/A | G46: =VLOOKUP(DataOld!$B46,DATA!B:G,6,FALSE) -> #N/A | H46: 22301797464 | I46: =DataOld!$H46=DataOld!$G46 -> #N/A | J46: 324-OFICINA PLAZA CHARLES SUMMER | K46: SANTO DOMINGO;SANTO DOMINGO ESTE;los mina sur | L46: SANTO DOMINGO-SANTO DOMINGO ESTE-SANTO DOMINGO ESTE-los mina sur-C 5D-35-0-0-colegio la milagrosa-C-8494422314-0-C-8094133692-0-C-0-0 | M46: SANTO DOMINGO | N46: SANTO DOMINGO ESTE | O46: SANTO DOMINGO ESTE | P46: los mina sur | Q46: C 5D | R46: 35 | S46: 0 | T46: 0 | U46: colegio la milagrosa | V46: C | W46: 8494422314 | X46: 0 | Y46: C | Z46: 8094133692 | AA46: 0 | AB46: C | AC46: 0 | AD46: 0 | AE46: 45883.574 | AG46: TD- ENTREGADO
A47: 45883 | B47: 4-12188721162 | C47: 45883 | D47: ANAISY ROBLES MATEO | E47: =VLOOKUP(DataOld!$B47,DATA!B:H,7,FALSE) -> #N/A | F47: =DataOld!$D47=DataOld!$E47 -> #N/A | G47: =VLOOKUP(DataOld!$B47,DATA!B:G,6,FALSE) -> #N/A | H47: 40229448416 | I47: =DataOld!$H47=DataOld!$G47 -> #N/A | J47: Centro Digital Popular | K47: SANTO DOMINGO;SANTO DOMINGO ESTE;los mina sur | L47: Santo Domingo-Santo Domingo Este-Santo Domingo Este-Los mina sur-Geraldo Mena -28-0-0-0-C-8096347243-0-C-8294532462-0-0-0 | M47: SANTO DOMINGO | N47: SANTO DOMINGO ESTE | O47: SANTO DOMINGO ESTE | P47: los mina sur | Q47: Geraldo Mena | R47: 28 | S47: 0 | T47: 0 | U47: 0 | V47: C | W47: 8096347243 | X47: 0 | Y47: C | Z47: 8294532462 | AA47: 0 | AB47: 0 | AC47: 0 | AE47: 45883.573 | AG47: TD- ENTREGADO
A48: 45883 | B48: 4-12189215572 | C48: 45883 | D48: MACCTEW ALEXANDER ALVAREZ MAGO | E48: =VLOOKUP(DataOld!$B48,DATA!B:H,7,FALSE) -> #N/A | F48: =DataOld!$D48=DataOld!$E48 -> #N/A | G48: =VLOOKUP(DataOld!$B48,DATA!B:G,6,FALSE) -> #N/A | H48: 40234808760 | I48: =DataOld!$H48=DataOld!$G48 -> #N/A | J48: Centro Digital Popular | K48: SANTO DOMINGO;SANTO DOMINGO ESTE;prado oriental | L48: Santo Domingo-Santo Domingo Este-Santo Domingo Este-Prado oriental-Calle hetor b jimene-52-Elpedrobarber-1-Farmacia greliz -C-8494805663-0-C-8093547419-0-T-8299888497-1 | M48: SANTO DOMINGO | N48: SANTO DOMINGO ESTE | O48: SANTO DOMINGO ESTE | P48: prado oriental | Q48: Calle hetor b jimene | R48: 52 | S48: elpedrobarber | T48: 1 | U48: farmacia greliz | V48: C | W48: 8494805663 | X48: 0 | Y48: C | Z48: 8093547419 | AA48: 0 | AB48: T | AC48: 8299888497 | AD48: 1 | AE48: 45883.62 | AG48: TD- ENTREGADO
A49: 45883 | B49: 4-12189146462 | C49: 45883 | D49: HERIBERTO MIGUEL FRIAS VOLQUEZ | E49: =VLOOKUP(DataOld!$B49,DATA!B:H,7,FALSE) -> #N/A | F49: =DataOld!$D49=DataOld!$E49 -> #N/A | G49: =VLOOKUP(DataOld!$B49,DATA!B:G,6,FALSE) -> #N/A | H49: 40213009307 | I49: =DataOld!$H49=DataOld!$G49 -> #N/A | J49: Centro Digital Popular | K49: SANTO DOMINGO;SANTO DOMINGO ESTE;prado oriental | L49: SANTO DOMINGO-SANTO DOMINGO ESTE-SANTO DOMINGO ESTE-prado oriental-hetor b jimenes-52-elpedrobarber-1-farmacia greliz-C-8493931525-0-C-8094058497-0-T-8299888497-1 | M49: SANTO DOMINGO | N49: SANTO DOMINGO ESTE | O49: SANTO DOMINGO ESTE | P49: prado oriental | Q49: hetor b jimenes | R49: 52 | S49: elpedrobarber | T49: 1 | U49: farmacia greliz | V49: C | W49: 8493931525 | X49: 0 | Y49: C | Z49: 8094058497 | AA49: 0 | AB49: T | AC49: 8299888497 | AD49: 1 | AE49: 45883.612 | AG49: TD- ENTREGADO
A50: 45883 | B50: 4-12189063902 | C50: 45883 | D50: JEAN ALEXANDER MEDINA RODRIGUEZ | E50: =VLOOKUP(DataOld!$B50,DATA!B:H,7,FALSE) -> #N/A | F50: =DataOld!$D50=DataOld!$E50 -> #N/A | G50: =VLOOKUP(DataOld!$B50,DATA!B:G,6,FALSE) -> #N/A | H50: 40224012209 | I50: =DataOld!$H50=DataOld!$G50 -> #N/A | J50: 209-OFICINA CHARLES DE GAULLE | K50: SANTO DOMINGO;SANTO DOMINGO ESTE;villa Eloisa | L50: SANTO DOMINGO-SANTO DOMINGO ESTE-SANTO DOMINGO ESTE-villa Eloisa-calle proyecto 8-11-0-0-al lado de la iglesia-C-8495187686-0-T-8297874250-0-C-8494089032-0 | M50: SANTO DOMINGO | N50: SANTO DOMINGO ESTE | O50: SANTO DOMINGO ESTE | P50: villa Eloisa | Q50: calle proyecto 8 | R50: 11 | S50: 0 | T50: 0 | U50: al lado de la iglesia | V50: C | W50: 8495187686 | X50: 0 | Y50: T | Z50: 8297874250 | AA50: 0 | AB50: C | AC50: 8494089032 | AD50: 0 | AE50: 45883.606 | AG50: TD- ENTREGADO
A51: 45883 | B51: 4-12188882142 | C51: 45883 | D51: YISSEL ALEXANDRA RAMOS ROSARIO | E51: =VLOOKUP(DataOld!$B51,DATA!B:H,7,FALSE) -> #N/A | F51: =DataOld!$D51=DataOld!$E51 -> #N/A | G51: =VLOOKUP(DataOld!$B51,DATA!B:G,6,FALSE) -> #N/A | H51: 05300459046 | I51: =DataOld!$H51=DataOld!$G51 -> #N/A | J51: 355-OFICINA MULTICENTRO ORIENTAL | K51: SANTO DOMINGO;SANTO DOMINGO ESTE;Villa tropicalia | L51: Santo Domingo-Santo Domingo Este-Santo Domingo Este-Villa tropicalia -Manuela Diez -7-0-0-Por el control de la omsa -C-8098483637-0-C-8295622334-0-0-0 | M51: SANTO DOMINGO | N51: SANTO DOMINGO ESTE | O51: SANTO DOMINGO ESTE | P51: Villa tropicalia | Q51: Manuela Diez | R51: 7 | S51: 0 | T51: 0 | U51: Por el control de la omsa | V51: C | W51: 8098483637 | X51: 0 | Y51: C | Z51: 8295622334 | AA51: 0 | AB51: 0 | AC51: 0 | AE51: 45883.593 | AG51: TD- ENTREGADO
A52: 45883 | B52: 4-12188023652 | C52: 45883 | D52: EUDIS GUILLEN RAMIREZ | E52: =VLOOKUP(DataOld!$B52,DATA!B:H,7,FALSE) -> #N/A | F52: =DataOld!$D52=DataOld!$E52 -> #N/A | G52: =VLOOKUP(DataOld!$B52,DATA!B:G,6,FALSE) -> #N/A | H52: 40227319304 | I52: =DataOld!$H52=DataOld!$G52 -> #N/A | J52: 205-OFICINA VILLA MELLA | K52: SANTO DOMINGO;SANTO DOMINGO NORTE;Carlos alvarez | L52: SANTO DOMINGO-SANTO DOMINGO NORTE-SANTO DOMINGO NORTE-carlos alvarez-calle 27-30-0-0-casa 30 azul 3 niveles-C-8099179309-0-R-8092941265-0-C-0-0 | M52: SANTO DOMINGO | N52: SANTO DOMINGO NORTE | O52: SANTO DOMINGO NORTE | P52: Carlos alvarez | Q52: calle 27 | R52: 30 | S52: 0 | T52: 0 | U52: casa 30 azul 3 niveles | V52: C | W52: 8099179309 | X52: 0 | Y52: R | Z52: 8092941265 | AA52: 0 | AB52: C | AC52: 0 | AD52: 0 | AE52: 45883.512 | AG52: TD- ENTREGADO
A53: 45883 | B53: 4-12188177242 | C53: 45883 | D53: RAFAEL IGNACIO TAPIA VALDEZ | E53: =VLOOKUP(DataOld!$B53,DATA!B:H,7,FALSE) -> #N/A | F53: =DataOld!$D53=DataOld!$E53 -> #N/A | G53: =VLOOKUP(DataOld!$B53,DATA!B:G,6,FALSE) -> #N/A | H53: 40200552905 | I53: =DataOld!$H53=DataOld!$G53 -> #N/A | J53: 166-OFICINA VILLA MELLA HERMANAS MIRABAL | K53: SANTO DOMINGO;SANTO DOMINGO NORTE;guaricano | L53: SANTO DOMINGO-SANTO DOMINGO NORTE-SANTO DOMINGO NORTE-guaricano-Juan Pablo Duarte-17-0-0-philovocalmusic en el mapa-C-8295705963-0-C-8093023744-0-C-0-0 | M53: SANTO DOMINGO | N53: SANTO DOMINGO NORTE | O53: SANTO DOMINGO NORTE | P53: guaricano | Q53: Juan Pablo Duarte | R53: 17 | S53: 0 | T53: 0 | U53: philovocalmusic en el mapa | V53: C | W53: 8295705963 | X53: 0 | Y53: C | Z53: 8093023744 | AA53: 0 | AB53: C | AC53: 0 | AD53: 0 | AE53: 45883.543 | AG53: TD- ENTREGADO
A54: 45883 | B54: 4-12188086532 | C54: 45883 | D54: JOSE CONFESOR BRITO POLONIA | E54: =VLOOKUP(DataOld!$B54,DATA!B:H,7,FALSE) -> #N/A | F54: =DataOld!$D54=DataOld!$E54 -> #N/A | G54: =VLOOKUP(DataOld!$B54,DATA!B:G,6,FALSE) -> #N/A | H54: 08700019907 | I54: =DataOld!$H54=DataOld!$G54 -> #N/A | J54: 142-OFICINA NUÑEZ DE CACERES | K54: SANTO DOMINGO;SANTO DOMINGO NORTE;Urbanizacion Santa C | L54: SANTO DOMINGO-SANTO DOMINGO NORTE-SANTO DOMINGO NORTE-Urbanizacion Santa C-calle segunda-12-0-0-0-C-8098600505-0-C-8098625856-0-C-0-0 | M54: SANTO DOMINGO | N54: SANTO DOMINGO NORTE | O54: SANTO DOMINGO NORTE | P54: Urbanizacion Santa C | Q54: calle segunda | R54: 12 | S54: 0 | T54: 0 | U54: 0 | V54: C | W54: 8098600505 | X54: 0 | Y54: C | Z54: 8098625856 | AA54: 0 | AB54: C | AC54: 0 | AD54: 0 | AE54: 45883.518 | AG54: TD- ENTREGADO
A55: 45883 | B55: 4-12187795972 | C55: 45883 | D55: MANUEL ALEJANDRO LUGO GERMAN | E55: =VLOOKUP(DataOld!$B55,DATA!B:H,7,FALSE) -> #N/A | F55: =DataOld!$D55=DataOld!$E55 -> #N/A | G55: =VLOOKUP(DataOld!$B55,DATA!B:G,6,FALSE) -> #N/A | H55: 40244121212 | I55: =DataOld!$H55=DataOld!$G55 -> #N/A | J55: Centro Digital Popular | K55: SANTO DOMINGO;SANTO DOMINGO OESTE;Herrera | L55: Santo Domingo-Santo Domingo Oeste-Santo Domingo Oeste-Herrera -Calle 3 -03-Industrial electric -Noo -0-C-8099073621-0-C-8296363351-0-0-0 | M55: SANTO DOMINGO | N55: SANTO DOMINGO OESTE | O55: SANTO DOMINGO OESTE | P55: Herrera | Q55: Calle 3 | R55: 03 | S55: Industrial electric | T55: Noo | U55: 0 | V55: C | W55: 8099073621 | X55: 0 | Y55: C | Z55: 8296363351 | AA55: 0 | AB55: 0 | AC55: 0 | AE55: 45883.491 | AG55: TD- ENTREGADO
A56: 45883 | B56: 4-12188451342 | C56: 45883 | D56: KATHIANA BOUBERT | E56: =VLOOKUP(DataOld!$B56,DATA!B:H,7,FALSE) -> #N/A | F56: =DataOld!$D56=DataOld!$E56 -> #N/A | G56: =VLOOKUP(DataOld!$B56,DATA!B:G,6,FALSE) -> #N/A | H56: 40242365233 | I56: =DataOld!$H56=DataOld!$G56 -> #N/A | J56: 145-OFICINA PASEO 27 | K56: SANTO DOMINGO;SANTO DOMINGO OESTE;Herrera | L56: SANTO DOMINGO-SANTO DOMINGO OESTE-SANTO DOMINGO OESTE-Herrera-Calle Puerto Rico-26-0-0-Al lado de la botica comunit-C-8096667714-0-C-8096280999-0-C-0-0 | M56: SANTO DOMINGO | N56: SANTO DOMINGO OESTE | O56: SANTO DOMINGO OESTE | P56: Herrera | Q56: Calle Puerto Rico | R56: 26 | S56: 0 | T56: 0 | U56: Al lado de la botica comunit | V56: C | W56: 8096667714 | X56: 0 | Y56: C | Z56: 8096280999 | AA56: 0 | AB56: C | AC56: 0 | AD56: 0 | AE56: 45883.529 | AG56: TD- ENTREGADO
A57: 45883 | B57: 4-12187716742 | C57: 45883 | D57: ALBA LUNA GARCIA BERROA | E57: =VLOOKUP(DataOld!$B57,DATA!B:H,7,FALSE) -> #N/A | F57: =DataOld!$D57=DataOld!$E57 -> #N/A | G57: =VLOOKUP(DataOld!$B57,DATA!B:G,6,FALSE) -> #N/A | H57: 40231051612 | I57: =DataOld!$H57=DataOld!$G57 -> #N/A | J57: 135-OFICINA TORRE POPULAR | K57: Distrito Nacional;Santo Domingo;los Peralejos | L57: DISTRITO NACIONAL-SANTO DOMINGO-SANTO DOMINGO DE GUZMAN-los Peralejos-29-10-si-1-al lado de una fantasia-C-8298919800-0-C-8298948020-0-C-0-0 | M57: Distrito Nacional | N57: Santo Domingo | O57: Santo Domingo De Guzman | P57: los Peralejos | Q57: 29 | R57: 10 | S57: si | T57: 1 | U57: al lado de una fantasia | V57: C | W57: 8298919800 | X57: 0 | Y57: C | Z57: 8298948020 | AA57: 0 | AB57: C | AC57: 0 | AD57: 0 | AE57: 45883.485 | AG57: TD- ENTREGADO
A58: 45883 | B58: 4-12187444442 | C58: 45883 | D58: DILCY MARID PIMENTEL HURTADO | E58: =VLOOKUP(DataOld!$B58,DATA!B:H,7,FALSE) -> #N/A | F58: =DataOld!$D58=DataOld!$E58 -> #N/A | G58: =VLOOKUP(DataOld!$B58,DATA!B:G,6,FALSE) -> #N/A | H58: 40222704658 | I58: =DataOld!$H58=DataOld!$G58 -> #N/A | J58: 136-OFICINA CENTRO DE LOS HEROES | K58: Distrito Nacional;Santo Domingo;Atala | L58: Distrito Nacional-Santo Domingo-Santo Domingo De Guzman-Atala -Apolinar perdomo -1-American Beauty Soplay -Negocio -Negocio-C-8296489874-0-T-8095324491-1-0-0 | M58: Distrito Nacional | N58: Santo Domingo | O58: Santo Domingo De Guzman | P58: Atala | Q58: Apolinar perdomo | R58: 1 | S58: American Beauty Soplay | T58: Negocio | U58: Negocio | V58: C | W58: 8296489874 | X58: 0 | Y58: T | Z58: 8095324491 | AA58: 1 | AB58: 0 | AC58: 0 | AE58: 45883.455 | AG58: TD- ENTREGADO
A59: 45883 | B59: 4-12187297522 | C59: 45883 | D59: CRONY NATANAEL GARCIA SORIANO | E59: =VLOOKUP(DataOld!$B59,DATA!B:H,7,FALSE) -> #N/A | F59: =DataOld!$D59=DataOld!$E59 -> #N/A | G59: =VLOOKUP(DataOld!$B59,DATA!B:G,6,FALSE) -> #N/A | H59: 40200464903 | I59: =DataOld!$H59=DataOld!$G59 -> #N/A | J59: 137-OFICINA WINSTON CHURCHILL | K59: Santo Domingo;Santo Domingo Oeste;Herrera | L59: Santo Domingo-Santo Domingo Oeste-Santo Domingo Oeste-Herrera-Isabel aguiar-1-Banreservas -Negocios-Banreservas isabel aguiar -C-8297755069-0-C-8293867819-0-0-0 | M59: Santo Domingo | N59: Santo Domingo Oeste | O59: Santo Domingo Oeste | P59: Herrera | Q59: Isabel aguiar | R59: 1 | S59: Banreservas | T59: Negocios | U59: Banreservas isabel aguiar | V59: C | W59: 8297755069 | X59: 0 | Y59: C | Z59: 8293867819 | AA59: 0 | AB59: 0 | AC59: 0 | AE59: 45883.442 | AG59: TD- ENTREGADO
A60: 45883 | B60: 4-12186901942 | C60: 45883 | D60: LUIS ALBERTO BLANCO | E60: =VLOOKUP(DataOld!$B60,DATA!B:H,7,FALSE) -> #N/A | F60: =DataOld!$D60=DataOld!$E60 -> #N/A | G60: =VLOOKUP(DataOld!$B60,DATA!B:G,6,FALSE) -> #N/A | H60: 40215088044 | I60: =DataOld!$H60=DataOld!$G60 -> #N/A | J60: 141-OFICINA TORRE EMPRESARIAL 27 DE FEBRERO | K60: Santo Domingo;Santo Domingo Este;Los tres brazos | L60: SANTO DOMINGO-SANTO DOMINGO ESTE-SANTO DOMINGO ESTE-Los tres brazos-calle Salmos-32-32b-1-frente al caipi apt rojo-C-8094153073-0-C-8096049785-0-C-0-0 | M60: Santo Domingo | N60: Santo Domingo Este | O60: Santo Domingo Este | P60: Los tres brazos | Q60: calle Salmos | R60: 32 | S60: 32b | T60: 1 | U60: frente al caipi apt rojo | V60: C | W60: 8094153073 | X60: 0 | Y60: C | Z60: 8096049785 | AA60: 0 | AB60: C | AC60: 0 | AD60: 0 | AE60: 45883.409 | AG60: TD- ENTREGADO
A61: 45883 | B61: 4-12186969052 | C61: 45883 | D61: ROBIN DANIEL CONCEPCION PEGUERO | E61: =VLOOKUP(DataOld!$B61,DATA!B:H,7,FALSE) -> #N/A | F61: =DataOld!$D61=DataOld!$E61 -> #N/A | G61: =VLOOKUP(DataOld!$B61,DATA!B:G,6,FALSE) -> #N/A | H61: 40200768865 | I61: =DataOld!$H61=DataOld!$G61 -> #N/A | J61: 141-OFICINA TORRE EMPRESARIAL 27 DE FEBRERO | K61: Distrito Nacional;Santo Domingo;guayiga | L61: DISTRITO NACIONAL-SANTO DOMINGO-SANTO DOMINGO DE GUZMAN-guayiga-autopiata duarte-20-centro d servicio peralta-01-al lado de la bomba sigma-C-8493607171-0-C-8292223599-0-C-0-0 | M61: Distrito Nacional | N61: Santo Domingo | O61: Santo Domingo De Guzman | P61: guayiga | Q61: autopiata duarte | R61: 20 | S61: centro d servicio peralta | T61: 01 | U61: al lado de la bomba sigma | V61: C | W61: 8493607171 | X61: 0 | Y61: C | Z61: 8292223599 | AA61: 0 | AB61: C | AC61: 0 | AD61: 0 | AE61: 45883.423 | AG61: TD- ENTREGADO
A62: 45883 | B62: 4-12187536752 | C62: 45883 | D62: PAUL ANDRES ROSA JIMENEZ | E62: =VLOOKUP(DataOld!$B62,DATA!B:H,7,FALSE) -> #N/A | F62: =DataOld!$D62=DataOld!$E62 -> #N/A | G62: =VLOOKUP(DataOld!$B62,DATA!B:G,6,FALSE) -> #N/A | H62: 40232342317 | I62: =DataOld!$H62=DataOld!$G62 -> #N/A | J62: 149-OFICINA ROMULO BETANCOURT | K62: Distrito Nacional;Santo Domingo;Renacimiento | L62: Distrito Nacional-Santo Domingo-Santo Domingo De Guzman-Renacimiento-Calle Interior A-9-Torre Jeshua 6-PHF-Atras de las fuerzas armadas-C-8097074486-0-C-8096534778-0-0-0 | M62: Distrito Nacional | N62: Santo Domingo | O62: Santo Domingo De Guzman | P62: Renacimiento | Q62: Calle Interior A | R62: 9 | S62: Torre Jeshua 6 | T62: PHF | U62: Atras de las fuerzas armadas | V62: C | W62: 8097074486 | X62: 0 | Y62: C | Z62: 8096534778 | AA62: 0 | AB62: 0 | AC62: 0 | AE62: 45883.468 | AG62: TD- ENTREGADO
A63: 45883 | B63: 4-12187078702 | C63: 45883 | D63: MANUEL ANTONIO RODRIGUEZ LUCAS | E63: =VLOOKUP(DataOld!$B63,DATA!B:H,7,FALSE) -> #N/A | F63: =DataOld!$D63=DataOld!$E63 -> #N/A | G63: =VLOOKUP(DataOld!$B63,DATA!B:G,6,FALSE) -> #N/A | H63: 00201834710 | I63: =DataOld!$H63=DataOld!$G63 -> #N/A | J63: 158-OFICINA PIISA HAINA | K63: San Cristobal;San Cristobal;los molinas | L63: SAN CRISTOBAL-SAN CRISTOBAL-SAN CRISTOBAL-los molinas-calle 2da edificio 6-2-edifico 6-2-0-C-8296826216-0-T-8092212222-5109-C-0-0 | M63: San Cristobal | N63: San Cristobal | O63: San Cristobal | P63: los molinas | Q63: calle 2da edificio 6 | R63: 2 | S63: edifico 6 | T63: 2 | U63: 0 | V63: C | W63: 8296826216 | X63: 0 | Y63: T | Z63: 8092212222 | AA63: 5109 | AB63: C | AC63: 0 | AD63: 0 | AE63: 45883.423 | AG63: TD- ENTREGADO | AH63: en ruta hoy
A64: 45883 | B64: 4-12187452072 | C64: 45883 | D64: DENNISSE MICHELLE ALCEQUIEZ PACHECO | E64: =VLOOKUP(DataOld!$B64,DATA!B:H,7,FALSE) -> #N/A | F64: =DataOld!$D64=DataOld!$E64 -> #N/A | G64: =VLOOKUP(DataOld!$B64,DATA!B:G,6,FALSE) -> #N/A | H64: 40223061256 | I64: =DataOld!$H64=DataOld!$G64 -> #N/A | J64: 162-OFICINA LOS ALCARRIZOS | K64: San Cristobal;BAJOS DE HAINA;puerto de haina | L64: SAN CRISTOBAL-BAJOS DE HAINA-BAJOS DE HAINA-puerto de haina-av rio haina-00-Pollo cibao planta ABA-calidad-colmado queche-C-8298694628-0-C-8297554362-0-C-0-0 | M64: San Cristobal | N64: BAJOS DE HAINA | O64: BAJOS DE HAINA | P64: puerto de haina | Q64: av rio haina | R64: 00 | S64: Pollo cibao planta ABA | T64: calidad | U64: colmado queche | V64: C | W64: 8298694628 | X64: 0 | Y64: C | Z64: 8297554362 | AA64: 0 | AB64: C | AC64: 0 | AD64: 0 | AE64: 45883.464 | AG64: TD- ENTREGADO
A65: 45883 | B65: 4-12187612812 | C65: 45883 | D65: HEIDY KAROLINA TEJEDA ALBERTO | E65: =VLOOKUP(DataOld!$B65,DATA!B:H,7,FALSE) -> #N/A | F65: =DataOld!$D65=DataOld!$E65 -> #N/A | G65: =VLOOKUP(DataOld!$B65,DATA!B:G,6,FALSE) -> #N/A | H65: 40211950098 | I65: =DataOld!$H65=DataOld!$G65 -> #N/A | J65: 166-OFICINA VILLA MELLA HERMANAS MIRABAL | K65: Santo Domingo;SANTO DOMINGO NORTE;sabana perdida | L65: SANTO DOMINGO-SANTO DOMINGO NORTE-SANTO DOMINGO NORTE-sabana perdida-1era-38-0-0-barrio nuevo botica elohim-C-8496351930-0-R-8095909210-0-C-0-0 | M65: Santo Domingo | N65: SANTO DOMINGO NORTE | O65: SANTO DOMINGO NORTE | P65: sabana perdida | Q65: 1era | R65: 38 | S65: 0 | T65: 0 | U65: barrio nuevo botica elohim | V65: C | W65: 8496351930 | X65: 0 | Y65: R | Z65: 8095909210 | AA65: 0 | AB65: C | AC65: 0 | AD65: 0 | AE65: 45883.479 | AG65: TD- ENTREGADO
A66: 45883 | B66: 4-12186999322 | C66: 45883 | D66: KEILA FELIZ | E66: =VLOOKUP(DataOld!$B66,DATA!B:H,7,FALSE) -> #N/A | F66: =DataOld!$D66=DataOld!$E66 -> #N/A | G66: =VLOOKUP(DataOld!$B66,DATA!B:G,6,FALSE) -> #N/A | H66: 40230475671 | I66: =DataOld!$H66=DataOld!$G66 -> #N/A | J66: 169-OFICINA BELLA VISTA MALL | K66: Distrito Nacional;Santo Domingo;Bella vista | L66: Distrito Nacional-Santo Domingo-Santo Domingo De Guzman-Bella vista-Calle sagrario Diaz -14-0-0-Detrs del dragon de oro -C-8299573269-0-R-8095321361-0-0-0 | M66: Distrito Nacional | N66: Santo Domingo | O66: Santo Domingo De Guzman | P66: Bella vista | Q66: Calle sagrario Diaz | R66: 14 | S66: 0 | T66: 0 | U66: Detrs del dragon de oro | V66: C | W66: 8299573269 | X66: 0 | Y66: R | Z66: 8095321361 | AA66: 0 | AB66: 0 | AC66: 0 | AE66: 45883.409 | AG66: TD- ENTREGADO
A67: 45883 | B67: 4-12187073032 | C67: 45883 | D67: RAFAEL MANUEL GARCIA AQUINO | E67: =VLOOKUP(DataOld!$B67,DATA!B:H,7,FALSE) -> #N/A | F67: =DataOld!$D67=DataOld!$E67 -> #N/A | G67: =VLOOKUP(DataOld!$B67,DATA!B:G,6,FALSE) -> #N/A | H67: 00117803700 | I67: =DataOld!$H67=DataOld!$G67 -> #N/A | J67: 169-OFICINA BELLA VISTA MALL | K67: Distrito Nacional;Santo Domingo;arrollo hondo | L67: DISTRITO NACIONAL-SANTO DOMINGO-SANTO DOMINGO DE GUZMAN-arrollo hondo-avenida del zoologic-62-ferretería soluciones GyF-ventas-encargado-C-8094084225-0-C-8099094225-0-C-0-0 | M67: Distrito Nacional | N67: Santo Domingo | O67: Santo Domingo De Guzman | P67: arrollo hondo | Q67: avenida del zoologic | R67: 62 | S67: ferretería soluciones GyF | T67: ventas | U67: encargado | V67: C | W67: 8094084225 | X67: 0 | Y67: C | Z67: 8099094225 | AA67: 0 | AB67: C | AC67: 0 | AD67: 0 | AE67: 45883.426 | AG67: TD- ENTREGADO
A68: 45883 | B68: 4-12187577502 | C68: 45883 | D68: HENRY ALEXANDER VILLAR TEJEDA | E68: =VLOOKUP(DataOld!$B68,DATA!B:H,7,FALSE) -> #N/A | F68: =DataOld!$D68=DataOld!$E68 -> #N/A | G68: =VLOOKUP(DataOld!$B68,DATA!B:G,6,FALSE) -> #N/A | H68: 22600241073 | I68: =DataOld!$H68=DataOld!$G68 -> #N/A | J68: 170-Sucursal Olé 27 de febrero | K68: Santo Domingo;Boca Chica;La caleta | L68: Santo Domingo-Boca Chica-Boca Chica-La caleta-Respaldo francisco d-28-0-0-Frente al colmado la bendici-C-8098762056-0-C-8295049108-0-0-0 | M68: Santo Domingo | N68: Boca Chica | O68: Boca Chica | P68: La caleta | Q68: Respaldo francisco d | R68: 28 | S68: 0 | T68: 0 | U68: Frente al colmado la bendici | V68: C | W68: 8098762056 | X68: 0 | Y68: C | Z68: 8295049108 | AA68: 0 | AB68: 0 | AC68: 0 | AE68: 45883.468 | AG68: TD- DEVUELTO NO LOCALIZADO | AH68: NUMEROS NO RESPONDEN | AL68: no responde
A69: 45883 | B69: 4-12187358662 | C69: 45883 | D69: CRISTINA MAGDALENA RAMIREZ MARTINEZ | E69: =VLOOKUP(DataOld!$B69,DATA!B:H,7,FALSE) -> #N/A | F69: =DataOld!$D69=DataOld!$E69 -> #N/A | G69: =VLOOKUP(DataOld!$B69,DATA!B:G,6,FALSE) -> #N/A | H69: 22301659334 | I69: =DataOld!$H69=DataOld!$G69 -> #N/A | J69: 195-OFICINA BOCA CHICA | K69: Santo Domingo;Santo Domingo Este;maquiteria | L69: SANTO DOMINGO-SANTO DOMINGO ESTE-SANTO DOMINGO ESTE-maquiteria-interior A-44-0-0-Interior A parte atrás-R-8296659537-0-C-8098632495-0-C-8298945518-0 | M69: Santo Domingo | N69: Santo Domingo Este | O69: Santo Domingo Este | P69: maquiteria | Q69: interior A | R69: 44 | S69: 0 | T69: 0 | U69: Interior A parte atrás | V69: R | W69: 8296659537 | X69: 0 | Y69: C | Z69: 8098632495 | AA69: 0 | AB69: C | AC69: 8298945518 | AD69: 0 | AE69: 45883.449 | AG69: TD- ENTREGADO
A70: 45883 | B70: 4-12187716602 | C70: 45883 | D70: FERNANDA RAISEL POLANCO FLORIAN | E70: =VLOOKUP(DataOld!$B70,DATA!B:H,7,FALSE) -> #N/A | F70: =DataOld!$D70=DataOld!$E70 -> #N/A | G70: =VLOOKUP(DataOld!$B70,DATA!B:G,6,FALSE) -> #N/A | H70: 40234228936 | I70: =DataOld!$H70=DataOld!$G70 -> #N/A | J70: 195-OFICINA BOCA CHICA | K70: Santo Domingo;Santo Domingo Este;Brisas del este | L70: Santo Domingo-Santo Domingo Este-Santo Domingo Este-Brisas del este -Violeta -1-0-0-Casa azul frente iglesia -C-8494353755-0-C-8493888305-0-0-0 | M70: Santo Domingo | N70: Santo Domingo Este | O70: Santo Domingo Este | P70: Brisas del este | Q70: Violeta | R70: 1 | S70: 0 | T70: 0 | U70: Casa azul frente iglesia | V70: C | W70: 8494353755 | X70: 0 | Y70: C | Z70: 8493888305 | AA70: 0 | AB70: 0 | AC70: 0 | AE70: 45883.483 | AG70: TD- ENTREGADO
A71: 45883 | B71: 4-12187594352 | C71: 45883 | D71: FRANCISCO ADONIS MEDRANO DISLA | E71: =VLOOKUP(DataOld!$B71,DATA!B:H,7,FALSE) -> #N/A | F71: =DataOld!$D71=DataOld!$E71 -> #N/A | G71: =VLOOKUP(DataOld!$B71,DATA!B:G,6,FALSE) -> #N/A | H71: 40224911079 | I71: =DataOld!$H71=DataOld!$G71 -> #N/A | J71: 271-OFICINA DAJABON | K71: Distrito Nacional;Santo Domingo;Los rios | L71: Distrito Nacional-Santo Domingo-Santo Domingo De Guzman-Los Rios-Pradera Hermosa c3-11-0-0-Pradera hermosa calle 3era-C-8496537099-0-C-8292594916-0-0-0 | M71: Distrito Nacional | N71: Santo Domingo | O71: Santo Domingo De Guzman | P71: Los rios | Q71: Pradera Hermosa c3 | R71: 11 | S71: 0 | T71: 0 | U71: Pradera hermosa calle 3era | V71: C | W71: 8496537099 | X71: 0 | Y71: C | Z71: 8292594916 | AA71: 0 | AB71: 0 | AC71: 0 | AE71: 45883.467 | AG71: TD- ENTREGADO
A72: 45883 | B72: 4-12187016392 | C72: 45883 | D72: EDWIN FIGUEROA GUZMAN | E72: =VLOOKUP(DataOld!$B72,DATA!B:H,7,FALSE) -> #N/A | F72: =DataOld!$D72=DataOld!$E72 -> #N/A | G72: =VLOOKUP(DataOld!$B72,DATA!B:G,6,FALSE) -> #N/A | H72: 07100532113 | I72: =DataOld!$H72=DataOld!$G72 -> #N/A | J72: 280-OFICINA MEGACENTRO I | K72: Santo Domingo;Santo Domingo Este;El kolosal | L72: SANTO DOMINGO-SANTO DOMINGO ESTE-SANTO DOMINGO ESTE-El kolosal-manzana 7-12-manzana 7 casa 12-0-0-C-8492071988-0-C-8099189565-0-C-0-0 | M72: Santo Domingo | N72: Santo Domingo Este | O72: Santo Domingo Este | P72: El kolosal | Q72: manzana 7 | R72: 12 | S72: manzana 7 casa 12 | T72: 0 | U72: 0 | V72: C | W72: 8492071988 | X72: 0 | Y72: C | Z72: 8099189565 | AA72: 0 | AB72: C | AC72: 0 | AD72: 0 | AE72: 45883.412 | AG72: TD- ENTREGADO
A73: 45883 | B73: 4-12187203192 | C73: 45883 | D73: AMAURY AGUSTIN PENALO VALENZUELA | E73: =VLOOKUP(DataOld!$B73,DATA!B:H,7,FALSE) -> #N/A | F73: =DataOld!$D73=DataOld!$E73 -> #N/A | G73: =VLOOKUP(DataOld!$B73,DATA!B:G,6,FALSE) -> #N/A | H73: 00113021117 | I73: =DataOld!$H73=DataOld!$G73 -> #N/A | J73: 280-OFICINA MEGACENTRO I | K73: Santo Domingo;Santo Domingo Este;brisas oriental | L73: SANTO DOMINGO-SANTO DOMINGO ESTE-SANTO DOMINGO ESTE-brisas oriental-principal-10-0-0-entrando por plaza roja-C-8098857750-0-C-8493532507-0-C-0-0 | M73: Santo Domingo | N73: Santo Domingo Este | O73: Santo Domingo Este | P73: brisas oriental | Q73: Principal | R73: 10 | S73: 0 | T73: 0 | U73: entrando por plaza roja | V73: C | W73: 8098857750 | X73: 0 | Y73: C | Z73: 8493532507 | AA73: 0 | AB73: C | AC73: 0 | AD73: 0 | AE73: 45883.438 | AG73: TD- ENTREGADO
A74: 45883 | B74: 4-12187578032 | C74: 45883 | D74: KEVIN ALBERTO FOURNIER CUEVAS | E74: =VLOOKUP(DataOld!$B74,DATA!B:H,7,FALSE) -> #N/A | F74: =DataOld!$D74=DataOld!$E74 -> #N/A | G74: =VLOOKUP(DataOld!$B74,DATA!B:G,6,FALSE) -> #N/A | H74: 40230509743 | I74: =DataOld!$H74=DataOld!$G74 -> #N/A | J74: 280-OFICINA MEGACENTRO I | K74: Santo Domingo;Santo Domingo Este;Los mina | L74: SANTO DOMINGO-SANTO DOMINGO ESTE-SANTO DOMINGO ESTE-los mina-gabriela morillo-43-0-0-segundo piso edif amarillo-C-8298875160-0-C-8098052222-0-C-0-0 | M74: Santo Domingo | N74: Santo Domingo Este | O74: Santo Domingo Este | P74: Los mina | Q74: gabriela morillo | R74: 43 | S74: 0 | T74: 0 | U74: segundo piso edif amarillo | V74: C | W74: 8298875160 | X74: 0 | Y74: C | Z74: 8098052222 | AA74: 0 | AB74: C | AC74: 0 | AD74: 0 | AE74: 45883.474 | AG74: TD- ENTREGADO
A75: 45883 | B75: 4-12187595232 | C75: 45883 | D75: ANA MILEIDY VICTORIANO LEBRON | E75: =VLOOKUP(DataOld!$B75,DATA!B:H,7,FALSE) -> #N/A | F75: =DataOld!$D75=DataOld!$E75 -> #N/A | G75: =VLOOKUP(DataOld!$B75,DATA!B:G,6,FALSE) -> #N/A | H75: 40212991471 | I75: =DataOld!$H75=DataOld!$G75 -> #N/A | J75: 303-OFICINA SAMBIL | K75: Santo Domingo;Santo Domingo Oeste;la rosa | L75: SANTO DOMINGO-SANTO DOMINGO OESTE-SANTO DOMINGO OESTE-la rosa-27 de febrero-441-centro automotriz loma-441-frente a yohelis motor-C-8299457652-0-T-8092377288-1712-C-8095341712-0 | M75: Santo Domingo | N75: Santo Domingo Oeste | O75: Santo Domingo Oeste | P75: la rosa | Q75: 27 de Febrero | R75: 441 | S75: centro automotriz loma | T75: 441 | U75: frente a yohelis motor | V75: C | W75: 8299457652 | X75: 0 | Y75: T | Z75: 8092377288 | AA75: 1712 | AB75: C | AC75: 8095341712 | AD75: 0 | AE75: 45883.48 | AG75: TD- ENTREGADO
A76: 45883 | B76: 4-12187130642 | C76: 45883 | D76: ALEXIS MATOS NOVAS | E76: =VLOOKUP(DataOld!$B76,DATA!B:H,7,FALSE) -> #N/A | F76: =DataOld!$D76=DataOld!$E76 -> #N/A | G76: =VLOOKUP(DataOld!$B76,DATA!B:G,6,FALSE) -> #N/A | H76: 40213613082 | I76: =DataOld!$H76=DataOld!$G76 -> #N/A | J76: 314-OFICINA MULTICENTRO CHURCHILL | K76: Santo Domingo;Santo Domingo Oeste;Libertador de herrer | L76: Santo Domingo-Santo Domingo Oeste-Santo Domingo Oeste-Libertador de herrer-Calle primera -12-Edificio azul -2-Frente colmado Fabin-C-8296165693-0-C-8295840309-0-0-0 | M76: Santo Domingo | N76: Santo Domingo Oeste | O76: Santo Domingo Oeste | P76: Libertador de herrer | Q76: Calle primera | R76: 12 | S76: Edificio azul | T76: 2 | U76: Frente colmado Fabin | V76: C | W76: 8296165693 | X76: 0 | Y76: C | Z76: 8295840309 | AA76: 0 | AB76: 0 | AC76: 0 | AE76: 45883.428 | AG76: TD- ENTREGADO
A77: 45883 | B77: 4-12187071492 | C77: 45883 | D77: JOSE RENE SALDIVAR SALDIVAR | E77: =VLOOKUP(DataOld!$B77,DATA!B:H,7,FALSE) -> #N/A | F77: =DataOld!$D77=DataOld!$E77 -> #N/A | G77: =VLOOKUP(DataOld!$B77,DATA!B:G,6,FALSE) -> #N/A | H77: 40225628318 | I77: =DataOld!$H77=DataOld!$G77 -> #N/A | J77: 317-OFICINA CARREFOUR | K77: Santo Domingo;Santo Domingo Oeste;manoguayabo | L77: SANTO DOMINGO-SANTO DOMINGO OESTE-SANTO DOMINGO OESTE-manoguayabo-carr de manoguayabo-267-saldivar y ascd-recepción-entregar a la secretaria-C-8299633684-0-T-8093722418-0-C-0-0 | M77: Santo Domingo | N77: Santo Domingo Oeste | O77: Santo Domingo Oeste | P77: manoguayabo | Q77: carr de manoguayabo | R77: 267 | S77: saldivar y ascd | T77: Recepción | U77: entregar a la secretaria | V77: C | W77: 8299633684 | X77: 0 | Y77: T | Z77: 8093722418 | AA77: 0 | AB77: C | AC77: 0 | AD77: 0 | AE77: 45883.421 | AG77: TD- ENTREGADO
A78: 45883 | B78: 4-12187072702 | C78: 45883 | D78: ODALIS MABEL RAMOS SOTO | E78: =VLOOKUP(DataOld!$B78,DATA!B:H,7,FALSE) -> #N/A | F78: =DataOld!$D78=DataOld!$E78 -> #N/A | G78: =VLOOKUP(DataOld!$B78,DATA!B:G,6,FALSE) -> #N/A | H78: 40222698686 | I78: =DataOld!$H78=DataOld!$G78 -> #N/A | J78: 353-OFICINA CENTRO NACIONAL DEL ESTE | K78: SAN PEDRO DE MACORIS;SAN PEDRO MACORIS;villa municipal | L78: SAN PEDRO DE MACORIS-SAN PEDRO MACORIS-SAN PEDRO DE MACORIS-villa municipal-padre luciani-4-elina-elina-cerca del colegio jerusalem-C-8296967405-0-C-8296718626-0-C-0-0 | M78: SAN PEDRO DE MACORIS | N78: SAN PEDRO MACORIS | O78: SAN PEDRO DE MACORIS | P78: villa municipal | Q78: padre luciani | R78: 4 | S78: elina | T78: elina | U78: cerca del colegio jerusalem | V78: C | W78: 8296967405 | X78: 0 | Y78: C | Z78: 8296718626 | AA78: 0 | AB78: C | AC78: 0 | AD78: 0 | AE78: 45883.422 | AG78: TD- ENTREGADO
A79: 45883 | B79: 4-12187082912 | C79: 45883 | D79: MAGDALENA LOFFICIAL | E79: =VLOOKUP(DataOld!$B79,DATA!B:H,7,FALSE) -> #N/A | F79: =DataOld!$D79=DataOld!$E79 -> #N/A | G79: =VLOOKUP(DataOld!$B79,DATA!B:G,6,FALSE) -> #N/A | H79: 40208763066 | I79: =DataOld!$H79=DataOld!$G79 -> #N/A | J79: Centro Digital Popular | K79: Santo Domingo;PEDRO BRAND;Pedro brand | L79: Santo Domingo-Pedro Brand-Pedro Brand-Pedro brand-Pepillo Salcedo no9-9-2-3a-Entrando por el repuesto-C-8099742672-0-C-8298060202-0-0-0 | M79: Santo Domingo | N79: PEDRO BRAND | O79: Pedro Brand | P79: Pedro brand | Q79: Pepillo Salcedo no9 | R79: 9 | S79: 2 | T79: 3a | U79: Entrando por el repuesto | V79: C | W79: 8099742672 | X79: 0 | Y79: C | Z79: 8298060202 | AA79: 0 | AB79: 0 | AC79: 0 | AE79: 45883.425 | AG79: TD- ENTREGADO
A80: 45883 | B80: 4-12187108222 | C80: 45883 | D80: JUNIOR FRANCISCO FERNANDEZ BETANCES | E80: =VLOOKUP(DataOld!$B80,DATA!B:H,7,FALSE) -> #N/A | F80: =DataOld!$D80=DataOld!$E80 -> #N/A | G80: =VLOOKUP(DataOld!$B80,DATA!B:G,6,FALSE) -> #N/A | H80: 40230278414 | I80: =DataOld!$H80=DataOld!$G80 -> #N/A | J80: Centro Digital Popular | K80: Distrito Nacional;Santo Domingo;Gascuer | L80: Distrito Nacional-Santo Domingo-Santo Domingo De Guzman-Gascuer-Lugar Malecon center-211-Batista pena inversiones-211c-Segundo nivel 211c-C-8492666408-0-C-8292018662-0-0-0 | M80: Distrito Nacional | N80: Santo Domingo | O80: Santo Domingo De Guzman | P80: Gascuer | Q80: Lugar Malecon center | R80: 211 | S80: Batista pena inversiones | T80: 211c | U80: Segundo nivel 211c | V80: C | W80: 8492666408 | X80: 0 | Y80: C | Z80: 8292018662 | AA80: 0 | AB80: 0 | AC80: 0 | AE80: 45883.43 | AG80: TD- ENTREGADO
A81: 45883 | B81: 4-12187181302 | C81: 45883 | D81: GABRIEL LEONARDO ESPINAL HERNANDEZ | E81: =VLOOKUP(DataOld!$B81,DATA!B:H,7,FALSE) -> #N/A | F81: =DataOld!$D81=DataOld!$E81 -> #N/A | G81: =VLOOKUP(DataOld!$B81,DATA!B:G,6,FALSE) -> #N/A | H81: 40218838320 | I81: =DataOld!$H81=DataOld!$G81 -> #N/A | J81: Centro Digital Popular | K81: Distrito Nacional;Santo Domingo;Mirador sur | L81: Distrito Nacional-Santo Domingo-Santo Domingo De Guzman-Mirador sur -Calle Leonor feltz -60-Lo quiero auto import -Piso 1-Dealer de vehculos-C-8298161726-0-C-8294781726-0-0-0 | M81: Distrito Nacional | N81: Santo Domingo | O81: Santo Domingo De Guzman | P81: Mirador sur | Q81: Calle Leonor feltz | R81: 60 | S81: Lo quiero auto import | T81: Piso 1 | U81: Dealer de vehculos | V81: C | W81: 8298161726 | X81: 0 | Y81: C | Z81: 8294781726 | AA81: 0 | AB81: 0 | AC81: 0 | AE81: 45883.427 | AG81: TD- ENTREGADO
A82: 45883 | B82: 4-12187202742 | C82: 45883 | D82: AVRIL SOTO CARO | E82: =VLOOKUP(DataOld!$B82,DATA!B:H,7,FALSE) -> #N/A | F82: =DataOld!$D82=DataOld!$E82 -> #N/A | G82: =VLOOKUP(DataOld!$B82,DATA!B:G,6,FALSE) -> #N/A | H82: 40219978505 | I82: =DataOld!$H82=DataOld!$G82 -> #N/A | J82: Centro Digital Popular | K82: Distrito Nacional;Santo Domingo;Los rios | L82: Distrito Nacional-Santo Domingo-Santo Domingo De Guzman-Los Rios -2da la esperanza -32-0-0-0-C-8293380727-0-C-8298107575-0-0-0 | M82: Distrito Nacional | N82: Santo Domingo | O82: Santo Domingo De Guzman | P82: Los rios | Q82: 2da la esperanza | R82: 32 | S82: 0 | T82: 0 | U82: 0 | V82: C | W82: 8293380727 | X82: 0 | Y82: C | Z82: 8298107575 | AA82: 0 | AB82: 0 | AC82: 0 | AE82: 45883.434 | AG82: TD- ENTREGADO
A83: 45883 | B83: 4-12187359752 | C83: 45883 | D83: LISETT ALTAGRACIA ESPINAL | E83: =VLOOKUP(DataOld!$B83,DATA!B:H,7,FALSE) -> #N/A | F83: =DataOld!$D83=DataOld!$E83 -> #N/A | G83: =VLOOKUP(DataOld!$B83,DATA!B:G,6,FALSE) -> #N/A | H83: 40213224807 | I83: =DataOld!$H83=DataOld!$G83 -> #N/A | J83: Centro Digital Popular | K83: La Altagracia;Higuey;La Malena | L83: La Altagracia-Higuey-Higuey-La Malena-Anacaona -104-104-12-Frente a salon Escocia -C-8293753230-0-C-8297599446-0-0-0 | M83: La Altagracia | N83: Higuey | O83: Higuey | P83: La Malena | Q83: Anacaona | R83: 104 | S83: 104 | T83: 12 | U83: Frente a salon Escocia | V83: C | W83: 8293753230 | X83: 0 | Y83: C | Z83: 8297599446 | AA83: 0 | AB83: 0 | AC83: 0 | AE83: 45883.452 | AG83: TD- ENTREGADO | AL83: 8297599446 HABLE CON SU AMIGA TEL WSS LE ESCRIBI SOLO 829-980-4524 ME ENVIO SU UBICACION DE INMEDIATO
A84: 45883 | B84: 4-12187443282 | C84: 45883 | D84: DEIVY ENMANUEL CID MARTINEZ | E84: =VLOOKUP(DataOld!$B84,DATA!B:H,7,FALSE) -> #N/A | F84: =DataOld!$D84=DataOld!$E84 -> #N/A | G84: =VLOOKUP(DataOld!$B84,DATA!B:G,6,FALSE) -> #N/A | H84: 40212097881 | I84: =DataOld!$H84=DataOld!$G84 -> #N/A | J84: Centro Digital Popular | K84: Distrito Nacional;Santo Domingo;Herrera | L84: Distrito Nacional-Santo Domingo-Santo Domingo De Guzman-Herrera -Calle Alvarez Guzman-9-Cidae Soluciones -3er piso-Frente al colmado Xavier-C-8297548705-0-C-8094419896-0-0-0 | M84: Distrito Nacional | N84: Santo Domingo | O84: Santo Domingo De Guzman | P84: Herrera | Q84: Calle Alvarez Guzman | R84: 9 | S84: Cidae Soluciones | T84: 3er piso | U84: Frente al colmado Xavier | V84: C | W84: 8297548705 | X84: 0 | Y84: C | Z84: 8094419896 | AA84: 0 | AB84: 0 | AC84: 0 | AE84: 45883.464 | AG84: TD- ENTREGADO
A85: 45883 | B85: 4-12187472812 | C85: 45883 | D85: CESAR OSCAR JIMENEZ MORENO | E85: =VLOOKUP(DataOld!$B85,DATA!B:H,7,FALSE) -> #N/A | F85: =DataOld!$D85=DataOld!$E85 -> #N/A | G85: =VLOOKUP(DataOld!$B85,DATA!B:G,6,FALSE) -> #N/A | H85: 40242427801 | I85: =DataOld!$H85=DataOld!$G85 -> #N/A | J85: Centro Digital Popular | K85: Distrito Nacional;Santo Domingo;ensanche paraiso | L85: Distrito Nacional-Santo Domingo-Santo Domingo De Guzman-Ensanche paraiso-Av Abraham Lincoln-1012-Motor Credito-Cobros-Edificio ambar-C-8497544254-0-T-8095403900-629-0-0 | M85: Distrito Nacional | N85: Santo Domingo | O85: Santo Domingo De Guzman | P85: ensanche paraiso | Q85: Av Abraham Lincoln | R85: 1012 | S85: Motor Credito | T85: cobros | U85: Edificio ambar | V85: C | W85: 8497544254 | X85: 0 | Y85: T | Z85: 8095403900 | AA85: 629 | AB85: 0 | AC85: 0 | AE85: 45883.46 | AG85: TD- ENTREGADO
A86: 45883 | B86: 4-12187667932 | C86: 45883 | D86: CRISTOPHER MATOS | E86: =VLOOKUP(DataOld!$B86,DATA!B:H,7,FALSE) -> #N/A | F86: =DataOld!$D86=DataOld!$E86 -> #N/A | G86: =VLOOKUP(DataOld!$B86,DATA!B:G,6,FALSE) -> #N/A | H86: 40229782871 | I86: =DataOld!$H86=DataOld!$G86 -> #N/A | J86: Centro Digital Popular | K86: Santo Domingo;Santo Domingo Este;Brisa del este | L86: Santo Domingo-Santo Domingo Este-Santo Domingo Este-Brisa del este -Calle paseo del eden-33-Arlado de colmado seleida-1-Al lado de colmado -C-8293348726-0-C-8097871690-0-0-0 | M86: Santo Domingo | N86: Santo Domingo Este | O86: Santo Domingo Este | P86: Brisa del este | Q86: Calle paseo del eden | R86: 33 | S86: Arlado de colmado seleida | T86: 1 | U86: Al lado de colmado | V86: C | W86: 8293348726 | X86: 0 | Y86: C | Z86: 8097871690 | AA86: 0 | AB86: 0 | AC86: 0 | AE86: 45883.481 | AG86: TD- ENTREGADO
A87: 45884 | B87: 4-12192576592 | C87: 45884 | D87: CANDIDA ARACELIS VITTINI PENA | E87: =VLOOKUP(DataOld!$B87,DATA!B:H,7,FALSE) -> #N/A | F87: =DataOld!$D87=DataOld!$E87 -> #N/A | G87: =VLOOKUP(DataOld!$B87,DATA!B:G,6,FALSE) -> #N/A | H87: 00103677381 | I87: =DataOld!$H87=DataOld!$G87 -> #N/A | J87: CLIENTES A ELIMINAR ICBS | K87: DISTRITO NACIONAL;SANTO DOMINGO;La Esperilla | L87: Distrito Nacional-Santo Domingo-Santo Domingo De Guzman-La Esperilla-Avenida Mximo Gomez -60-Fajate-Taller-Frente al teatro nacional -C-8492031901-0-C-8495127821-0-0-0 | M87: DISTRITO NACIONAL | N87: SANTO DOMINGO | O87: SANTO DOMINGO DE GUZMAN | P87: La Esperilla | Q87: Avenida Mximo Gomez | R87: 60 | S87: Fajate | T87: Taller | U87: Frente al teatro nacional | V87: C | W87: 8492031901 | X87: 0 | Y87: C | Z87: 8495127821 | AA87: 0 | AB87: 0 | AC87: 0 | AE87: 45884.475 | AG87: TD- ENTREGADO
A88: 45884 | B88: 4-12194238112 | C88: 45884 | D88: KISBEL DISMERI ALMONTE | E88: =VLOOKUP(DataOld!$B88,DATA!B:H,7,FALSE) -> #N/A | F88: =DataOld!$D88=DataOld!$E88 -> #N/A | G88: =VLOOKUP(DataOld!$B88,DATA!B:G,6,FALSE) -> #N/A | H88: 22500799881 | I88: =DataOld!$H88=DataOld!$G88 -> #N/A | J88: 142-OFICINA NUÑEZ DE CACERES | K88: DISTRITO NACIONAL;SANTO DOMINGO;Manoguayabo | L88: Distrito Nacional-Santo Domingo-Santo Domingo De Guzman-Manoguayabo -Calle san Luis 6-0915-Psi productos y solucio-Ventas-Bufete victoria -C-8097800469-0-C-8294207880-0-0-0 | M88: DISTRITO NACIONAL | N88: SANTO DOMINGO | O88: SANTO DOMINGO DE GUZMAN | P88: Manoguayabo | Q88: Calle san Luis 6 | R88: 0915 | S88: Psi productos y solucio | T88: ventas | U88: Bufete victoria | V88: C | W88: 8097800469 | X88: 0 | Y88: C | Z88: 8294207880 | AA88: 0 | AB88: 0 | AC88: 0 | AE88: 45884.633 | AG88: TD- ENTREGADO
A89: 45884 | B89: 4-12192584212 | C89: 45884 | D89: ERICK ANTONIO TORRES PRESINAL | E89: =VLOOKUP(DataOld!$B89,DATA!B:H,7,FALSE) -> #N/A | F89: =DataOld!$D89=DataOld!$E89 -> #N/A | G89: =VLOOKUP(DataOld!$B89,DATA!B:G,6,FALSE) -> #N/A | H89: 40214524924 | I89: =DataOld!$H89=DataOld!$G89 -> #N/A | J89: Centro Digital Popular | K89: DISTRITO NACIONAL;SANTO DOMINGO;La Julia | L89: Distrito Nacional-Santo Domingo-Santo Domingo De Guzman-La Julia-avenida abraham linc-304-Banco Vimenca -Paga todo-Paga todo -C-8294054162-0-C-8496354611-0-0-0 | M89: DISTRITO NACIONAL | N89: SANTO DOMINGO | O89: SANTO DOMINGO DE GUZMAN | P89: La Julia | Q89: avenida abraham linc | R89: 304 | S89: Banco Vimenca | T89: Paga todo | U89: Paga todo | V89: C | W89: 8294054162 | X89: 0 | Y89: C | Z89: 8496354611 | AA89: 0 | AB89: 0 | AC89: 0 | AE89: 45884.51 | AG89: TD- ENTREGADO
A90: 45884 | B90: 4-12193363052 | C90: 45884 | D90: JULIO ISAAC ESCOTTO CARMONA | E90: =VLOOKUP(DataOld!$B90,DATA!B:H,7,FALSE) -> #N/A | F90: =DataOld!$D90=DataOld!$E90 -> #N/A | G90: =VLOOKUP(DataOld!$B90,DATA!B:G,6,FALSE) -> #N/A | H90: 40200769434 | I90: =DataOld!$H90=DataOld!$G90 -> #N/A | J90: Centro Digital Popular | K90: DISTRITO NACIONAL;SANTO DOMINGO;Zona colonial | L90: DISTRITO NACIONAL-SANTO DOMINGO-SANTO DOMINGO DE GUZMAN-Zona Colonial-Calle Las Mercedes-57-Granier Zona Colonial-caja-Restaurante Granier Zona-C-8299247455-0-C-8093591800-0-C-0-0 | M90: DISTRITO NACIONAL | N90: SANTO DOMINGO | O90: SANTO DOMINGO DE GUZMAN | P90: Zona colonial | Q90: Calle Las Mercedes | R90: 57 | S90: Granier Zona Colonial | T90: Caja | U90: Restaurante Granier Zona | V90: C | W90: 8299247455 | X90: 0 | Y90: C | Z90: 8093591800 | AA90: 0 | AB90: C | AC90: 0 | AD90: 0 | AE90: 45884.56 | AG90: TD- ENTREGADO
A91: 45884 | B91: 4-12192251022 | C91: 45884 | D91: JULIO CESAR RUIZ CASTRO | E91: =VLOOKUP(DataOld!$B91,DATA!B:H,7,FALSE) -> #N/A | F91: =DataOld!$D91=DataOld!$E91 -> #N/A | G91: =VLOOKUP(DataOld!$B91,DATA!B:G,6,FALSE) -> #N/A | H91: 40240020137 | I91: =DataOld!$H91=DataOld!$G91 -> #N/A | J91: 752-DEPARTAMENTO COBROS ESPECIALIZADOS | K91: DISTRITO NACIONAL;SANTO DOMINGO;Los Guaricano | L91: Distrito Nacional-Santo Domingo-Santo Domingo De Guzman-Los Guaricano -Hermana mirrabal-28-Respueto beyby -1-Mas para lante de los bomber-C-8295743571-0-C-8495629735-0-0-0 | M91: DISTRITO NACIONAL | N91: SANTO DOMINGO | O91: SANTO DOMINGO DE GUZMAN | P91: Los Guaricano | Q91: Hermana mirrabal | R91: 28 | S91: Respueto beyby | T91: 1 | U91: Mas para lante de los bomber | V91: C | W91: 8295743571 | X91: 0 | Y91: C | Z91: 8495629735 | AA91: 0 | AB91: 0 | AC91: 0 | AE91: 45884.452 | AG91: TD- ENTREGADO
A92: 45884 | B92: 4-12192451092 | C92: 45884 | D92: JOSE MIGUEL URBAEZ MESA | E92: =VLOOKUP(DataOld!$B92,DATA!B:H,7,FALSE) -> #N/A | F92: =DataOld!$D92=DataOld!$E92 -> #N/A | G92: =VLOOKUP(DataOld!$B92,DATA!B:G,6,FALSE) -> #N/A | H92: 00118824085 | I92: =DataOld!$H92=DataOld!$G92 -> #N/A | J92: 143-OFICINA ARROYO HONDO | K92: DISTRITO NACIONAL;SANTO DOMINGO;Harroyo hondo | L92: Distrito Nacional-Santo Domingo-Santo Domingo De Guzman-Harroyo hondo -Calle Q-10-0-0-Casa -R-8092316451-0-C-8099137424-0-0-0 | M92: DISTRITO NACIONAL | N92: SANTO DOMINGO | O92: SANTO DOMINGO DE GUZMAN | P92: Harroyo hondo | Q92: Calle Q | R92: 10 | S92: 0 | T92: 0 | U92: Casa | V92: R | W92: 8092316451 | X92: 0 | Y92: C | Z92: 8099137424 | AA92: 0 | AB92: 0 | AC92: 0 | AE92: 45884.492 | AG92: TD- ENTREGADO
A93: 45884 | B93: 4-12193363312 | C93: 45884 | D93: WILFRED BATISTA BELTRE | E93: =VLOOKUP(DataOld!$B93,DATA!B:H,7,FALSE) -> #N/A | F93: =DataOld!$D93=DataOld!$E93 -> #N/A | G93: =VLOOKUP(DataOld!$B93,DATA!B:G,6,FALSE) -> #N/A | H93: 40240001897 | I93: =DataOld!$H93=DataOld!$G93 -> #N/A | J93: 752-DEPARTAMENTO COBROS ESPECIALIZADOS | K93: DISTRITO NACIONAL;SANTO DOMINGO;los girasoles ll | L93: DISTRITO NACIONAL-SANTO DOMINGO-SANTO DOMINGO DE GUZMAN-los girasoles ll-los claveles-13-0-0-0-C-8098815690-0-C-8295232779-0-C-0-0 | M93: DISTRITO NACIONAL | N93: SANTO DOMINGO | O93: SANTO DOMINGO DE GUZMAN | P93: los girasoles ll | Q93: los claveles | R93: 13 | S93: 0 | T93: 0 | U93: 0 | V93: C | W93: 8098815690 | X93: 0 | Y93: C | Z93: 8295232779 | AA93: 0 | AB93: C | AC93: 0 | AD93: 0 | AE93: 45884.563 | AG93: TD- ENTREGADO
A94: 45884 | B94: 4-12193444352 | C94: 45884 | D94: LISBETH DEL CARMEN PERALTA SOSA | E94: =VLOOKUP(DataOld!$B94,DATA!B:H,7,FALSE) -> #N/A | F94: =DataOld!$D94=DataOld!$E94 -> #N/A | G94: =VLOOKUP(DataOld!$B94,DATA!B:G,6,FALSE) -> #N/A | H94: 40233849286 | I94: =DataOld!$H94=DataOld!$G94 -> #N/A | J94: 752-DEPARTAMENTO COBROS ESPECIALIZADOS | K94: DISTRITO NACIONAL;SANTO DOMINGO;Bella vista | L94: Distrito Nacional-Santo Domingo-Santo Domingo De Guzman-Bella vista -Respaldosagrariodiaz-26-Colmado papo -26-Entrado por el colmado papo-C-8292850424-0-C-8296340454-0-0-0 | M94: DISTRITO NACIONAL | N94: SANTO DOMINGO | O94: SANTO DOMINGO DE GUZMAN | P94: Bella vista | Q94: Respaldosagrariodiaz | R94: 26 | S94: Colmado papo | T94: 26 | U94: Entrado por el colmado papo | V94: C | W94: 8292850424 | X94: 0 | Y94: C | Z94: 8296340454 | AA94: 0 | AB94: 0 | AC94: 0 | AE94: 45884.578 | AG94: TD- ENTREGADO
A95: 45884 | B95: 4-12193481682 | C95: 45884 | D95: BRAYAN DAVID CARELA DIAZ | E95: =VLOOKUP(DataOld!$B95,DATA!B:H,7,FALSE) -> #N/A | F95: =DataOld!$D95=DataOld!$E95 -> #N/A | G95: =VLOOKUP(DataOld!$B95,DATA!B:G,6,FALSE) -> #N/A | H95: 40239171461 | I95: =DataOld!$H95=DataOld!$G95 -> #N/A | J95: 752-DEPARTAMENTO COBROS ESPECIALIZADOS | K95: DISTRITO NACIONAL;SANTO DOMINGO;La fe | L95: Distrito Nacional-Santo Domingo-Santo Domingo De Guzman-La fe-Maximo Gomez -1-Induban-1-Cafe Santo Domingo -C-8092691385-0-T-8095653121-2346-0-0 | M95: DISTRITO NACIONAL | N95: SANTO DOMINGO | O95: SANTO DOMINGO DE GUZMAN | P95: La fe | Q95: Maximo Gomez | R95: 1 | S95: Induban | T95: 1 | U95: Cafe Santo Domingo | V95: C | W95: 8092691385 | X95: 0 | Y95: T | Z95: 8095653121 | AA95: 2346 | AB95: 0 | AC95: 0 | AE95: 45884.572 | AG95: TD- ENTREGADO
A96: 45884 | B96: 4-12194081382 | C96: 45884 | D96: RUI DEL CARMEN SANCHEZ NUNEZ | E96: =VLOOKUP(DataOld!$B96,DATA!B:H,7,FALSE) -> #N/A | F96: =DataOld!$D96=DataOld!$E96 -> #N/A | G96: =VLOOKUP(DataOld!$B96,DATA!B:G,6,FALSE) -> #N/A | H96: 40226273544 | I96: =DataOld!$H96=DataOld!$G96 -> #N/A | J96: 752-DEPARTAMENTO COBROS ESPECIALIZADOS | K96: DISTRITO NACIONAL;SANTO DOMINGO;naco | L96: DISTRITO NACIONAL-SANTO DOMINGO-SANTO DOMINGO DE GUZMAN-naco-Keneddy-1-agencia bella-taller-0-C-8494556004-0-C-8097176004-0-C-0-0 | M96: DISTRITO NACIONAL | N96: SANTO DOMINGO | O96: SANTO DOMINGO DE GUZMAN | P96: naco | Q96: Keneddy | R96: 1 | S96: agencia bella | T96: Taller | U96: 0 | V96: C | W96: 8494556004 | X96: 0 | Y96: C | Z96: 8097176004 | AA96: 0 | AB96: C | AC96: 0 | AD96: 0 | AE96: 45884.619 | AG96: TD- ENTREGADO
A97: 45884 | B97: 4-12194157342 | C97: 45884 | D97: ADALKENNY JIMENEZ LIMA | E97: =VLOOKUP(DataOld!$B97,DATA!B:H,7,FALSE) -> #N/A | F97: =DataOld!$D97=DataOld!$E97 -> #N/A | G97: =VLOOKUP(DataOld!$B97,DATA!B:G,6,FALSE) -> #N/A | H97: 40232724092 | I97: =DataOld!$H97=DataOld!$G97 -> #N/A | J97: 293-OFICINA AGORA MALL | K97: DISTRITO NACIONAL;SANTO DOMINGO;Ensanche la Fe | L97: Distrito Nacional-Santo Domingo-Santo Domingo De Guzman-Ensanche la Fe-Mauricio Baez -225-Ramiluz Montero -225-Frente al garaje Italia-C-8493851220-0-C-8492150818-0-0-0 | M97: DISTRITO NACIONAL | N97: SANTO DOMINGO | O97: SANTO DOMINGO DE GUZMAN | P97: Ensanche la Fe | Q97: Mauricio Baez | R97: 225 | S97: Ramiluz Montero | T97: 225 | U97: Frente al garaje Italia | V97: C | W97: 8493851220 | X97: 0 | Y97: C | Z97: 8492150818 | AA97: 0 | AB97: 0 | AC97: 0 | AE97: 45884.625 | AG97: TD- ENTREGADO
A98: 45884 | B98: 4-12192576932 | C98: 45884 | D98: ROBERT CHRISTOPHER CESPEDES RAMIREZ | E98: =VLOOKUP(DataOld!$B98,DATA!B:H,7,FALSE) -> #N/A | F98: =DataOld!$D98=DataOld!$E98 -> #N/A | G98: =VLOOKUP(DataOld!$B98,DATA!B:G,6,FALSE) -> #N/A | H98: 00119529600 | I98: =DataOld!$H98=DataOld!$G98 -> #N/A | J98: 208-OFICINA PADRE CASTELLANOS | K98: DISTRITO NACIONAL;SANTO DOMINGO;Ensanche luperon | L98: DISTRITO NACIONAL-SANTO DOMINGO-SANTO DOMINGO DE GUZMAN-Ensanche Luperon-23 Este-7-0-0-0-R-8092387049-0-C-8094011898-0-C-0-0 | M98: DISTRITO NACIONAL | N98: SANTO DOMINGO | O98: SANTO DOMINGO DE GUZMAN | P98: Ensanche luperon | Q98: 23 Este | R98: 7 | S98: 0 | T98: 0 | U98: 0 | V98: R | W98: 8092387049 | X98: 0 | Y98: C | Z98: 8094011898 | AA98: 0 | AB98: C | AC98: 0 | AD98: 0 | AE98: 45884.479 | AG98: TD- ENTREGADO
A99: 45884 | B99: 4-12192191732 | C99: 45884 | D99: RUTH DELANIA PEREZ PAYANO | E99: =VLOOKUP(DataOld!$B99,DATA!B:H,7,FALSE) -> #N/A | F99: =DataOld!$D99=DataOld!$E99 -> #N/A | G99: =VLOOKUP(DataOld!$B99,DATA!B:G,6,FALSE) -> #N/A | H99: 40221599182 | I99: =DataOld!$H99=DataOld!$G99 -> #N/A | J99: 204-OFICINA MAXIMO GOMEZ | K99: DISTRITO NACIONAL;SANTO DOMINGO;Los Prados | L99: DISTRITO NACIONAL-SANTO DOMINGO-SANTO DOMINGO DE GUZMAN-Los Prados-Jose Lopez-1-Alarmas 24-RRHH-Edificio Dominican Watchman-C-8295802831-0-C-8492582171-0-C-0-0 | M99: DISTRITO NACIONAL | N99: SANTO DOMINGO | O99: SANTO DOMINGO DE GUZMAN | P99: Los Prados | Q99: Jose Lopez | R99: 1 | S99: Alarmas 24 | T99: RRHH | U99: Edificio Dominican Watchman | V99: C | W99: 8295802831 | X99: 0 | Y99: C | Z99: 8492582171 | AA99: 0 | AB99: C | AC99: 0 | AD99: 0 | AE99: 45884.442 | AG99: TD- ENTREGADO
A100: 45884 | B100: 4-12192926302 | C100: 45884 | D100: ESTAIRY MARIA HERNANDEZ FLORENCIO | E100: =VLOOKUP(DataOld!$B100,DATA!B:H,7,FALSE) -> #N/A | F100: =DataOld!$D100=DataOld!$E100 -> #N/A | G100: =VLOOKUP(DataOld!$B100,DATA!B:G,6,FALSE) -> #N/A | H100: 40233923750 | I100: =DataOld!$H100=DataOld!$G100 -> #N/A | J100: 201-OFICINA VILLA CONSUELO | K100: DISTRITO NACIONAL;SANTO DOMINGO;San Carlos | L100: Distrito Nacional-Santo Domingo-Santo Domingo De Guzman-San Carlos -Benigno del castillo-72-72A-A-Hay una banca loteka abajo -C-8297032271-0-C-8098181870-0-0-0 | M100: DISTRITO NACIONAL | N100: SANTO DOMINGO | O100: SANTO DOMINGO DE GUZMAN | P100: San Carlos | Q100: Benigno del castillo | R100: 72 | S100: 72A | T100: A | U100: Hay una banca loteka abajo | V100: C | W100: 8297032271 | X100: 0 | Y100: C | Z100: 8098181870 | AA100: 0 | AB100: 0 | AC100: 0 | AE100: 45884.505 | AG100: TD- ENTREGADO
...

Sheet Sheet1
A1: FECH ASIG | B1: (All)
A3: Row Labels | B3: Count of ESTATUS
A4: TD- DEVUELTO NO LOCALIZADO | B4: 7
A5: TD- ENTREGADO | B5: 684
A6: EN RUTA | B6: 45
A7: NO LOCALIZADA | B7: 8
A8: Grand Total | B8: 744
A21: Count of ESTATUS | B21: Column Labels
A22: Row Labels | B22: EN RUTA | C22: NO LOCALIZADA | D22: Grand Total
A23: 45922 | B23: 2 | D23: 2
A24: 45925 | B24: 5 | C24: 5 | D24: 10
A25: 45926 | B25: 2 | C25: 1 | D25: 3
A26: 45927 | B26: 4 | D26: 4
A27: 45929 | B27: 5 | C27: 2 | D27: 7
A28: 45930 | B28: 27 | D28: 27
A29: Grand Total | B29: 45 | C29: 8 | D29: 53

Sheet DATA
A1: FECH ASIG | B1: N-SS | C1: TIPO | D1: AREA | E1: SUBAREA | F1: ANALISTA_ASIGNADO | G1: NRO_ID | H1: CONTACTO | I1: NOMBRE_DE_OFICINA | J1: OFICIAL | K1: PROVMUNSEC | L1: DESCRIPCION_AMPLIADA | M1: PROVINCIA | N1: ESTADO | O1: DISTRITO_MUNICIPIAL | P1: SECTOR | Q1: CALLE | R1: NUMERO | S1: EMPRESA_EDIFICIO | T1: DEPTO_APTO | U1: REFERENCIA | V1: TIPO_TEL_1 | W1: TEL_1 | X1: EXT_TEL_1 | Y1: TIPO_TEL_2 | Z1: TEL_2 | AA1: EXT_TEL_2 | AB1: TIPO_TEL_3 | AC1: TEL_3 | AD1: EXT_TEL_3 | AE1: CREADO_POR | AF1: FECHA_CREACION | AG1: ZONA | AH1: STATUS | AI1: COMENTARIO | AJ1: QUIEN RECIBE | AK1: INFO TERCERO | AL1: FECHA DE ENTREGA | AM1: Comentario BPD | AN1: AREAS REMOTAS | AO1: Status Cc | AP1: Contacto Cc | AQ1: No. Contact
A2: 46204 | B2: 4-13794643002 | C2: Cuentas | D2: Solicitud de Servicios | E2: Entrega Tarjeta Debito | F2: U52123 | G2: 05600054539 | H2: NURYS JULISSA ABREU TAVAREZ | I2: 243-OFICINA CALLE DEL SOL, STGO. | J2: U32288 | K2: Santiago;Santiago;Fernndez | L2: Santiago-Santiago-Santiago-Fernndez-Circunvalacion -202-Funpisa-202-Supermercado-C-8092515808-0-C-8298561307-0-T-8092417771-0 | M2: Santiago | N2: Santiago | O2: Santiago | P2: Fernndez | Q2: Circunvalacion | R2: 202 | S2: Funpisa | T2: 202 | U2: Supermercado | V2: C | W2: 8092515808 | X2: 0 | Y2: C | Z2: 8298561307 | AA2: 0 | AB2: T | AC2: 8092417771 | AD2: 0 | AE2: APPPOPULAR | AF2: 46203.679 | AG2: En proceso | AH2: TD- ENTREGADO | AJ2: PRINCIPAL | AL2: 46209 | AO2: Contactos Efectivos | AP2: ENVIO A DIRECCION AL CLIENTE !NPROVINCIA// SANTIANGO DE LOS CABALLEROS !NEMPRESA// VILLA OLIMPICA !NSECTOR// FUNPISA !NCALLE // AV CINCUNVALACION !NDEP// SERVICIO !NREFE// DENTRO DE LA PLAZA FERNANDEZ AL LADO DE SUPERMERCADO LA FUENTE !NTELL/HORA 8092515808 8 AM A 5 PM !NKCRUZ!N!N | AQ2: 8092515808
A3: 46204 | B3: 4-13800808542 | C3: Cuentas | D3: Solicitud de Servicios | E3: Entrega Tarjeta Debito | F3: U52123 | G3: 40224078192 | H3: CRISMARY JIMENEZ GUZMAN | I3: 253-OFICINA PUERTO PLATA | J3: U39793 | K3: Puerto Plata;Sosua;El choco | L3: Puerto Plata-Sosua-Sosua-El choco-Carretera el choco-0-Casa linda-Arq-Arquitectura -C-8295521220-0-T-8095711190-221-0-0 | M3: Puerto Plata | N3: Sosua | O3: Sosua | P3: El choco | Q3: Carretera el choco | R3: 0 | S3: Casa linda | T3: arq | U3: Arquitectura | V3: C | W3: 8295521220 | X3: 0 | Y3: T | Z3: 8095711190 | AA3: 221 | AB3: 0 | AC3: 0 | AE3: APPPOPULAR | AF3: 46204.54 | AG3: En proceso | AH3: TD- ENTREGADO | AJ3: PRINCIPAL | AL3: 46216 | AN3: SI | AO3: Contactos Efectivos | AP3: POERTO PLATA//SOSUA!NCALLE CARRE EL CHOCO !NResidencial Casa Linda!NDP// Arquitectura !NREF/Sosua Ocean Village!N8295521220 HORA 8 A 5 !NJRAMOS | AQ3: 8295521220
A4: 46204 | B4: 4-13798526962 | C4: Cuentas | D4: Solicitud de Servicios | E4: Entrega Tarjeta Debito | F4: U52123 | G4: 03200219420 | H4: MIGUELINA SANTANA RAMOS | I4: 246-OFICINA ZONA FRANCA, STGO. | J4: U35634 | K4: SANTIAGO;SANTIAGO;ZonaFrancaIndustrial | L4: SANTIAGO-SANTIAGO-SANTIAGO-ZonaFrancaIndustrial-Av Longitudinal-28-Eaton Aerospace Souriau-Servicio-2da Etapa cerca Los Bomberos-C-8099033339-0-T-8096252000-0-C-0-0 | M4: Santiago | N4: Santiago | O4: Santiago | P4: ZonaFrancaIndustrial | Q4: Av longitudinal | R4: 28 | S4: Eaton Aerospace Souriau | T4: Servicio | U4: 2da Etapa cerca Los Bomberos | V4: C | W4: 8099033339 | X4: 0 | Y4: T | Z4: 8096252000 | AA4: 0 | AB4: C | AC4: 0 | AD4: 0 | AE4: APPPOPULAR | AF4: 46204.414 | AG4: En proceso | AH4: TD- ENTREGADO | AJ4: PRINCIPAL | AL4: 46209 | AO4: Contactos Efectivos | AP4: ENVIAR A DIRECCION CLIENTE!NOGUTIERREZ!N!NSANTIAGO!NSECT//ZONA FRANCA INDUSTRIAL!NCALLE//AV LONGITUDINAL NO 28!NEMPRESAS//EATON AEROSPACCE SOURIAU!NDEP//SERVICIO !NREF// PROXIMO A LOS BOMBEROS !N8099033339 HORA 8AM A 5PM !NDISPONIBLE EL LUNES | AQ4: 8099033339
A5: 46205 | B5: 4-13806004192 | C5: Cuentas | D5: Solicitud de Servicios | E5: Entrega Tarjeta Debito | F5: U52123 | G5: 03101913196 | H5: MARIA ANTONIA DE JESUS MUESES E DE CANAHUAT | I5: 244-OFICINA 27 DE FEBRERO, STGO. | J5: U19099 | K5: Santiago;Santiago;Los jardines | L5: SANTIAGO-SANTIAGO-SANTIAGO-Los Jardines-Aquiles Ramirez-17-0-0-Cancha CDP-C-8096961118-0-R-8095826834-0-C-8096961119-0 | M5: Santiago | N5: Santiago | O5: Santiago | P5: Los jardines | Q5: Aquiles Ramirez | R5: 17 | S5: 0 | T5: 0 | U5: Cancha CDP | V5: C | W5: 8096961118 | X5: 0 | Y5: R | Z5: 8095826834 | AA5: 0 | AB5: C | AC5: 8096961119 | AD5: 0 | AE5: APPPOPULAR | AF5: 46205.319 | AG5: En proceso | AH5: TD- ENTREGADO | AJ5: PRINCIPAL | AL5: 46210 | AO5: Contactos Efectivos | AP5: SATIAGO !NLOS JARDINES METROPOLITANOS !NCALLE AQUILES RAMIREZ !NCASA NO 17!NPROX AL CLUB DOMINGO PAULINO !N8096961118 HORA 3PM A 5PM !NAOGANDO | AQ5: 8096961118
A6: 46205 | B6: 4-13805664032 | C6: Cuentas | D6: Solicitud de Servicios | E6: Entrega Tarjeta Debito | F6: U52123 | G6: 03105743565 | H6: RAILYN ISMAEL PAULINO BALBUENA | I6: 458-OFICINA MULTICENTRO LA SIRENA EL EMBRUJO STGO | J6: U22429 | K6: Santiago;Santiago;Hato del Yaque | L6: Santiago-Santiago-Santiago-Hato Del Yaque-La Paz -40-0-0-Estudio de grabacin-C-8299804858-0-C-8299804852-0-0-0 | M6: Santiago | N6: Santiago | O6: Santiago | P6: Hato del Yaque | Q6: la paz | R6: 40 | S6: 0 | T6: 0 | U6: Estudio de grabacin | V6: C | W6: 8299804858 | X6: 0 | Y6: C | Z6: 8299804852 | AA6: 0 | AB6: 0 | AC6: 0 | AE6: APPPOPULAR | AF6: 46204.992 | AG6: En proceso | AH6: TD- DEVUELTO NO LOCALIZADO | AI6: no responde ws ni llamadas | AJ6: PRINCIPAL
A7: 46205 | B7: 4-13802824452 | C7: Cuentas | D7: Solicitud de Servicios | E7: Entrega Tarjeta Debito | F7: U46603 | G7: 40212318824 | H7: EMELY MELISSA PICHARDO CASTILLO | I7: OFICINA DOWNTOWN CENTER MALL | K7: Santiago;Santiago;Arroyo hondo abajo | L7: SANTIAGO-SANTIAGO-SANTIAGO-ARROYO HONDO ABAJO-MARIA TRINIDAD SANCHEZ-17-0-0-AL LADO DE COLMADO MARLIN -C-8297523579-0-T-8494288039- | M7: Santiago | N7: Santiago | O7: Santiago | P7: Arroyo hondo abajo | Q7: Maria trinidad sanch | R7: 17 | S7: 0 | T7: 0 | U7: AL LADO DE COLMADO MARLIN | V7: C | W7: 8297523579 | X7: 0 | Y7: T | Z7: 8494288039 | AE7: APPPOPULAR | AF7: 46204.636 | AG7: En proceso | AH7: TD- ENTREGADO | AJ7: PRINCIPAL | AL7: 46209 | AO7: Contactos Efectivos | AP7: ENVIO A DIRECCION AL CLIENTE !NPROVINCIA//SANTIAGO DE CABALLEROS !NSECTOR// ARROYO HONDO ABAJO !NREFE// AL LADO DE COLMADO MARLIN!NCALLE// MARIA TRINIDAD SANCHEZ NO 17!NTELL//HORA 8297523579 8 AM A 5 PM !NRECIBIRA// MELISSA!NKCRUZ!N | AQ7: 8297523579
A8: 46205 | B8: 4-13805672272 | C8: Cuentas | D8: Solicitud de Servicios | E8: Entrega Tarjeta Debito | F8: U52123 | G8: 40218265987 | H8: ROIDANYS DE LOS SANTOS CRUZ | I8: 245-OFICINA RESTAURACION | J8: U38516 | K8: Santiago;Santiago;Hato del Yaque | L8: Santiago-Santiago-Santiago-Hato del Yaque -Calle 7 la mina -56-0-0-Por el taller de Fili-C-8493952210-0-C-8494097927-0-0-0 | M8: Santiago | N8: Santiago | O8: Santiago | P8: Hato del Yaque | Q8: Calle 7 la mina | R8: 56 | S8: 0 | T8: 0 | U8: Por el taller de Fili | V8: C | W8: 8493952210 | X8: 0 | Y8: C | Z8: 8494097927 | AA8: 0 | AB8: 0 | AC8: 0 | AE8: APPPOPULAR | AF8: 46204.958 | AG8: En proceso | AH8: TD- ENTREGADO | AJ8: PRINCIPAL | AL8: 46210
A9: 46205 | B9: 4-13805247502 | C9: Cuentas | D9: Solicitud de Servicios | E9: Entrega Tarjeta Debito | F9: U46603 | G9: 40215703063 | H9: CESAR LEONCIO REYES MEJIA | I9: OFICINA DOWNTOWN CENTER MALL | K9: Santiago;Santiago;Mejoramiento social | L9: SANTIAGO-SANTIAGO-SANTIAGO-MEJORAMIENTO SOCIAL-LA FUENTE CASA-16-0-0-DENISES-C-8294909466-0-C-8494487694-0 | M9: Santiago | N9: Santiago | O9: Santiago | P9: Mejoramiento social | Q9: LA FUENTE CASA | R9: 16 | S9: 0 | T9: 0 | U9: DENISES | V9: C | W9: 8294909466 | X9: 0 | Y9: C | Z9: 8494487694 | AA9: 0 | AE9: APPPOPULAR | AF9: 46204.822 | AG9: En proceso | AH9: TD- DEVUELTO NO LOCALIZADO | AJ9: PRINCIPAL
A10: 46205 | B10: 4-13809606032 | C10: Cuentas | D10: Solicitud de Servicios | E10: Entrega Tarjeta Debito | F10: APPPOPULAR | G10: 03105181071 | H10: ANTHONY DE JESUS HERNANDEZ ESTEVEZ | I10: 259-OFICINA UTESA, SANTIAGO | J10: U37650 | K10: Santiago;Santiago;Ensanche Espaillat | L10: SANTIAGO-SANTIAGO-SANTIAGO-ensanche espaillat-12-78-0-0-0-C-8492200921-0-C-8297262494-0-C-0-0 | M10: SANTIAGO | N10: Santiago | O10: Santiago | P10: Ensanche Espaillat | Q10: 12 | R10: 78 | S10: 0 | T10: 0 | U10: 0 | V10: C | W10: 8492200921 | X10: 0 | Y10: C | Z10: 8297262494 | AA10: 0 | AB10: C | AC10: 0 | AD10: 0 | AE10: APPPOPULAR | AF10: 46205.551 | AG10: En proceso | AH10: TD- ENTREGADO | AJ10: PRINCIPAL | AL10: 46209
A11: 46205 | B11: 4-13809476302 | C11: Cuentas | D11: Solicitud de Servicios | E11: Entrega Tarjeta Debito | F11: APPPOPULAR | G11: 40230381366 | H11: PABLO DANIEL PEREZ ROSA | I11: 199-OFICINA DUARTE | J11: U41438 | K11: SANTIAGO;BISONO;MINERVA O SIMON BOLI | L11: SANTIAGO-BISONO-BISONO-MINERVA O SIMON BOLIVAR-LAS AMERCA CASA--0-0-0-C-8295322044-0-C-8494318168-0 | M11: SANTIAGO | N11: Bisono | O11: Bisono | P11: MINERVA O SIMON BOLI | Q11: LAS AMERCA CASA | S11: 0 | T11: 0 | U11: 0 | V11: C | W11: 8295322044 | X11: 0 | Y11: C | Z11: 8494318168 | AA11: 0 | AE11: APPPOPULAR | AF11: 46205.533 | AG11: En proceso | AH11: TD- ENTREGADO | AI11: Josue | AJ11: PRINCIPAL | AK11: Josue | AL11: 46218 | AN11: SI
A12: 46206 | B12: 4-13813809882 | C12: Cuentas | D12: Solicitud de Servicios | E12: Entrega Tarjeta Debito | F12: U46603 | G12: 03103439901 | H12: CARMEN ALEJANDRINA DELGADO RAMOS | I12: 243-OFICINA CALLE DEL SOL, STGO. | J12: U46454 | K12: Santiago;Santiago;La Rosaleda | L12: SANTIAGO-SANTIAGO-SANTIAGO-La Rosaleda-Juan Lockward-5-Edificio GVVI-C1-Cerca Cine Hollywood-C-8098201516-0-R-8099712341-0-C-0-0 | M12: Santiago | N12: Santiago | O12: Santiago | P12: La Rosaleda | Q12: Juan Lockward | R12: 5 | S12: Edificio GVVI | T12: C1 | U12: Cerca Cine Hollywood | V12: C | W12: 8098201516 | X12: 0 | Y12: R | Z12: 8099712341 | AA12: 0 | AB12: C | AC12: 0 | AD12: 0 | AE12: APPPOPULAR | AF12: 46206.287 | AG12: En proceso | AH12: TD- ENTREGADO | AJ12: PRINCIPAL | AL12: 46209
A13: 46206 | B13: 4-13813573252 | C13: Cuentas | D13: Solicitud de Servicios | E13: Entrega Tarjeta Debito | F13: U46603 | G13: 35000012985 | H13: JUAN ENMANUEL GUZMAN GUZMAN | I13: 458-OFICINA MULTICENTRO LA SIRENA EL EMBRUJO STGO | J13: U22429 | K13: Santiago;Santiago;Baracoa | L13: SANTIAGO-SANTIAGO-SANTIAGO-BARACOA-principal-11-0-0-Al lado de one tech-C-8494594908-0-R-8093951274-0 | M13: Santiago | N13: Santiago | O13: Santiago | P13: Baracoa | Q13: Principal | R13: 11 | S13: 0 | T13: 0 | U13: Al lado de one tech | V13: C | W13: 8494594908 | X13: 0 | Y13: R | Z13: 8093951274 | AA13: 0 | AE13: APPPOPULAR | AF13: 46205.96 | AG13: En proceso | AH13: TD- ENTREGADO | AJ13: PRINCIPAL | AL13: 46209
A14: 46206 | B14: 4-13813346882 | C14: Cuentas | D14: Solicitud de Servicios | E14: Entrega Tarjeta Debito | F14: U52123 | G14: 40219093172 | H14: NOELIA RAQUEL CASTANEDA SANTIAGO | I14: 349-OFICINA SANTIAGO CENTER | J14: U40202 | K14: Santiago;Santiago;Yapurt Dumit | L14: Santiago-Santiago-Santiago-Yapurt dumit -Margarita-0-Casa crema con blanco -Casa 36-Al lado del hospital hemmi-C-8092145237-0-C-8092191453-0-0-0 | M14: Santiago | N14: Santiago | O14: Santiago | P14: Yapurt Dumit | Q14: Margarita | R14: 0 | S14: Casa crema con blanco | T14: Casa 36 | U14: Al lado del hospital hemmi | V14: C | W14: 8092145237 | X14: 0 | Y14: C | Z14: 8092191453 | AA14: 0 | AB14: 0 | AC14: 0 | AE14: APPPOPULAR | AF14: 46205.899 | AG14: En proceso | AH14: TD- ENTREGADO | AJ14: PRINCIPAL | AL14: 46209
A15: 46206 | B15: 4-13811310822 | C15: Cuentas | D15: Solicitud de Servicios | E15: Entrega Tarjeta Debito | F15: APPPOPULAR | G15: 40220154260 | H15: GINNETTE LOUISE BENOIT CABRERA | I15: 246-OFICINA ZONA FRANCA, STGO. | J15: U38309 | K15: Santiago;Santiago;Los salados viejos | L15: Santiago-Santiago-Santiago-Los salados viejos -15 no 25-25-0-0-8092722170-C-8092722170-0-C-8297597471-0-0-0 | M15: Santiago | N15: Santiago | O15: Santiago | P15: Los salados viejos | Q15: 15 no 25 | R15: 25 | S15: 0 | T15: 0 | U15: 8092722170 | V15: C | W15: 8092722170 | X15: 0 | Y15: C | Z15: 8297597471 | AA15: 0 | AB15: 0 | AC15: 0 | AE15: APPPOPULAR | AF15: 46205.646 | AG15: En proceso | AH15: TD- ENTREGADO | AJ15: PRINCIPAL | AL15: 46210
A16: 46206 | B16: 4-13811370422 | C16: Cuentas | D16: Solicitud de Servicios | E16: Entrega Tarjeta Debito | F16: APPPOPULAR | G16: 40225954995 | H16: GENESIS VILLANUEVA | I16: 135-OFICINA TORRE POPULAR | J16: U24107 | K16: Santiago;Santiago;Valle Verde 1 | L16: Santiago-Santiago-Santiago-Valle Verde 1 -Calle 8-15-0-0-0-C-8094205672-0-C-8099759239-0-0-0 | M16: Santiago | N16: Santiago | O16: Santiago | P16: Valle Verde 1 | Q16: Calle 8 | R16: 15 | S16: 0 | T16: 0 | U16: 0 | V16: C | W16: 8094205672 | X16: 0 | Y16: C | Z16: 8099759239 | AA16: 0 | AB16: 0 | AC16: 0 | AE16: APPPOPULAR | AF16: 46205.65 | AG16: En proceso | AH16: TD- ENTREGADO | AJ16: PRINCIPAL | AL16: 46227
A17: 46206 | B17: 4-13817129792 | C17: Cuentas | D17: Solicitud de Servicios | E17: Entrega Tarjeta Debito | F17: APPPOPULAR | G17: 40235504715 | H17: FAUSTINA DE LEON RAMON | I17: 246-OFICINA ZONA FRANCA, STGO. | J17: U50597 | K17: Santiago;Santiago;Mella 2 | L17: SANTIAGO-SANTIAGO-SANTIAGO-mella 2-6-2-ensima del colmado gonzal-2-ensima del colmado gonzales-C-8293901833-0-C-8294552092-0-C-0-0 | M17: Santiago | N17: Santiago | O17: Santiago | P17: Mella 2 | Q17: 6 | R17: 2 | S17: ensima del colmado gonzal | T17: 2 | U17: ensima del colmado gonzales | V17: C | W17: 8293901833 | X17: 0 | Y17: C | Z17: 8294552092 | AA17: 0 | AB17: C | AC17: 0 | AD17: 0 | AE17: APPPOPULAR | AF17: 46206.568 | AG17: En proceso | AH17: TD- ENTREGADO | AJ17: PRINCIPAL | AL17: 46210
A18: 46206 | B18: 4-13814200352 | C18: Cuentas | D18: Solicitud de Servicios | E18: Entrega Tarjeta Debito | F18: U46603 | G18: 40214722858 | H18: ENGER RODRIGUEZ | I18: 290-OFICINA GURABO | J18: U43122 | K18: Santiago;Santiago;Bella vista | L18: Santiago-Santiago-Santiago-Bella vista-Calle marginal -3-Apto A3-A3-Arriba de tienda camalenjea-C-8494480110-0-C-8092010524-0-0-0 | M18: Santiago | N18: Santiago | O18: Santiago | P18: Bella vista | Q18: Calle marginal | R18: 3 | S18: Apto A3 | T18: A3 | U18: Arriba de tienda camalenjea | V18: C | W18: 8494480110 | X18: 0 | Y18: C | Z18: 8092010524 | AA18: 0 | AB18: 0 | AC18: 0 | AE18: APPPOPULAR | AF18: 46206.387 | AG18: En proceso | AH18: TD- ENTREGADO | AJ18: PRINCIPAL | AL18: 46209
A19: 46204 | B19: 4-13796626732 | C19: Cuentas | D19: Solicitud de Servicios | E19: Entrega Tarjeta Debito | F19: U52123 | G19: 40212883371 | H19: SMAILY REYES ROSARIO | I19: OFICINA DOWNTOWN CENTER MALL | K19: DISTRITO NACIONAL;SANTO DOMINGO;los Alcarrizos klm14 | L19: DISTRITO NACIONAL-SANTO DOMINGO-SANTO DOMINGO DE GUZMAN-los Alcarrizos klm14-calle los triste-01-0-0-después del mocano mofongo-C-8296493323-0-C-8098693622-0-C-0-0 | M19: Distrito Nacional | N19: Santo Domingo | O19: Santo Domingo De Guzman | P19: los Alcarrizos klm14 | Q19: calle los triste | R19: 01 | S19: 0 | T19: 0 | U19: después del mocano mofongo | V19: C | W19: 8296493323 | X19: 0 | Y19: C | Z19: 8098693622 | AA19: 0 | AB19: C | AC19: 0 | AD19: 0 | AE19: APPPOPULAR | AF19: 46203.879 | AG19: En proceso | AH19: TD- ENTREGADO | AI19: Charina Mendez | AJ19: PRINCIPAL | AL19: 46205
A20: 46204 | B20: 4-13796292932 | C20: Cuentas | D20: Solicitud de Servicios | E20: Entrega Tarjeta Debito | F20: U52123 | G20: 40200476733 | H20: JESSICA MARIEL DE LA HOZ NUNEZ | I20: 142-OFICINA NUÑEZ DE CACERES | J20: U30387 | K20: Distrito Nacional;Santo Domingo;Los alcarrizos | L20: Distrito Nacional-Santo Domingo-Santo Domingo De Guzman-Los alcarrizos -Calle triste -1-Mercatodo -Recepcin-Detrs de Agroindustrial-C-8296901595-0-C-8099731605-0-0-0 | M20: Distrito Nacional | N20: Santo Domingo | O20: Santo Domingo De Guzman | P20: Los alcarrizos | Q20: Calle triste | R20: 1 | S20: Mercatodo | T20: Recepcin | U20: Detrs de Agroindustrial | V20: C | W20: 8296901595 | X20: 0 | Y20: C | Z20: 8099731605 | AA20: 0 | AB20: 0 | AC20: 0 | AE20: APPPOPULAR | AF20: 46203.854 | AG20: En proceso | AH20: TD- ENTREGADO | AI20: Charina Mendez | AJ20: PRINCIPAL | AL20: 46205
A21: 46209 | B21: 4-13823892552 | C21: Cuentas | D21: Solicitud de Servicios | E21: Entrega Tarjeta Debito | F21: APPPOPULAR | G21: 40255006179 | H21: ENMANUEL GONZALEZ FERRERAS | I21: 246-OFICINA ZONA FRANCA, STGO. | J21: U38309 | K21: Santiago;Santiago;Rafey | L21: Santiago-Santiago-Santiago-Rafey-Calle Central 3 -3-Sewn product inc -almacn-0-C-8093912203-0-C-8297200948-0-0-0 | M21: Santiago | N21: Santiago | O21: Santiago | P21: Rafey | Q21: Calle Central 3 | R21: 3 | S21: Sewn product inc | T21: Almacn | U21: 0 | V21: C | W21: 8093912203 | X21: 0 | Y21: C | Z21: 8297200948 | AA21: 0 | AB21: 0 | AC21: 0 | AE21: APPPOPULAR | AF21: 46208.882 | AG21: En proceso | AH21: TD- ENTREGADO | AI21: Posiblemente entregada | AJ21: PRINCIPAL | AL21: 46218
A22: 46209 | B22: 4-13823928972 | C22: Cuentas | D22: Solicitud de Servicios | E22: Entrega Tarjeta Debito | F22: APPPOPULAR | G22: 40209968730 | H22: YOSELIN DE LA ROSA DE AZA | I22: 246-OFICINA ZONA FRANCA, STGO. | J22: U45679 | K22: SANTIAGO;SANTIAGO;ensanche espallat | L22: SANTIAGO-SANTIAGO-SANTIAGO-ensanche espallat-10 esquina 8-56-0-0-0-C-8297124941-0-C-8298806674-0-C-0-0 | M22: Santiago | N22: Santiago | O22: Santiago | P22: ensanche espallat | Q22: 10 esquina 8 | R22: 56 | S22: 0 | T22: 0 | U22: 0 | V22: C | W22: 8297124941 | X22: 0 | Y22: C | Z22: 8298806674 | AA22: 0 | AB22: C | AC22: 0 | AD22: 0 | AE22: APPPOPULAR | AF22: 46208.718 | AG22: En proceso | AH22: TD- ENTREGADO | AJ22: PRINCIPAL | AL22: 46213
A23: 46209 | B23: 4-13823797392 | C23: Cuentas | D23: Solicitud de Servicios | E23: Entrega Tarjeta Debito | F23: APPPOPULAR | G23: 40218287643 | H23: ARGENIDY VASQUEZ GARCIA | I23: OFICINA DOWNTOWN CENTER MALL | K23: Santiago;Santiago;Ensanche libertad | L23: SANTIAGO-SANTIAGO-SANTIAGO-ENSANCHE LIBERTAD-VILLA ROSA 1 CALLE-6-0-0-METALERA RICARDO PISTA NUEVA -C-8292480942-0-C-8292948668-0 | M23: Santiago | N23: Santiago | O23: Santiago | P23: Ensanche libertad | Q23: VILLA ROSA 1 CALLE | R23: 6 | S23: 0 | T23: 0 | U23: METALERA RICARDO PISTA NUEVA | V23: C | W23: 8292480942 | X23: 0 | Y23: C | Z23: 8292948668 | AA23: 0 | AE23: APPPOPULAR | AF23: 46208.581 | AG23: En proceso | AH23: TD- ENTREGADO | AJ23: PRINCIPAL | AL23: 46213
A24: 46209 | B24: 4-13823739162 | C24: Cuentas | D24: Solicitud de Servicios | E24: Entrega Tarjeta Debito | F24: APPPOPULAR | G24: 00119476687 | H24: JORGE MANUEL LAUREANO | I24: OFICINA DOWNTOWN CENTER MALL | K24: SANTIAGO;SANTIAGO;ESPAILLAT | L24: SANTIAGO-SANTIAGO-SANTIAGO-ESPAILLAT-CENTRAL CASA-27-0-0-COMPRAVENTA FEDERICO-C-8094161920-0-C-8492807169-0 | M24: Santiago | N24: Santiago | O24: Santiago | P24: Espaillat | Q24: CENTRAL CASA | R24: 27 | S24: 0 | T24: 0 | U24: COMPRAVENTA FEDERICO | V24: C | W24: 8094161920 | X24: 0 | Y24: C | Z24: 8492807169 | AA24: 0 | AE24: APPPOPULAR | AF24: 46208.571 | AG24: En proceso | AH24: TD- ENTREGADO | AI24: Josue | AJ24: PRINCIPAL | AK24: Josue | AL24: 46223
A25: 46209 | B25: 4-13823734982 | C25: Cuentas | D25: Solicitud de Servicios | E25: Entrega Tarjeta Debito | F25: APPPOPULAR | G25: 40232829503 | H25: RICARDO ALFONSO MORA GARCIA | I25: OFICINA DOWNTOWN CENTER MALL | K25: Santiago;Santiago;Ensanche libertad | L25: SANTIAGO-SANTIAGO-SANTIAGO-ENSANCHE LIBERTAD-CASA 36 CALLE-13-0-0-METALERA RICARDO PISTA MUEVA-C-8292948668-0-C-8297122282-0 | M25: Santiago | N25: Santiago | O25: Santiago | P25: Ensanche libertad | Q25: CASA 36 CALLE | R25: 13 | S25: 0 | T25: 0 | U25: METALERA RICARDO PISTA MUEVA | V25: C | W25: 8292948668 | X25: 0 | Y25: C | Z25: 8297122282 | AA25: 0 | AE25: APPPOPULAR | AF25: 46208.555 | AG25: En proceso | AH25: TD- ENTREGADO | AJ25: PRINCIPAL | AL25: 46213
A26: 46209 | B26: 4-13823548252 | C26: Cuentas | D26: Solicitud de Servicios | E26: Entrega Tarjeta Debito | F26: APPPOPULAR | G26: 40204763094 | H26: DARLENYS MARIA ESPINO PEREZ | I26: OFICINA DOWNTOWN CENTER MALL | K26: Santiago;Santiago;Cerros de Gurabo | L26: Santiago-Santiago-Santiago-Cerros de gurabo-Av 27 de febrero-1-Mr Grilled-Mr GRILLED-Frente a los cerros de gurab-C-8496548184-0-T-8099713021-0-0-0 | M26: Santiago | N26: Santiago | O26: Santiago | P26: Cerros de Gurabo | Q26: Av 27 de febrero | R26: 1 | S26: Mr Grilled | T26: Mr GRILLED | U26: Frente a los cerros de gurab | V26: C | W26: 8496548184 | X26: 0 | Y26: T | Z26: 8099713021 | AA26: 0 | AB26: 0 | AC26: 0 | AE26: APPPOPULAR | AF26: 46208.348 | AG26: En proceso | AH26: TD- ENTREGADO | AJ26: PRINCIPAL | AL26: 46213
A27: 46209 | B27: 4-13823429012 | C27: Cuentas | D27: Solicitud de Servicios | E27: Entrega Tarjeta Debito | F27: APPPOPULAR | G27: 40237302605 | H27: RICHARD ENMANUEL PENA NIVAR | I27: 266-OFICINA AV. JUAN PABLO DUARTE | J27: U28485 | K27: Santiago;Santiago;Nibaje | L27: SANTIAGO-SANTIAGO-SANTIAGO-Nibaje-3-36-0-0-Cerca de Coraasan-C-8292898501-0-C-8096046979-0-C-0-0 | M27: Santiago | N27: Santiago | O27: Santiago | P27: Nibaje | Q27: 3 | R27: 36 | S27: 0 | T27: 0 | U27: Cerca de Coraasan | V27: C | W27: 8292898501 | X27: 0 | Y27: C | Z27: 8096046979 | AA27: 0 | AB27: C | AC27: 0 | AD27: 0 | AE27: APPPOPULAR | AF27: 46208.185 | AG27: En proceso | AH27: TD- ENTREGADO | AJ27: PRINCIPAL | AL27: 46212
A28: 46204 | B28: 4-13796423192 | C28: Cuentas | D28: Solicitud de Servicios | E28: Entrega Tarjeta Debito | F28: U52123 | G28: 02600166504 | H28: ROSELY MARTINEZ G DE BERGES | I28: SUCURSAL MULTIPLAZA LA ROMANA | J28: U22711 | K28: La Romana;La Romana;Romana del Oeste | L28: LA ROMANA-LA ROMANA-LA ROMANA-Romana del Oeste-10-42-0-0-detras del edificio Cristal-R-8095501665-0-T-8293447581-0-T-8094810717-0 | M28: La Romana | N28: LA ROMANA | O28: La Romana | P28: Romana del Oeste | Q28: 10 | R28: 42 | S28: 0 | T28: 0 | U28: detras del edificio Cristal | V28: R | W28: 8095501665 | X28: 0 | Y28: T | Z28: 8293447581 | AA28: 0 | AB28: T | AC28: 8094810717 | AD28: 0 | AE28: APPPOPULAR | AF28: 46203.93 | AG28: En proceso | AH28: TD- ENTREGADO | AJ28: PRINCIPAL | AL28: 46205
A29: 46204 | B29: 4-13796423072 | C29: Cuentas | D29: Solicitud de Servicios | E29: Entrega Tarjeta Debito | F29: U52123 | G29: 02601424076 | H29: JESSICA QUEZADA PEREZ | I29: 337-OFICINA HIPERJUMBO LA ROMANA | J29: U29844 | K29: La Romana;La Romana;Batey Principal | L29: La Romana-La Romana-La Romana-Batey Principal - primera-01-Central Romana -Compras-Frente hospital -C-8497524225-0-C-8498555617-0-0-0 | M29: La Romana | N29: LA ROMANA | O29: La Romana | P29: Batey Principal | Q29: Primera | R29: 01 | S29: Central Romana | T29: Compras | U29: Frente hospital | V29: C | W29: 8497524225 | X29: 0 | Y29: C | Z29: 8498555617 | AA29: 0 | AB29: 0 | AC29: 0 | AE29: APPPOPULAR | AF29: 46203.911 | AG29: En proceso | AH29: TD- ENTREGADO | AJ29: PRINCIPAL | AL29: 46204
A30: 46209 | B30: 4-13819149252 | C30: Cuentas | D30: Solicitud de Servicios | E30: Entrega Tarjeta Debito | F30: APPPOPULAR | G30: 03104823111 | H30: MARIELA LOPEZ SANTANA | I30: 290-OFICINA GURABO | J30: U24448 | K30: Santiago;Santiago;Llanos de Gurabo | L30: Santiago-Santiago-Santiago-Llanos de Gurabo-Calle 10 -0-RyL XV -F1-0-C-8098564742-0-C-8097103340-0-0-0 | M30: Santiago | N30: Santiago | O30: Santiago | P30: Llanos de Gurabo | Q30: Calle 10 | R30: 0 | S30: RyL XV | T30: F1 | U30: 0 | V30: C | W30: 8098564742 | X30: 0 | Y30: C | Z30: 8097103340 | AA30: 0 | AB30: 0 | AC30: 0 | AE30: APPPOPULAR | AF30: 46206.687 | AG30: En proceso | AH30: TD- ENTREGADO | AJ30: PRINCIPAL | AL30: 46213
A31: 46209 | B31: 4-13823180452 | C31: Cuentas | D31: Solicitud de Servicios | E31: Entrega Tarjeta Debito | F31: APPPOPULAR | G31: 03105419331 | H31: MICHEL NATALI LOPEZ GUZMAN | I31: MODELO PREFERENTE | J31: U35981 | K31: SANTIAGO;SANTIAGO;el paraiso | L31: SANTIAGO-SANTIAGO-SAN FRANCISCO DE JACAGUA-el paraiso-calle 8 casa 8-08-0-0-entrando por el puesto de ma-C-8492820062-0-C-8299904688-0-C-0-0 | M31: Santiago | N31: Santiago | O31: SAN FRANCISCO DE JACAGUA | P31: El Paraiso | Q31: calle 8 casa 8 | R31: 08 | S31: 0 | T31: 0 | U31: entrando por el puesto de ma | V31: C | W31: 8492820062 | X31: 0 | Y31: C | Z31: 8299904688 | AA31: 0 | AB31: C | AC31: 0 | AD31: 0 | AE31: APPPOPULAR | AF31: 46207.849 | AG31: En proceso | AH31: TD- ENTREGADO | AJ31: PRINCIPAL | AL31: 46213
A32: 46204 | B32: 4-13795808432 | C32: Cuentas | D32: Solicitud de Servicios | E32: Entrega Tarjeta Debito | F32: U52123 | G32: 40210326407 | H32: BRYANT CAPARROSA MORENO | I32: OFICINA DOWNTOWN CENTER MALL | K32: La Romana;La Romana;Katanga | L32: LA ROMANA-LA ROMANA-LA ROMANA-KATANGA-SANTA LUISA DE MARILLA-10-0-0-ESCUELA DE MANEJO JONAHTAN-C-8295125396-0-C-8097878547-0 | M32: La Romana | N32: LA ROMANA | O32: La Romana | P32: Katanga | Q32: SANTA LUISA DE MARIL | R32: 10 | S32: 0 | T32: 0 | U32: ESCUELA DE MANEJO JONAHTAN | V32: C | W32: 8295125396 | X32: 0 | Y32: C | Z32: 8097878547 | AA32: 0 | AE32: APPPOPULAR | AF32: 46203.738 | AG32: En proceso | AH32: TD- ENTREGADO | AI32: Gabriel | AJ32: PRINCIPAL | AL32: 46209 | AO32: Contactos Efectivos | AP32: !NENVIO A RESIDENCIA!NPROVINCIA // SANTO DOMINGO ESTE !N SECTOR// BARRIO KATANGA !NCALLE// STA LUISA DE MARILLAC !NNO.// 10!NREFE// PROXIMO A FUNDAION ANGELICA MATILDE BUGUE!NHORA// 8AM A 5PM !NTELE//8097878547!NCOMISCAT | AQ32: 8295125396
A33: 46204 | B33: 4-13796934212 | C33: Cuentas | D33: Solicitud de Servicios | E33: Entrega Tarjeta Debito | F33: U52123 | G33: 03701218830 | H33: YANELY SANTANA ALMONTE | I33: 253-OFICINA PUERTO PLATA | J33: U39793 | K33: Puerto Plata;Puerto Plata;Los limones | L33: Puerto Plata-Puerto Plata-Puerto Plata-Los limones-9 esquina 11-20-0-0-Segundo nivel-C-8298895049-0-R-8092616498-0-0-0 | M33: PUERTO PLATA | N33: Puerto Plata | O33: Puerto Plata | P33: Los limones | Q33: 9 esquina 11 | R33: 20 | S33: 0 | T33: 0 | U33: Segundo nivel | V33: C | W33: 8298895049 | X33: 0 | Y33: R | Z33: 8092616498 | AA33: 0 | AB33: 0 | AC33: 0 | AE33: APPPOPULAR | AF33: 46203.874 | AG33: En proceso | AH33: TD- ENTREGADO | AJ33: PRINCIPAL | AL33: 46209 | AO33: Contactos Efectivos | AP33: PROV//PUERTO PLATA!NSECTOR//URB GINEGRA ARZENO!NCALLE//9!NNUM CASA//20!NREFERENCIA//PROXIMO COLMADO ROQUE!NHORA//8AM A 5PM!NTELL//8298895049!N!NVA A RECIBIR SU SUEGRA VICENTA!N!NHMONTERO!N | AQ33: 8298895049
A34: 46204 | B34: 4-13793802862 | C34: Cuentas | D34: Solicitud de Servicios | E34: Entrega Tarjeta Debito | F34: U46603 | G34: 40259619480 | H34: JOSE FABIAN MELO | I34: OFICINA DOWNTOWN CENTER MALL | K34: PUERTO PLATA;LUPERON;LUPERON O CENTRO DEL | L34: PUERTO PLATA-LUPERON-LUPERON-LUPERON O CENTRO DEL PUEBLO-ENRIQUILLO-5-0-0-ENRIQUILLO 5-C-8296340375-0-C-8292570826-0 | M34: PUERTO PLATA | N34: Luperon | O34: Luperon | P34: LUPERON O CENTRO DEL | Q34: Enriquillo | R34: 5 | S34: 0 | T34: 0 | U34: ENRIQUILLO 5 | V34: C | W34: 8296340375 | X34: 0 | Y34: C | Z34: 8292570826 | AA34: 0 | AE34: APPPOPULAR | AF34: 46203.633 | AG34: En proceso | AH34: TD- ZONA FUERA DE COBERTURA | AI34: esta en bani
A35: 46204 | B35: 4-13796386172 | C35: Cuentas | D35: Solicitud de Servicios | E35: Entrega Tarjeta Debito | F35: U46603 | G35: 03700749926 | H35: JENNIFFER NARDI ARIAS | I35: 253-OFICINA PUERTO PLATA | J35: U39793 | K35: PUERTO PLATA;PUERTO PLATA;area hospital | L35: PUERTO PLATA-PUERTO PLATA-PUERTO PLATA-area hospital-Manolo Tavares Just-0-Botello Motors-edificio-antes del parque del Hospita-C-8493878843-0-R-8099805539-0-C-0-0 | M35: PUERTO PLATA | N35: Puerto Plata | O35: Puerto Plata | P35: area hospital | Q35: Manolo Tavares Just | R35: 0 | S35: Botello Motors | T35: Edificio | U35: antes del parque del Hospita | V35: C | W35: 8493878843 | X35: 0 | Y35: R | Z35: 8099805539 | AA35: 0 | AB35: C | AC35: 0 | AD35: 0 | AE35: APPPOPULAR | AF35: 46203.799 | AG35: En proceso | AH35: TD- ENTREGADO | AJ35: PRINCIPAL | AL35: 46209 | AO35: Contactos Efectivos | AP35: ENVIAR DIRECCION CLIENTE !N!NPROVINCIA /PUERTO PLATA!NSECTOR /CAMBELEN!NCALLE/ AV MANOLO TAVAREZ JUSTO!NEMPRESA/BOTELLO MOTORS POP!NDEP/VENTA !NREF /PROX EL HOSPITAL DOCENTE UNIVERSITARIO RICARDO LIMARDO!NNO/ 8493878843!NHORA /8AM A 4PM!NCPEREZ | AQ35: 8493878843
A36: 46204 | B36: 4-13797444162 | C36: Cuentas | D36: Solicitud de Servicios | E36: Entrega Tarjeta Debito | F36: U52123 | G36: 05601058109 | H36: SANDY RAFAEL RODRIGUEZ ABREU | I36: 349-OFICINA SANTIAGO CENTER | J36: U47143 | K36: Santiago;Santiago;Vilo Olga | L36: Santiago-Santiago-Santiago-Vilo Olga-Ave Juan P Duarte-195-Seguros Universal -Negocios-Torre Seguros Universal -C-8295378167-0-C-8096043046-0-T-8095803279-3279 | M36: Santiago | N36: Santiago | O36: Santiago | P36: Vilo Olga | Q36: Ave Juan P Duarte | R36: 195 | S36: Seguros Universal | T36: Negocios | U36: Torre Seguros Universal | V36: C | W36: 8295378167 | X36: 0 | Y36: C | Z36: 8096043046 | AA36: 0 | AB36: T | AC36: 8095803279 | AD36: 3279 | AE36: APPPOPULAR | AF36: 46204.299 | AG36: En proceso | AH36: TD- ENTREGADO | AJ36: PRINCIPAL | AL36: 46204
A37: 46204 | B37: 4-13797445052 | C37: Cuentas | D37: Solicitud de Servicios | E37: Entrega Tarjeta Debito | F37: U46603 | G37: 40239212539 | H37: DILSON RODRIGUEZ REYES | I37: 242-OFICINA LAS COLINAS, STGO. | J37: U39668 | K37: Santiago;Santiago;Ensanche libertad | L37: SANTIAGO-SANTIAGO-SANTIAGO-Ensanche Libertad-2-37-0-0-Serca de la Farmacia Yna-C-8298408285-0-C-8093962038-0-C-0-0 | M37: Santiago | N37: Santiago | O37: Santiago | P37: Ensanche libertad | Q37: 2 | R37: 37 | S37: 0 | T37: 0 | U37: Serca de la Farmacia Yna | V37: C | W37: 8298408285 | X37: 0 | Y37: C | Z37: 8093962038 | AA37: 0 | AB37: C | AC37: 0 | AD37: 0 | AE37: APPPOPULAR | AF37: 46204.154 | AG37: En proceso | AH37: TD- ENTREGADO | AJ37: PRINCIPAL | AL37: 46205
A38: 46204 | B38: 4-13793685632 | C38: Cuentas | D38: Solicitud de Servicios | E38: Entrega Tarjeta Debito | F38: U52123 | G38: 40239125848 | H38: JAROLIN CORNIEL DE LA ROSA | I38: OFICINA DOWNTOWN CENTER MALL | K38: Santiago;Santiago;Barrio libertad | L38: Santiago-Santiago-Santiago-Barrio libertad -Penetracin-8-Gomez textil-Gomez A-Al lado de envaces antillan-C-8296681017-0-C-8093216475-0-0-0 | M38: Santiago | N38: Santiago | O38: Santiago | P38: Barrio libertad | Q38: Penetracin | R38: 8 | S38: Gomez textil | T38: Gomez A | U38: Al lado de envaces antillan | V38: C | W38: 8296681017 | X38: 0 | Y38: C | Z38: 8093216475 | AA38: 0 | AB38: 0 | AC38: 0 | AE38: APPPOPULAR | AF38: 46203.629 | AG38: En proceso | AH38: TD- ENTREGADO | AJ38: PRINCIPAL | AL38: 46204
A39: 46204 | B39: 4-13796867242 | C39: Cuentas | D39: Solicitud de Servicios | E39: Entrega Tarjeta Debito | F39: U46603 | G39: 03104884758 | H39: YOKASTA MARIA LORA VICIOSO | I39: 243-OFICINA CALLE DEL SOL, STGO. | J39: U48172 | K39: Santiago;Santiago;Hato mayor | L39: SANTIAGO-SANTIAGO-SANTIAGO-Hato Mayor-5-62-0-0-casi frente a la Iglesia-C-8297634458-0-C-8299812476-0-C-0-0 | M39: Santiago | N39: Santiago | O39: Santiago | P39: Hato mayor | Q39: 5 | R39: 62 | S39: 0 | T39: 0 | U39: casi frente a la Iglesia | V39: C | W39: 8297634458 | X39: 0 | Y39: C | Z39: 8299812476 | AA39: 0 | AB39: C | AC39: 0 | AD39: 0 | AE39: APPPOPULAR | AF39: 46203.863 | AG39: En proceso | AH39: TD- ENTREGADO | AJ39: PRINCIPAL | AL39: 46205
A40: 46204 | B40: 4-13794060202 | C40: Cuentas | D40: Solicitud de Servicios | E40: Entrega Tarjeta Debito | F40: U52123 | G40: 03100605108 | H40: PEDRO NOLASCO ESCOBOSA MATTA | I40: 242-OFICINA LAS COLINAS, STGO. | J40: U39668 | K40: Santiago;Santiago;El ingenio abajo | L40: SANTIAGO-SANTIAGO-SANTIAGO-El ingenio abajo-2-1-0-0-calle 2 no1 los tocones-C-8096390766-0-R-8293801200-0-C-0-0 | M40: Santiago | N40: Santiago | O40: Santiago | P40: El ingenio abajo | Q40: 2 | R40: 1 | S40: 0 | T40: 0 | U40: calle 2 no1 los tocones | V40: C | W40: 8096390766 | X40: 0 | Y40: R | Z40: 8293801200 | AA40: 0 | AB40: C | AC40: 0 | AD40: 0 | AE40: APPPOPULAR | AF40: 46203.641 | AG40: En proceso | AH40: TD- ENTREGADO | AJ40: PRINCIPAL | AL40: 46205
A41: 46204 | B41: 4-13793818922 | C41: Cuentas | D41: Solicitud de Servicios | E41: Entrega Tarjeta Debito | F41: U46603 | G41: 40218494611 | H41: GRISMELDY MARIA TEJADA ACEVEDO | I41: 270-OFICINA LICEY AL MEDIO | J41: U39194 | K41: SANTIAGO;SANTIAGO;los jardines metropo | L41: Santiago-Santiago-Santiago-Los Jardines metropo-Av 27 de febrero-19-San vicente de paul-Terapia-Frente al banco Santa Cruz -C-8293263302-0-T-8095822797-228-T-8095825596-242 | M41: Santiago | N41: Santiago | O41: Santiago | P41: los jardines metropo | Q41: Av 27 de febrero | R41: 19 | S41: San vicente de paul | T41: Terapia | U41: Frente al banco Santa Cruz | V41: C | W41: 8293263302 | X41: 0 | Y41: T | Z41: 8095822797 | AA41: 228 | AB41: T | AC41: 8095825596 | AD41: 242 | AE41: APPPOPULAR | AF41: 46203.657 | AG41: En proceso | AH41: TD- ENTREGADO | AJ41: PRINCIPAL | AL41: 46205
A42: 46204 | B42: 4-13794259812 | C42: Cuentas | D42: Solicitud de Servicios | E42: Entrega Tarjeta Debito | F42: U52123 | G42: 40236303471 | H42: MATTY LISBETH SANTOS ROMAN | I42: 373-OFICINA TENARES | J42: U28377 | K42: SANTIAGO;SANTIAGO;la esmeralda | L42: Santiago-Santiago-Santiago-La esmeralda -Bisono Toribio-1-Constructora Luba-Modulo 1-Cercano al Padre Fortin-C-8492063173-0-T-8297337777-0-0-0 | M42: Santiago | N42: Santiago | O42: Santiago | P42: la esmeralda | Q42: BISONO Toribio | R42: 1 | S42: Constructora Luba | T42: Modulo 1 | U42: Cercano al Padre Fortin | V42: C | W42: 8492063173 | X42: 0 | Y42: T | Z42: 8297337777 | AA42: 0 | AB42: 0 | AC42: 0 | AE42: APPPOPULAR | AF42: 46203.659 | AG42: En proceso | AH42: TD- ENTREGADO | AJ42: PRINCIPAL | AL42: 46204
A43: 46204 | B43: 4-13796292682 | C43: Cuentas | D43: Solicitud de Servicios | E43: Entrega Tarjeta Debito | F43: U52123 | G43: 40243312226 | H43: MARIA JOSE BLOISE GONZALEZ | I43: 290-OFICINA GURABO | J43: U24448 | K43: SANTIAGO;SANTIAGO;Embrujo I | L43: SANTIAGO-SANTIAGO-SANTIAGO-Embrujo I-Av Rafael Vidal-51-Palo Alto-Oficina-por el Lavadero Enriqueta-C-8092068295-0-T-8093823549-0-C-0-0 | M43: Santiago | N43: Santiago | O43: Santiago | P43: Embrujo I | Q43: Av Rafael Vidal | R43: 51 | S43: Palo Alto | T43: Oficina | U43: por el Lavadero Enriqueta | V43: C | W43: 8092068295 | X43: 0 | Y43: T | Z43: 8093823549 | AA43: 0 | AB43: C | AC43: 0 | AD43: 0 | AE43: APPPOPULAR | AF43: 46203.827 | AG43: En proceso | AH43: TD- ENTREGADO | AJ43: PRINCIPAL | AL43: 46204
A44: 46204 | B44: 4-13795422012 | C44: Cuentas | D44: Solicitud de Servicios | E44: Entrega Tarjeta Debito | F44: U52123 | G44: 40223109832 | H44: JOAN MIGUEL MIGUEL DIAZ CRUCETA | I44: 290-OFICINA GURABO | J44: U24448 | K44: SANTIAGO;SANTIAGO;villa verde | L44: SANTIAGO-SANTIAGO-SANTIAGO-villa verde-principal-12-Yohanretro23-ropas-motocentro saul-C-8296829889-0-C-8297058757-0-C-0-0 | M44: Santiago | N44: Santiago | O44: Santiago | P44: Villa verde | Q44: Principal | R44: 12 | S44: Yohanretro23 | T44: ropas | U44: motocentro saul | V44: C | W44: 8296829889 | X44: 0 | Y44: C | Z44: 8297058757 | AA44: 0 | AB44: C | AC44: 0 | AD44: 0 | AE44: APPPOPULAR | AF44: 46203.764 | AG44: En proceso | AH44: TD- ENTREGADO | AJ44: PRINCIPAL | AL44: 46204
A45: 46204 | B45: 4-13795890982 | C45: Cuentas | D45: Solicitud de Servicios | E45: Entrega Tarjeta Debito | F45: U52123 | G45: 03104663566 | H45: YELERIN GOMEZ ALMONTE | I45: 259-OFICINA UTESA, SANTIAGO | J45: U37650 | K45: Santiago;Santiago;Monterrico 1 | L45: SANTIAGO-SANTIAGO-SANTIAGO-monterrico 1-calle 1-11-juan colon-11 3ra-frente ala boutique Stones-C-8299844972-0-C-8494415473-0-C-0-0 | M45: Santiago | N45: Santiago | O45: Santiago | P45: Monterrico 1 | Q45: Calle 1 | R45: 11 | S45: juan colon | T45: 11 3ra | U45: frente ala boutique Stones | V45: C | W45: 8299844972 | X45: 0 | Y45: C | Z45: 8494415473 | AA45: 0 | AB45: C | AC45: 0 | AD45: 0 | AE45: APPPOPULAR | AF45: 46203.748 | AG45: En proceso | AH45: TD- ENTREGADO | AJ45: PRINCIPAL | AL45: 46206 | AO45: Contactos Efectivos | AP45: ENVIAR DIRECCION CLIENTE !N!NPROVINCIA /SANTIAGO!NSECTOR /MONTE RICO!NCALLE/ 1!NCASA/11!NREF/PROX A STONE FASHION!NNO/ 8299844972!NHORA /4PM A 5PM!NCPEREZ | AQ45: 8299844972
A46: 46204 | B46: 4-13795754452 | C46: Cuentas | D46: Solicitud de Servicios | E46: Entrega Tarjeta Debito | F46: U52123 | G46: 40235838147 | H46: YEIDY LAURIN GRULLON BONILLA | I46: 242-OFICINA LAS COLINAS, STGO. | J46: U39668 | K46: Santiago;Santiago;Jardines del este | L46: SANTIAGO-SANTIAGO-SANTIAGO-JARDINES DEL ESTE-CALLE PENETRACION EDIFICIO VIRTUDES LL--0-0-0-C-8492485880-0-R-8492585880-0 | M46: Santiago | N46: Santiago | O46: Santiago | P46: Jardines del este | Q46: CALLE PENETRACION ED | S46: 0 | T46: 0 | U46: 0 | V46: C | W46: 8492485880 | X46: 0 | Y46: R | Z46: 8492585880 | AA46: 0 | AE46: APPPOPULAR | AF46: 46203.734 | AG46: En proceso | AH46: TD- ENTREGADO | AJ46: PRINCIPAL | AL46: 46205
A47: 46204 | B47: 4-13794055162 | C47: Cuentas | D47: Solicitud de Servicios | E47: Entrega Tarjeta Debito | F47: U52123 | G47: 03104230853 | H47: JUDITH ELIZABETH CRUZ DOMINGUEZ | I47: 244-OFICINA 27 DE FEBRERO, STGO. | J47: U19099 | K47: Santiago;Santiago;Los salados | L47: SANTIAGO-SANTIAGO-SANTIAGO-Los Salados-Av Estrella Sadhala-247-Baldom-Seguridad-8 am a 5 pm-C-8098671206-0-T-8095753256-243-C-0-0 | M47: Santiago | N47: Santiago | O47: Santiago | P47: Los salados | Q47: Av Estrella sadhala | R47: 247 | S47: baldom | T47: Seguridad | U47: 8 am a 5 pm | V47: C | W47: 8098671206 | X47: 0 | Y47: T | Z47: 8095753256 | AA47: 243 | AB47: C | AC47: 0 | AD47: 0 | AE47: APPPOPULAR | AF47: 46203.677 | AG47: En proceso | AH47: TD- ENTREGADO | AJ47: PRINCIPAL | AL47: 46204
A48: 46209 | B48: 4-13819772522 | C48: Cuentas | D48: Solicitud de Servicios | E48: Entrega Tarjeta Debito | F48: U52123 | G48: 03104632512 | H48: SARAH TAVAREZ MARTINEZ | I48: 243-OFICINA CALLE DEL SOL, STGO. | J48: U32288 | K48: Santiago;Santiago;Bella vista | L48: Santiago-Santiago-Santiago-Bella vista-Av Antonio Guzman -20-0-0-Repuestos tavarez-C-8296377540-0-R-8092471813-0-0-0 | M48: Santiago | N48: Santiago | O48: Santiago | P48: Bella vista | Q48: Av Antonio Guzman | R48: 20 | S48: 0 | T48: 0 | U48: Repuestos tavarez | V48: C | W48: 8296377540 | X48: 0 | Y48: R | Z48: 8092471813 | AA48: 0 | AB48: 0 | AC48: 0 | AE48: APPPOPULAR | AF48: 46206.745 | AG48: En proceso | AH48: TD- ENTREGADO | AJ48: PRINCIPAL | AL48: 46212
A49: 46204 | B49: 4-13797601342 | C49: Cuentas | D49: Solicitud de Servicios | E49: Entrega Tarjeta Debito | F49: U46603 | G49: 40227634264 | H49: JORGE LUIS REYNOSO ESPINOSA | I49: 317-OFICINA CARREFOUR | J49: U22052 | K49: Santo Domingo;Santo Domingo Oeste;La venta | L49: SANTO DOMINGO-SANTO DOMINGO OESTE-SANTO DOMINGO OESTE-la venta-duarte vieja-115-0-0-Joan Tren-C-8493906208-0-C-8099940508-0-C-0-0 | M49: Santo Domingo | N49: Santo Domingo Oeste | O49: Santo Domingo Oeste | P49: la venta | Q49: duarte vieja | R49: 115 | S49: 0 | T49: 0 | U49: Joan Tren | V49: C | W49: 8493906208 | X49: 0 | Y49: C | Z49: 8099940508 | AA49: 0 | AB49: C | AC49: 0 | AD49: 0 | AE49: APPPOPULAR | AF49: 46204.334 | AG49: En proceso | AH49: TD- ENTREGADO | AI49: michael | AJ49: PRINCIPAL | AL49: 46205
A50: 46204 | B50: 4-13797620962 | C50: Cuentas | D50: Solicitud de Servicios | E50: Entrega Tarjeta Debito | F50: U52123 | G50: 22900253042 | H50: KATHERIN ESTHEFANY ALVARADO NUNEZ | I50: 137-OFICINA WINSTON CHURCHILL | K50: Santo Domingo;Los Alcarrizos;Pantoja | L50: SANTO DOMINGO-LOS ALCARRIZOS-PANTOJA-PANTOJA-calle transversal 7 edificio-3-0-0-0-C-8296034818-0-C-8296034818-0 | M50: Santo Domingo | N50: LOS ALCARRIZOS | O50: PANTOJA | P50: Pantoja | Q50: calle transversal 7 | R50: 3 | S50: 0 | T50: 0 | U50: 0 | V50: C | W50: 8296034818 | X50: 0 | Y50: C | Z50: 8296034818 | AA50: 0 | AE50: APPPOPULAR | AF50: 46204.301 | AG50: En proceso | AH50: TD- ENTREGADO | AI50: Charina Mendez | AJ50: PRINCIPAL | AL50: 46205
A51: 46204 | B51: 4-13797558822 | C51: Cuentas | D51: Solicitud de Servicios | E51: Entrega Tarjeta Debito | F51: U52123 | G51: 22500775113 | H51: LEANDRO RODRIGUEZ GARCIA | I51: 280-OFICINA MEGACENTRO I | J51: U35271 | K51: Santo Domingo;Santo Domingo Oeste;San Luis | L51: Santo Domingo-Santo Domingo Oeste-Santo Domingo Oeste-San Luis -Felipe alfau-105-0-0-0-C-8493916122-0-C-8093325580-0-0-0 | M51: Santo Domingo | N51: Santo Domingo Oeste | O51: Santo Domingo Oeste | P51: san Luis | Q51: Felipe Alfau | R51: 105 | S51: 0 | T51: 0 | U51: 0 | V51: C | W51: 8493916122 | X51: 0 | Y51: C | Z51: 8093325580 | AA51: 0 | AB51: 0 | AC51: 0 | AE51: APPPOPULAR | AF51: 46204.241 | AG51: En proceso | AH51: TD- ENTREGADO | AI51: Gabriel | AJ51: PRINCIPAL | AL51: 46209
A52: 46204 | B52: 4-13797415752 | C52: Cuentas | D52: Solicitud de Servicios | E52: Entrega Tarjeta Debito | F52: U52123 | G52: 40222165983 | H52: YANIL DE LOS SANTOS DE LA | I52: 141-OFICINA TORRE EMPRESARIAL 27 DE FEBRERO | J52: U43577 | K52: Santo Domingo;Santo Domingo Oeste;Los peralejos | L52: Santo Domingo-Santo Domingo Oeste-Santo Domingo Oeste-Los Peralejos-Res Altos de la Colo-1-8-1B-Av Republica de Colombia Res-C-8296699966-0-C-8492665646-0-0-0 | M52: Santo Domingo | N52: Santo Domingo Oeste | O52: Santo Domingo Oeste | P52: Los peralejos | Q52: Res Altos de la Colo | R52: 1 | S52: 8 | T52: 1B | U52: Av Republica de Colombia Res | V52: C | W52: 8296699966 | X52: 0 | Y52: C | Z52: 8492665646 | AA52: 0 | AB52: 0 | AC52: 0 | AE52: APPPOPULAR | AF52: 46204.068 | AG52: En proceso | AH52: TD- ENTREGADO | AI52: michael | AJ52: PRINCIPAL | AL52: 46205
A53: 46204 | B53: 4-13796867962 | C53: Cuentas | D53: Solicitud de Servicios | E53: Entrega Tarjeta Debito | F53: U52123 | G53: 40224999025 | H53: LUIS GUILLERMO NINA BLANCO | I53: 303-OFICINA SAMBIL | J53: U35901 | K53: SANTO DOMINGO;LOS ALCARRIZOS;Pantojas | L53: SANTO DOMINGO-LOS ALCARRIZOS-LOS ALCARRIZOS-Pantojas-carretera la isabel-58-laboratorios Alfa-1-después del banco de reserva-C-8297941459-0-C-8093502499-0-C-0-0 | M53: Santo Domingo | N53: LOS ALCARRIZOS | O53: LOS ALCARRIZOS | P53: pantojas | Q53: carretera la isabel | R53: 58 | S53: laboratorios alfa | T53: 1 | U53: después del banco de reserva | V53: C | W53: 8297941459 | X53: 0 | Y53: C | Z53: 8093502499 | AA53: 0 | AB53: C | AC53: 0 | AD53: 0 | AE53: APPPOPULAR | AF53: 46204.048 | AG53: En proceso | AH53: TD- ENTREGADO | AI53: Charina Mendez | AJ53: PRINCIPAL | AL53: 46205
A54: 46204 | B54: 4-13797206382 | C54: Cuentas | D54: Solicitud de Servicios | E54: Entrega Tarjeta Debito | F54: U46603 | G54: 40213929165 | H54: MIGUEL ALEJANDRO OVIEDO | I54: OFICINA DOWNTOWN CENTER MALL | K54: SANTO DOMINGO;SANTO DOMINGO OESTE;manoguayabo | L54: SANTO DOMINGO-SANTO DOMINGO OESTE-SANTO DOMINGO OESTE-Manoguayabo-Framboyan-11-0-0-Agua talise-C-8099053123-0-C-8493414743-0-C-8494471026-0 | M54: Santo Domingo | N54: Santo Domingo Oeste | O54: Santo Domingo Oeste | P54: manoguayabo | Q54: framboyan | R54: 11 | S54: 0 | T54: 0 | U54: Agua talise | V54: C | W54: 8099053123 | X54: 0 | Y54: C | Z54: 8493414743 | AA54: 0 | AB54: C | AC54: 8494471026 | AD54: 0 | AE54: APPPOPULAR | AF54: 46204 | AG54: En proceso | AH54: TD- ENTREGADO | AI54: michael | AJ54: PRINCIPAL | AL54: 46205 | AO54: Duplicada | AP54: Entregada
A55: 46204 | B55: 4-13793410802 | C55: Cuentas | D55: Solicitud de Servicios | E55: Entrega Tarjeta Debito | F55: U46603 | G55: 40230306033 | H55: YAFREISIS VALDEZ | I55: 317-OFICINA CARREFOUR | J55: U22052 | K55: SANTO DOMINGO;LOS ALCARRIZOS;Los Coquitos Union | L55: SANTO DOMINGO-LOS ALCARRIZOS-LOS ALCARRIZOS-Los Coquitos Union-Los Coquitos-07-0-0-Col Los Coco-C-8299735382-0-C-8098180799-0-C-0-0 | M55: Santo Domingo | N55: LOS ALCARRIZOS | O55: LOS ALCARRIZOS | P55: Los Coquitos Union | Q55: Los coquitos | R55: 07 | S55: 0 | T55: 0 | U55: Col Los Coco | V55: C | W55: 8299735382 | X55: 0 | Y55: C | Z55: 8098180799 | AA55: 0 | AB55: C | AC55: 0 | AD55: 0 | AE55: APPPOPULAR | AF55: 46203.61 | AG55: En proceso | AH55: TD- ENTREGADO | AI55: Charina Mendez | AJ55: PRINCIPAL | AL55: 46205
A56: 46204 | B56: 4-13796935062 | C56: Cuentas | D56: Solicitud de Servicios | E56: Entrega Tarjeta Debito | F56: U46603 | G56: 00107518250 | H56: ZORAIDA CHALJUB ROSA | I56: MODELO PREFERENTE | J56: U43373 | K56: Santo Domingo;Los Alcarrizos;Pantoja | L56: SANTO DOMINGO-LOS ALCARRIZOS-PANTOJA-Pantoja-Manz K-25-0-0-Residencial Don Gregorio-C-8094535467-0-C-8097070356-0-C-0-0 | M56: Santo Domingo | N56: LOS ALCARRIZOS | O56: PANTOJA | P56: Pantoja | Q56: manz k | R56: 25 | S56: 0 | T56: 0 | U56: Residencial Don Gregorio | V56: C | W56: 8094535467 | X56: 0 | Y56: C | Z56: 8097070356 | AA56: 0 | AB56: C | AC56: 0 | AD56: 0 | AE56: APPPOPULAR | AF56: 46203.896 | AG56: En proceso | AH56: TD- ENTREGADO | AI56: Charina Mendez | AJ56: PRINCIPAL | AL56: 46205
A57: 46204 | B57: 4-13793193962 | C57: Cuentas | D57: Solicitud de Servicios | E57: Entrega Tarjeta Debito | F57: U46603 | G57: 40230240083 | H57: ASHLEY DAHIANA SURIEL MORETA | I57: OFICINA DOWNTOWN CENTER MALL | K57: SANTO DOMINGO;SANTO DOMINGO OESTE;SANTO DOMINGO COUNTR | L57: SANTO DOMINGO-SANTO DOMINGO OESTE-SANTO DOMINGO OESTE-SANTO DOMINGO COUNTRY CLUB-PEDRO HENRRIQUEZ URE-1-JYL CONSULTORES -PROYECTOS -0-C-8296640686-0-C-8298668150-0 | M57: Santo Domingo | N57: Santo Domingo Oeste | O57: Santo Domingo Oeste | P57: SANTO DOMINGO COUNTR | Q57: PEDRO HENRRIQUEZ URE | R57: 1 | S57: JyL consultores | T57: Proyectos | U57: 0 | V57: C | W57: 8296640686 | X57: 0 | Y57: C | Z57: 8298668150 | AA57: 0 | AE57: APPPOPULAR | AF57: 46203.63 | AG57: En proceso | AH57: TD- ENTREGADO | AI57: Angel | AJ57: PRINCIPAL | AL57: 46206
A58: 46209 | B58: 4-13822813062 | C58: Cuentas | D58: Solicitud de Servicios | E58: Entrega Tarjeta Debito | F58: APPPOPULAR | G58: 03105641736 | H58: ERIKA ALMONTE BALBUENA | I58: OFICINA DOWNTOWN CENTER MALL | K58: Santiago;Santiago;Pekin | L58: SANTIAGO-SANTIAGO-SANTIAGO-PEKIN-CALLE PRINCIPAL LA CEIBITA--0-0-CALLE PRINCIPAL LA CEIBITA -C-8098972493-0-C-8295080328-0 | M58: Santiago | N58: Santiago | O58: Santiago | P58: Pekin | Q58: CALLE PRINCIPAL LA C | S58: 0 | T58: 0 | U58: CALLE PRINCIPAL LA CEIBITA | V58: C | W58: 8098972493 | X58: 0 | Y58: C | Z58: 8295080328 | AA58: 0 | AE58: APPPOPULAR | AF58: 46207.672 | AG58: En proceso | AH58: TD- ENTREGADO | AJ58: PRINCIPAL | AL58: 46213
A59: 46204 | B59: 4-13796619602 | C59: Cuentas | D59: Solicitud de Servicios | E59: Entrega Tarjeta Debito | F59: U46603 | G59: 40226266720 | H59: ADAN DEL CARMEN ROSARIO | I59: 149-OFICINA ROMULO BETANCOURT | J59: U33904 | K59: Santo Domingo;Los Alcarrizos;Barrio invi | L59: Santo Domingo-Los Alcarrizos-Los Alcarrizos-Barrio invi -invi manzana 10-33-0-0-Al lado de un edificio -C-8498280996-0-C-8298804876-0-0-0 | M59: Santo Domingo | N59: LOS ALCARRIZOS | O59: LOS ALCARRIZOS | P59: Barrio invi | Q59: invi manzana 10 | R59: 33 | S59: 0 | T59: 0 | U59: Al lado de un edificio | V59: C | W59: 8498280996 | X59: 0 | Y59: C | Z59: 8298804876 | AA59: 0 | AB59: 0 | AC59: 0 | AE59: APPPOPULAR | AF59: 46203.862 | AG59: En proceso | AH59: TD- ENTREGADO | AI59: Charina Mendez | AJ59: PRINCIPAL | AL59: 46205
A60: 46204 | B60: 4-13796507632 | C60: Cuentas | D60: Solicitud de Servicios | E60: Entrega Tarjeta Debito | F60: U46603 | G60: 40213791052 | H60: REYNALDO ANTONIO MARTINEZ MARTINEZ | I60: 293-OFICINA AGORA MALL | J60: U46455 | K60: SANTO DOMINGO;SANTO DOMINGO OESTE;Pedro brand | L60: Santo Domingo-Santo Domingo Oeste-Santo Domingo Oeste-Pedro Brand -Av Circunvalacin Pro-0-Agrolacteos Imanfa SRL-Compras -0-C-8297998385-0-C-8299213513-0-0-0 | M60: Santo Domingo | N60: Santo Domingo Oeste | O60: Santo Domingo Oeste | P60: Pedro brand | Q60: Av Circunvalacin Pro | R60: 0 | S60: Agrolacteos Imanfa SRL | T60: Compras | U60: 0 | V60: C | W60: 8297998385 | X60: 0 | Y60: C | Z60: 8299213513 | AA60: 0 | AB60: 0 | AC60: 0 | AE60: APPPOPULAR | AF60: 46203.851 | AG60: En proceso | AH60: TD- ENTREGADO | AI60: michael | AJ60: PRINCIPAL | AL60: 46205
A61: 46204 | B61: 4-13796292832 | C61: Cuentas | D61: Solicitud de Servicios | E61: Entrega Tarjeta Debito | F61: U46603 | G61: 01000775666 | H61: MARIA TRINIDAD RAMIREZ CUELLO | I61: 153-OFICINA AZUA | K61: Santo Domingo;Santo Domingo Oeste;Barrio Duarte | L61: SANTO DOMINGO-SANTO DOMINGO OESTE-SANTO DOMINGO OESTE-Barrio duarte-central-3-0-0-0-C-8293760233-0-C-8096757187-0-C-0-0 | M61: Santo Domingo | N61: Santo Domingo Oeste | O61: Santo Domingo Oeste | P61: Barrio Duarte | Q61: central | R61: 3 | S61: 0 | T61: 0 | U61: 0 | V61: C | W61: 8293760233 | X61: 0 | Y61: C | Z61: 8096757187 | AA61: 0 | AB61: C | AC61: 0 | AD61: 0 | AE61: APPPOPULAR | AF61: 46203.842 | AG61: En proceso | AH61: TD- ENTREGADO | AI61: michael | AJ61: PRINCIPAL | AL61: 46205
A62: 46209 | B62: 4-13822672012 | C62: Cuentas | D62: Solicitud de Servicios | E62: Entrega Tarjeta Debito | F62: APPPOPULAR | G62: 40210164469 | H62: ANTHONY RAFAEL SILVESTRE HERNANDEZ | I62: OFICINA DOWNTOWN CENTER MALL | K62: SANTIAGO;SANTIAGO;gurabo | L62: Santiago-Santiago-Santiago-Gurabo -Calle 11 de Gurabo -24-Reviel super Marke -A-Salon isa luna -C-8297435700-0-C-8299639563-0-0-0 | M62: Santiago | N62: Santiago | O62: Santiago | P62: gurabo | Q62: Calle 11 de Gurabo | R62: 24 | S62: Reviel super Marke | T62: A | U62: Salon isa luna | V62: C | W62: 8297435700 | X62: 0 | Y62: C | Z62: 8299639563 | AA62: 0 | AB62: 0 | AC62: 0 | AE62: APPPOPULAR | AF62: 46207.598 | AG62: En proceso | AH62: TD- ENTREGADO | AJ62: PRINCIPAL | AL62: 46212
A63: 46204 | B63: 4-13796667902 | C63: Cuentas | D63: Solicitud de Servicios | E63: Entrega Tarjeta Debito | F63: U46603 | G63: 09700133045 | H63: ROBERTO DURAN DE LA CRUZ | I63: 254-OFICINA SOSUA | J63: U50597 | K63: Santo Domingo;Santo Domingo Oeste;Buenos Aires de Herr | L63: SANTO DOMINGO-SANTO DOMINGO OESTE-SANTO DOMINGO OESTE-BUENOS AIRES DE HERRERA-CENTRAL-20-0-0-CALLE CENTRAL #20 BUENOS AIRES DE HERRERA -C-8097084164-0-C-8099827079-0 | M63: Santo Domingo | N63: Santo Domingo Oeste | O63: Santo Domingo Oeste | P63: Buenos Aires de Herr | Q63: central | R63: 20 | S63: 0 | T63: 0 | U63: CALLE CENTRAL #20 BUENOS AIRES DE HERRERA | V63: C | W63: 8097084164 | X63: 0 | Y63: C | Z63: 8099827079 | AA63: 0 | AE63: APPPOPULAR | AF63: 46203.839 | AG63: En proceso | AH63: TD- ENTREGADO | AI63: michael | AJ63: PRINCIPAL | AL63: 46205
A64: 46204 | B64: 4-13794270512 | C64: Cuentas | D64: Solicitud de Servicios | E64: Entrega Tarjeta Debito | F64: U46603 | G64: 40202424657 | H64: EMILY RASHEL LOPEZ | I64: 303-OFICINA SAMBIL | J64: U35901 | K64: Santo Domingo;Santo Domingo Oeste;Herrera | L64: Santo Domingo-Santo Domingo Oeste-Santo Domingo Oeste-Herrera -Los humildes -2-0-0-0-C-8298866654-0-C-8298638523-0-0-0 | M64: Santo Domingo | N64: Santo Domingo Oeste | O64: Santo Domingo Oeste | P64: Herrera | Q64: Los humildes | R64: 2 | S64: 0 | T64: 0 | U64: 0 | V64: C | W64: 8298866654 | X64: 0 | Y64: C | Z64: 8298638523 | AA64: 0 | AB64: 0 | AC64: 0 | AE64: APPPOPULAR | AF64: 46203.653 | AG64: En proceso | AH64: TD- ENTREGADO | AI64: michael | AJ64: PRINCIPAL | AL64: 46205 | AO64: Duplicada | AP64: Entregada
A65: 46209 | B65: 4-13819956032 | C65: Cuentas | D65: Solicitud de Servicios | E65: Entrega Tarjeta Debito | F65: U46603 | G65: 40238539924 | H65: MARIA DEL PILAR BAEZ SUSANA | I65: 246-OFICINA ZONA FRANCA, STGO. | J65: U38309 | K65: Santiago;Santiago;Urb Los Reyes | L65: Santiago-Santiago-Santiago-Urb Los Reyes-30 San Antonio-5-0-0-0-C-8293044637-0-C-8098215832-0-0-0 | M65: Santiago | N65: Santiago | O65: Santiago | P65: Urb Los Reyes | Q65: 30 San Antonio | R65: 5 | S65: 0 | T65: 0 | U65: 0 | V65: C | W65: 8293044637 | X65: 0 | Y65: C | Z65: 8098215832 | AA65: 0 | AB65: 0 | AC65: 0 | AE65: APPPOPULAR | AF65: 46206.791 | AG65: En proceso | AH65: TD- ENTREGADO | AJ65: PRINCIPAL | AL65: 46212
A66: 46204 | B66: 4-13793874952 | C66: Cuentas | D66: Solicitud de Servicios | E66: Entrega Tarjeta Debito | F66: U52123 | G66: 40211640988 | H66: BLADIMILKA CAMILO FLORENCIO | I66: OFICINA DOWNTOWN CENTER MALL | J66: U46569 | K66: Santo Domingo;Los Alcarrizos;Pueblo nuevo la malv | L66: Santo Domingo-Los Alcarrizos-Los Alcarrizos-Pueblo nuevo la malv-11 8-32-0-0-Despues del comedor economic-C-8495298601-0-C-8294526896-0-0-0 | M66: Santo Domingo | N66: LOS ALCARRIZOS | O66: LOS ALCARRIZOS | P66: Pueblo nuevo la malv | Q66: 11 8 | R66: 32 | S66: 0 | T66: 0 | U66: Despues del comedor economic | V66: C | W66: 8495298601 | X66: 0 | Y66: C | Z66: 8294526896 | AA66: 0 | AB66: 0 | AC66: 0 | AE66: APPPOPULAR | AF66: 46203.662 | AG66: En proceso | AH66: TD- ENTREGADO | AI66: Charina Mendez | AJ66: PRINCIPAL | AL66: 46205 | AO66: Duplicada | AP66: Entregada
A67: 46204 | B67: 4-13795796772 | C67: Cuentas | D67: Solicitud de Servicios | E67: Entrega Tarjeta Debito | F67: U46603 | G67: 40241034475 | H67: ENMANUELA NUNEZ | I67: 303-OFICINA SAMBIL | J67: U35901 | K67: SANTO DOMINGO;SANTO DOMINGO OESTE;La venta manoguayabo | L67: Santo Domingo-Santo Domingo Oeste-Santo Domingo Oeste-La venta Manoguayabo-Belen-9-0-0-0-C-8296557829-0-C-8492744002-0-0-0 | M67: Santo Domingo | N67: Santo Domingo Oeste | O67: Santo Domingo Oeste | P67: La venta manoguayabo | Q67: Belen | R67: 9 | S67: 0 | T67: 0 | U67: 0 | V67: C | W67: 8296557829 | X67: 0 | Y67: C | Z67: 8492744002 | AA67: 0 | AB67: 0 | AC67: 0 | AE67: APPPOPULAR | AF67: 46203.791 | AG67: En proceso | AH67: TD- ENTREGADO | AI67: michael | AJ67: PRINCIPAL | AL67: 46205 | AO67: Duplicada | AP67: Entregada
A68: 46204 | B68: 4-13795421372 | C68: Cuentas | D68: Solicitud de Servicios | E68: Entrega Tarjeta Debito | F68: U52123 | G68: 40212563221 | H68: KEYLA ALEXANDRA CEPEDA MATEO | I68: OFICINA DOWNTOWN CENTER MALL | K68: Santo Domingo;Santo Domingo Oeste;Repaldo Rosa | L68: Santo Domingo-Santo Domingo Oeste-Santo Domingo Oeste-Repaldo Rosa-Interior 14 -1-0-0-Rejas Azules -C-8093234036-0-R-8492216942-0-0-0 | M68: Santo Domingo | N68: Santo Domingo Oeste | O68: Santo Domingo Oeste | P68: Repaldo Rosa | Q68: Interior 14 | R68: 1 | S68: 0 | T68: 0 | U68: Rejas Azules | V68: C | W68: 8093234036 | X68: 0 | Y68: R | Z68: 8492216942 | AA68: 0 | AB68: 0 | AC68: 0 | AE68: APPPOPULAR | AF68: 46203.716 | AG68: En proceso | AH68: TD- ENTREGADO | AI68: michael | AJ68: PRINCIPAL | AL68: 46205
A69: 46209 | B69: 4-13822335772 | C69: Cuentas | D69: Solicitud de Servicios | E69: Entrega Tarjeta Debito | F69: U46603 | G69: 03103621201 | H69: JOHANNA YAHAIRA ALMONTE GONZALEZ | I69: 253-OFICINA PUERTO PLATA | J69: U39793 | K69: SANTIAGO;SABANA IGLESIA;la lima | L69: SANTIAGO-SABANA IGLESIA-SABANA IGLESIA-la lima-calle principal-13-0-0-casa en la lima abajo-C-8096643751-0-C-8293582614-0-C-0-0 | M69: Santiago | N69: Sabana Iglesia | O69: Sabana Iglesia | P69: la lima | Q69: Calle principal | R69: 13 | S69: 0 | T69: 0 | U69: casa en la lima abajo | V69: C | W69: 8096643751 | X69: 0 | Y69: C | Z69: 8293582614 | AA69: 0 | AB69: C | AC69: 0 | AD69: 0 | AE69: APPPOPULAR | AF69: 46207.534 | AG69: En proceso | AH69: TD- ZONA FUERA DE COBERTURA | AI69: cliente a mas de 40 km de santiago
A70: 46204 | B70: 4-13799574152 | C70: Cuentas | D70: Solicitud de Servicios | E70: Entrega Tarjeta Debito | F70: U52123 | G70: 22400290163 | H70: CAROLINA CLETO JAVIER | I70: 216-OFICINA IBERIA HIGUEY | J70: U41202 | K70: La Altagracia;Higuey;Nazareth | L70: La Altagracia-Higuey-Higuey-Nazareth -Francisco rijo cuto -104-Elisa frente a cabgil -1 A -Al lado De la iglesia centra-C-8298985186-0-C-8098568569-0-0-0 | M70: LA ALTAGRACIA | N70: HIGUEY | O70: HIGUEY | P70: Nazareth | Q70: Francisco Rijo Cuto | R70: 104 | S70: Elisa frente a cabgil | T70: 1 a | U70: Al lado De la iglesia centra | V70: C | W70: 8298985186 | X70: 0 | Y70: C | Z70: 8098568569 | AA70: 0 | AB70: 0 | AC70: 0 | AE70: APPPOPULAR | AF70: 46204.467 | AG70: En proceso | AH70: TD- ENTREGADO | AJ70: PRINCIPAL | AL70: 46209 | AO70: Contactos Efectivos | AP70: ENVIAR DIRECCION AL CLIENTE !NPROVIN// HIGUEY LA ALTAGRACIA !NSECTOR// PUEBLO NUEVO !NCALLE// CALLE FRANCISCO RIJO CUTO APART 1A !NREFER// PROX A HOTEL ROD !NNUMERO// 8298985186!NHORARIO// 8AM A 12PM !NMPEREZ !N | AQ70: 8298985186
A71: 46204 | B71: 4-13797634152 | C71: Cuentas | D71: Solicitud de Servicios | E71: Entrega Tarjeta Debito | F71: U52123 | G71: 40227838055 | H71: CHANTAL PEREZ | I71: 216-OFICINA IBERIA HIGUEY | J71: U41202 | K71: La Altagracia;Higuey;Nazaret | L71: La Altagracia-Higuey-Higuey-Nazaret -Manuel Emilio Gmez-5-0-0-0-C-8094283422-0-C-8293920955-0-0-0 | M71: LA ALTAGRACIA | N71: HIGUEY | O71: HIGUEY | P71: Nazaret | Q71: Manuel Emilio Gmez | R71: 5 | S71: 0 | T71: 0 | U71: 0 | V71: C | W71: 8094283422 | X71: 0 | Y71: C | Z71: 8293920955 | AA71: 0 | AB71: 0 | AC71: 0 | AE71: APPPOPULAR | AF71: 46204.397 | AG71: En proceso | AH71: TD- ENTREGADO | AJ71: PRINCIPAL | AL71: 46209
A72: 46209 | B72: 4-13822268242 | C72: Cuentas | D72: Solicitud de Servicios | E72: Entrega Tarjeta Debito | F72: U52123 | G72: 03104525484 | H72: RICHARD HERNANDEZ PEREZ | I72: 259-OFICINA UTESA, SANTIAGO | J72: U37650 | K72: SANTIAGO;SANTIAGO;plaza olimpica | L72: SANTIAGO-SANTIAGO-SANTIAGO-plaza olimpica-av estrella sadhala-2-Suplident-1er nivel-Plaza olimpica Suplident 1er-C-8098890946-0-T-8095815455-0-C-0-0 | M72: Santiago | N72: Santiago | O72: Santiago | P72: plaza olimpica | Q72: Av estrella sadhala | R72: 2 | S72: Suplident | T72: 1er Nivel | U72: Plaza olimpica Suplident 1er | V72: C | W72: 8098890946 | X72: 0 | Y72: T | Z72: 8095815455 | AA72: 0 | AB72: C | AC72: 0 | AD72: 0 | AE72: APPPOPULAR | AF72: 46207.514 | AG72: En proceso | AH72: TD- ENTREGADO | AJ72: PRINCIPAL | AL72: 46212
A73: 46204 | B73: 4-13802204402 | C73: Cuentas | D73: Solicitud de Servicios | E73: Entrega Tarjeta Debito | F73: U52123 | G73: 40238338624 | H73: LEONEL RUIZ COLON | I73: OFICINA DOWNTOWN CENTER MALL | K73: LA ROMANA;VILLA HERMOSA;villa hermosa | L73: LA ROMANA-VILLA HERMOSA-VILLA HERMOSA-VILLA HERMOSA-calle padre Abraham No-6-0-0-0-C-8096242509-0-C-8096242509-0 | M73: La Romana | N73: VILLA HERMOSA | O73: VILLA HERMOSA | P73: Villa Hermosa | Q73: calle padre Abraham | R73: 6 | S73: 0 | T73: 0 | U73: 0 | V73: C | W73: 8096242509 | X73: 0 | Y73: C | Z73: 8096242509 | AA73: 0 | AE73: APPPOPULAR | AF73: 46204.618 | AG73: En proceso | AH73: TD- ENTREGADO | AJ73: PRINCIPAL | AL73: 46206
A74: 46204 | B74: 4-13798155582 | C74: Cuentas | D74: Solicitud de Servicios | E74: Entrega Tarjeta Debito | F74: U46603 | G74: 40224535118 | H74: EMILIO ROSARIO ROSA | I74: 175-OFICINA INDEPENDENCIA | J74: U41496 | K74: LA ROMANA;VILLA HERMOSA;villa hermosa | L74: LA ROMANA-VILLA HERMOSA-VILLA HERMOSA-villa hermosa-Av prof Juan bosch-1-coca cola-Bodega-Entrada de cucama-C-8295205938-0-C-8499167686-0-C-0-0 | M74: La Romana | N74: VILLA HERMOSA | O74: VILLA HERMOSA | P74: Villa Hermosa | Q74: Av prof Juan bosch | R74: 1 | S74: coca cola | T74: Bodega | U74: Entrada de cucama | V74: C | W74: 8295205938 | X74: 0 | Y74: C | Z74: 8499167686 | AA74: 0 | AB74: C | AC74: 0 | AD74: 0 | AE74: APPPOPULAR | AF74: 46204.384 | AG74: En proceso | AH74: TD- ENTREGADO | AJ74: PRINCIPAL | AL74: 46206 | AO74: Contactos Efectivos | AP74: ENVIAR DIRECCION AL CLIENTE!N!NLA ROMANA !NSECTOR//VILLA HERMOSA !NEMPRESA//COCA COLA!NDEPART//BODEGA !NCALLE//AV PROF JUAN BOSCH!NREF//PROX A BOMBA DE GASOLINA PETRONAM !N8295205938 8AM A 5PM!NWMENDEZ | AQ74: 8295205938
A75: 46204 | B75: 4-13799380742 | C75: Cuentas | D75: Solicitud de Servicios | E75: Entrega Tarjeta Debito | F75: U52123 | G75: 40215305067 | H75: CRISTAL ALEJANDRINA FULGENCIO LUNA | I75: 211-OFICINA LA ROMANA | J75: U21982 | K75: La Romana;La Romana;villa san carlos | L75: La Romana-La Romana-La Romana-Villa San Carlos -3-15-0-0-Calle despus del cuartel -C-8493602719-0-R-8095563124-0-0-0 | M75: La Romana | N75: La Romana | O75: La Romana | P75: villa san carlos | Q75: 3 | R75: 15 | S75: 0 | T75: 0 | U75: Calle despus del cuartel | V75: C | W75: 8493602719 | X75: 0 | Y75: R | Z75: 8095563124 | AA75: 0 | AB75: 0 | AC75: 0 | AE75: APPPOPULAR | AF75: 46204.47 | AG75: En proceso | AH75: TD- ENTREGADO | AJ75: PRINCIPAL | AL75: 46209 | AO75: Contactos Efectivos | AP75: ENVIAR DIRECCION AL CLIENTE!N!NLA ROMANA !NSECTOR//VILLA SAN CARLOS!NCALLE//CALLE 3!NCASA NO 15!NREF//PROX A DESTACAMENTO POLICIA NACIONAL VILLA SAN CARLOS!N8493602719 8AM A 5PM!NWMENDEZ | AQ75: 8493602719
A76: 46204 | B76: 4-13797634102 | C76: Cuentas | D76: Solicitud de Servicios | E76: Entrega Tarjeta Debito | F76: U52123 | G76: 40228923039 | H76: YOSMERIS ESPADIS MERCEDES | I76: SUCURSAL MULTIPLAZA LA ROMANA | J76: U39067 | K76: La Romana;Villa Hermosa;Villa progreso | L76: La Romana-Villa Hermosa-Villa Hermosa-Villa progreso -C Ana -3-CCSM -Centro-Clnica de la vista villa pro-C-8294562911-0-C-8496546328-0-0-0 | M76: La Romana | N76: VILLA HERMOSA | O76: VILLA HERMOSA | P76: Villa progreso | Q76: C Ana | R76: 3 | S76: CCSM | T76: Centro | U76: Clnica de la vista villa pro | V76: C | W76: 8294562911 | X76: 0 | Y76: C | Z76: 8496546328 | AA76: 0 | AB76: 0 | AC76: 0 | AE76: APPPOPULAR | AF76: 46204.395 | AG76: En proceso | AH76: TD- ENTREGADO | AJ76: PRINCIPAL | AL76: 46206
A77: 46209 | B77: 4-13821403512 | C77: Cuentas | D77: Solicitud de Servicios | E77: Entrega Tarjeta Debito | F77: U52123 | G77: 40206054909 | H77: NASHELYN CAMILA TAVAREZ FIGUEROA | I77: OFICINA DOWNTOWN CENTER MALL | K77: SANTIAGO;SANTIAGO;PARQUE METROPOLITANO | L77: SANTIAGO-SANTIAGO-SANTIAGO-PARQUE METROPOLITANO DE SANTIAGO-CALLE10 NO 43 LOS QUEMADOS--0-0-8097160363-C-8092838733-0-C-8097160363-0 | M77: Santiago | N77: Santiago | O77: Santiago | P77: PARQUE METROPOLITANO | Q77: CALLE10 NO 43 LOS QU | S77: 0 | T77: 0 | U77: 8097160363 | V77: C | W77: 8092838733 | X77: 0 | Y77: C | Z77: 8097160363 | AA77: 0 | AE77: APPPOPULAR | AF77: 46207.438 | AG77: En proceso | AH77: TD- ENTREGADO | AJ77: PRINCIPAL | AL77: 46213
A78: 46209 | B78: 4-13820823912 | C78: Cuentas | D78: Solicitud de Servicios | E78: Entrega Tarjeta Debito | F78: U46603 | G78: 40220086389 | H78: EMELY ELIANA DE LOS SANTOS ROSARI | I78: 270-OFICINA LICEY AL MEDIO | J78: U50911 | K78: Santiago;Santiago;Cerros de Gurabo | L78: Santiago-Santiago-Santiago-Cerros de Gurabo-Calle Erick Eckman-14-Torre Don Manuel Apto -B1-Frente a MCC CARGO-C-8098391459-0-C-8098691459-0-0-0 | M78: Santiago | N78: Santiago | O78: Santiago | P78: Cerros de Gurabo | Q78: Calle Erick Eckman | R78: 14 | S78: Torre Don Manuel Apto | T78: B1 | U78: Frente a MCC CARGO | V78: C | W78: 8098391459 | X78: 0 | Y78: C | Z78: 8098691459 | AA78: 0 | AB78: 0 | AC78: 0 | AE78: APPPOPULAR | AF78: 46207.378 | AG78: En proceso | AH78: TD- DEVUELTO NO LOCALIZADO | AI78: numeros equivocados
A79: 46204 | B79: 4-13802400782 | C79: Cuentas | D79: Solicitud de Servicios | E79: Entrega Tarjeta Debito | F79: U52123 | G79: 40211600651 | H79: ERICKA LISBET RODRIGUEZ VALERIO | I79: 243-OFICINA CALLE DEL SOL, STGO. | J79: U32288 | K79: Santiago;Santiago;El Congo | L79: Santiago-Santiago-Santiago-El Congo -Calle Espana -93-D Charlotte Floristeria -Esquina 27-Antes de Braulio celular-C-8294590081-0-C-8098470192-0-0-0 | M79: Santiago | N79: Santiago | O79: Santiago | P79: El Congo | Q79: Calle Espana | R79: 93 | S79: D Charlotte Floristeria | T79: Esquina 27 | U79: Antes de Braulio celular | V79: C | W79: 8294590081 | X79: 0 | Y79: C | Z79: 8098470192 | AA79: 0 | AB79: 0 | AC79: 0 | AE79: APPPOPULAR | AF79: 46204.618 | AG79: En proceso | AH79: TD- ENTREGADO | AJ79: PRINCIPAL | AL79: 46209
A80: 46204 | B80: 4-13798442522 | C80: Cuentas | D80: Solicitud de Servicios | E80: Entrega Tarjeta Debito | F80: U46603 | G80: 40210046948 | H80: LAURA VICTORIA TORRES PAULINO | I80: 266-OFICINA AV. JUAN PABLO DUARTE | J80: U28485 | K80: Santiago;Santiago;Villa Olga | L80: SANTIAGO-SANTIAGO-SANTIAGO-Villa Olga-8 edificio 8A-8-Nadal Asociados-legal-Es una oficina de abogados-C-8296052096-0-R-8097240988-0-C-0-0 | M80: Santiago | N80: Santiago | O80: Santiago | P80: Villa Olga | Q80: 8 edificio 8A | R80: 8 | S80: Nadal Asociados | T80: legal | U80: Es una oficina de abogados | V80: C | W80: 8296052096 | X80: 0 | Y80: R | Z80: 8097240988 | AA80: 0 | AB80: C | AC80: 0 | AD80: 0 | AE80: APPPOPULAR | AF80: 46204.403 | AG80: En proceso | AH80: TD- ENTREGADO | AJ80: PRINCIPAL | AL80: 46209 | AO80: Contactos Efectivos | AP80: SANTIAGO!NVILLA OLGA !NCALLE 11 EDIF 8A !NNADAL ASOCIADOS !NLITIGIOS !NFRENTE A GOMEZ MALLOL!N8296052096 HORA 8AM A 5PM !NAOGANDO | AQ80: 8097240988
A81: 46204 | B81: 4-13801196932 | C81: Cuentas | D81: Solicitud de Servicios | E81: Entrega Tarjeta Debito | F81: U52123 | G81: 40211924572 | H81: STALIN FELIX ALONZO JIMENEZ | I81: OFICINA DOWNTOWN CENTER MALL | K81: Santiago;Santiago;Armera tapia | L81: Santiago-Santiago-Santiago-Armera tapia -Anthonio Guzmn-0-Armeratapia-Nivel 2 ar-Armeratapia segundo nivel-C-8097085298-0-C-8494091692-0-0-0 | M81: Santiago | N81: Santiago | O81: Santiago | P81: Armera tapia | Q81: Anthonio Guzmn | R81: 0 | S81: Armeratapia | T81: Nivel 2 ar | U81: Armeratapia segundo nivel | V81: C | W81: 8097085298 | X81: 0 | Y81: C | Z81: 8494091692 | AA81: 0 | AB81: 0 | AC81: 0 | AE81: APPPOPULAR | AF81: 46204.552 | AG81: En proceso | AH81: TD- ENTREGADO | AJ81: PRINCIPAL | AL81: 46209
A82: 46204 | B82: 4-13801006292 | C82: Cuentas | D82: Solicitud de Servicios | E82: Entrega Tarjeta Debito | F82: U52123 | G82: 40226171714 | H82: LADIE JULIANA RODRIGUEZ TURNBULL | I82: 247-OFICINA MOCA | J82: U28666 | K82: Santiago;Santiago;Altos de rafey | L82: Santiago-Santiago-Santiago-Altos de rafey-Notions dominicana-1-Notions dominicana -Compras-0-C-8493755238-0-C-8295294909-0-T-8095757000-0 | M82: Santiago | N82: Santiago | O82: Santiago | P82: Altos de rafey | Q82: Notions dominicana | R82: 1 | S82: Notions dominicana | T82: Compras | U82: 0 | V82: C | W82: 8493755238 | X82: 0 | Y82: C | Z82: 8295294909 | AA82: 0 | AB82: T | AC82: 8095757000 | AD82: 0 | AE82: APPPOPULAR | AF82: 46204.538 | AG82: En proceso | AH82: TD- ENTREGADO | AJ82: PRINCIPAL | AL82: 46209
A83: 46204 | B83: 4-13800808912 | C83: Cuentas | D83: Solicitud de Servicios | E83: Entrega Tarjeta Debito | F83: U52123 | G83: 03102063892 | H83: WINSTON RAFAEL CEPEDA ARIAS | I83: 242-OFICINA LAS COLINAS, STGO. | J83: U42559 | K83: Santiago;Santiago;Cienfuegos | L83: SANTIAGO-SANTIAGO-SANTIAGO-cienfuegos-calle 9-38-WINSTON CEPEDA UNIFORMES-d 3 nivele-esc cienfuego abajo-C-8098494862-0-C-8498494862-0-R-8095768942-0 | M83: Santiago | N83: Santiago | O83: Santiago | P83: Cienfuegos | Q83: calle 9 | R83: 38 | S83: WINSTON CEPEDA UNIFORMES | T83: d 3 nivele | U83: esc cienfuego abajo | V83: C | W83: 8098494862 | X83: 0 | Y83: C | Z83: 8498494862 | AA83: 0 | AB83: R | AC83: 8095768942 | AD83: 0 | AE83: APPPOPULAR | AF83: 46204.557 | AG83: En proceso | AH83: TD- ENTREGADO | AJ83: PRINCIPAL | AL83: 46209
A84: 46204 | B84: 4-13800557472 | C84: Cuentas | D84: Solicitud de Servicios | E84: Entrega Tarjeta Debito | F84: U52123 | G84: 40212297259 | H84: LUISA MARIA GENAO MOYA | I84: OFICINA DOWNTOWN CENTER MALL | K84: SANTIAGO;SANTIAGO;Ingenio abajo | L84: Santiago-Santiago-Santiago-Ingenio abajo -Parada 7-7-William electrodomsticos-3-En los apartamentos de Wilia-C-8298035154-0-C-8096663357-0-0-0 | M84: Santiago | N84: Santiago | O84: Santiago | P84: INGENIO ABAJO | Q84: Parada 7 | R84: 7 | S84: William electrodomsticos | T84: 3 | U84: En los apartamentos de Wilia | V84: C | W84: 8298035154 | X84: 0 | Y84: C | Z84: 8096663357 | AA84: 0 | AB84: 0 | AC84: 0 | AE84: APPPOPULAR | AF84: 46204.512 | AG84: En proceso | AH84: TD- ENTREGADO | AJ84: PRINCIPAL | AL84: 46207
A85: 46204 | B85: 4-13798693802 | C85: Cuentas | D85: Solicitud de Servicios | E85: Entrega Tarjeta Debito | F85: U52123 | G85: 03101003626 | H85: MARCO MIGUEL GARCIA GARCIA | I85: 244-OFICINA 27 DE FEBRERO, STGO. | J85: U45657 | K85: SANTIAGO;SANTIAGO;Vista de cerro alto | L85: SANTIAGO-SANTIAGO-SANTIAGO-Vista de Cerro Alto-Principal-01-I-A1-Residencial Brisas del Norte-C-8097969573-0-R-8095705180-0-C-0-0 | M85: Santiago | N85: Santiago | O85: Santiago | P85: Vista de cerro alto | Q85: principal | R85: 01 | S85: i | T85: a1 | U85: Residencial brisas del norte | V85: C | W85: 8097969573 | X85: 0 | Y85: R | Z85: 8095705180 | AA85: 0 | AB85: C | AC85: 0 | AD85: 0 | AE85: APPPOPULAR | AF85: 46204.419 | AG85: En proceso | AH85: TD- ENTREGADO | AJ85: PRINCIPAL | AL85: 46207 | AO85: Contactos Efectivos | AP85: RES VISTA DEL NORTE!NEDF YA1!NSECTOR/ VITA DEL CERRO ALTO !NCALLE/ PRINCIPAL!NREF/ ENTRANDO POR TALLER DE PLANTAS ELECTRICO!N8097969573 8AM A 4PM!NSVELOZ!N | AQ85: 8097969573
A86: 46209 | B86: 4-13820603532 | C86: Cuentas | D86: Solicitud de Servicios | E86: Entrega Tarjeta Debito | F86: U46603 | G86: 40211634478 | H86: FRANCIS JOEL TEJADA GONZALEZ | I86: 246-OFICINA ZONA FRANCA, STGO. | J86: U38309 | K86: Santiago;Santiago;Rafey | L86: SANTIAGO-SANTIAGO-SANTIAGO-rafey-b-0022-utp-v-utp-C-8299193662-0-C-8498821300-0-C-0-0 | M86: Santiago | N86: Santiago | O86: Santiago | P86: Rafey | Q86: B | R86: 0022 | S86: Utp | T86: V | U86: utp | V86: C | W86: 8299193662 | X86: 0 | Y86: C | Z86: 8498821300 | AA86: 0 | AB86: C | AC86: 0 | AD86: 0 | AE86: APPPOPULAR | AF86: 46207.102 | AG86: En proceso | AH86: TD- DEVUELTO NO LOCALIZADO
A87: 46204 | B87: 4-13798210002 | C87: Cuentas | D87: Solicitud de Servicios | E87: Entrega Tarjeta Debito | F87: U52123 | G87: 40211336215 | H87: FRANKLIN ALBERTO CAPELLAN HUBARDINO | I87: 244-OFICINA 27 DE FEBRERO, STGO. | J87: U19099 | K87: Santiago;Santiago;Los santos abajos | L87: Santiago-Santiago-Santiago-Los santos abajos -Calle 4-31-0-0-0-C-8092704441-0-C-8298144482-0-0-0 | M87: Santiago | N87: Santiago | O87: Santiago | P87: Los santos abajos | Q87: calle 4 | R87: 31 | S87: 0 | T87: 0 | U87: 0 | V87: C | W87: 8092704441 | X87: 0 | Y87: C | Z87: 8298144482 | AA87: 0 | AB87: 0 | AC87: 0 | AE87: APPPOPULAR | AF87: 46204.394 | AG87: En proceso | AH87: TD- ENTREGADO | AJ87: PRINCIPAL | AL87: 46209
A88: 46204 | B88: 4-13801745332 | C88: Cuentas | D88: Solicitud de Servicios | E88: Entrega Tarjeta Debito | F88: U46603 | G88: 03103646570 | H88: EPIFANIO SOSA NUNEZ | I88: 752-DEPARTAMENTO COBROS ESPECIALIZADOS | J88: U48968 | K88: SANTIAGO;SANTIAGO;LOS CIRUELITOS | L88: SANTIAGO-SANTIAGO-SANTIAGO-LOS CIRUELITOS-13-97-0-0-0-C-8293425354-0-R-8095709751-0-C-8098752563-0 | M88: Santiago | N88: Santiago | O88: Santiago | P88: LOS CIRUELITOS | Q88: 13 | R88: 97 | S88: 0 | T88: 0 | U88: 0 | V88: C | W88: 8293425354 | X88: 0 | Y88: R | Z88: 8095709751 | AA88: 0 | AB88: C | AC88: 8098752563 | AD88: 0 | AE88: APPPOPULAR | AF88: 46204.586 | AG88: En proceso | AH88: TD- ENTREGADO | AJ88: PRINCIPAL | AL88: 46207 | AO88: Contactos Efectivos | AP88: ENVIO DIRECCION CLIENTE!N!NPROV//SANTIAGO!NSECT//LOS CIRUELITOS!NCALLE//13!Ncasa no 97!NREF//frent barberia cristian leny!N8293425354 hora 11am a 1pm!Nbsoto | AQ88: 8095709751
A89: 46204 | B89: 4-13801103592 | C89: Cuentas | D89: Solicitud de Servicios | E89: Entrega Tarjeta Debito | F89: U46603 | G89: 40218119887 | H89: PAMELA NICOLE FRANCISCO URENA | I89: OFICINA DOWNTOWN CENTER MALL | J89: U46569 | K89: Santiago;Bisono;Barrio Duarte | L89: Santiago-Bisono-Bisono-Barrio Duarte-Calle Jose Vargas -2-0-0-0-C-8292795375-0-C-8296183223-0-0-0 | M89: Santiago | N89: BISONO | O89: Bisono | P89: Barrio Duarte | Q89: Calle Jose Vargas | R89: 2 | S89: 0 | T89: 0 | U89: 0 | V89: C | W89: 8292795375 | X89: 0 | Y89: C | Z89: 8296183223 | AA89: 0 | AB89: 0 | AC89: 0 | AE89: APPPOPULAR | AF89: 46204.541 | AG89: En proceso | AH89: TD- ENTREGADO | AJ89: PRINCIPAL | AL89: 46207 | AN89: SI | AO89: Contactos Efectivos | AP89: ENVIAR DIRECCION CLIENTE !N!NPROVINCIA /SANTIAGO !NSECTOR /BISONO!NCALLE/ JOSE VARGAS !NCASA/2!NREF /PROX AL CLUB JUAN PABLO DUARTE NAVARRETE !NNO/ 8292795375!NHORA /8AM A 5PM!NCPEREZ | AQ89: 8292795375
A90: 46204 | B90: 4-13795557532 | C90: Cuentas | D90: Solicitud de Servicios | E90: Entrega Tarjeta Debito | F90: U46603 | G90: 40238075333 | H90: SCARLET NOEMI LOPEZ PEREIRA | I90: OFICINA DOWNTOWN CENTER MALL | K90: Santo Domingo;Santo Domingo Este;Don Paco lll | L90: Santo Domingo-Santo Domingo Este-Santo Domingo Este-Don Paco lll-Cendero-14-0-0-5-C-8094422128-0-C-8096417674-0-0-0 | M90: Santo Domingo | N90: Santo Domingo Este | O90: Santo Domingo Este | P90: Don Paco lll | Q90: Cendero | R90: 14 | S90: 0 | T90: 0 | U90: 5 | V90: C | W90: 8094422128 | X90: 0 | Y90: C | Z90: 8096417674 | AA90: 0 | AB90: 0 | AC90: 0 | AE90: APPPOPULAR | AF90: 46203.749 | AG90: En proceso | AH90: TD- ENTREGADO | AI90: Brailin | AJ90: PRINCIPAL | AL90: 46205
A91: 46204 | B91: 4-13802097012 | C91: Cuentas | D91: Solicitud de Servicios | E91: Entrega Tarjeta Debito | F91: U52123 | G91: 40200264774 | H91: MICHAEL YOEL LANTIGUA | I91: OFICINA DOWNTOWN CENTER MALL | K91: Santo Domingo;Santo Domingo Este;Los minas | L91: Santo Domingo-Santo Domingo Este-Santo Domingo Este-Los minas -Calle Jose Ramirez -2-0-0-Frente a inaipi -C-8099438946-0-C-8099438946-0-0-0 | M91: Santo Domingo | N91: Santo Domingo Este | O91: Santo Domingo Este | P91: Los minas | Q91: Calle Jose Ramirez | R91: 2 | S91: 0 | T91: 0 | U91: Frente a inaipi | V91: C | W91: 8099438946 | X91: 0 | Y91: C | Z91: 8099438946 | AA91: 0 | AB91: 0 | AC91: 0 | AE91: APPPOPULAR | AF91: 46204.615 | AG91: En proceso | AH91: TD- ENTREGADO | AI91: Brailin | AJ91: PRINCIPAL | AL91: 46206 | AO91: Contactos Efectivos | AP91: !NENVIO A DIRECCION!N!NPROVINCIA // SANTO DOMINGO ESTE!NSECTOR// LOS MINAS !NCASA// NO 02!NCALLE// JOSE RAMIREZ !NREF// PROXIMO A SUPER COLMADO VICTORIA !NTEL// 8099438946!NHORA// 8 AMA 5 PM !NNDONE!N | AQ91: 8099438946
A92: 46204 | B92: 4-13801876232 | C92: Cuentas | D92: Solicitud de Servicios | E92: Entrega Tarjeta Debito | F92: U52123 | G92: 22301479261 | H92: INGRISELA BERIGUETE MONTERO | I92: 200-OFICINA OZAMA | J92: U34314 | K92: Santo Domingo;Santo Domingo Este;Villa esfuerzo | L92: SANTO DOMINGO-SANTO DOMINGO ESTE-SANTO DOMINGO ESTE-Villa esfuerzo-Jacobo macljuta-23-0-0-0-C-8094052056-0-C-8294414832-0-C-0-0 | M92: Santo Domingo | N92: Santo Domingo Este | O92: Santo Domingo Este | P92: Villa esfuerzo | Q92: Jacobo macljuta | R92: 23 | S92: 0 | T92: 0 | U92: 0 | V92: C | W92: 8094052056 | X92: 0 | Y92: C | Z92: 8294414832 | AA92: 0 | AB92: C | AC92: 0 | AD92: 0 | AE92: APPPOPULAR | AF92: 46204.589 | AG92: En proceso | AH92: TD- ENTREGADO | AI92: Brailin | AJ92: PRINCIPAL | AL92: 46206 | AO92: Contactos Efectivos | AP92: !NENVIO A DIRECCION!N!NPROVINCIA // SANTO DOMINGO ESTE !NSECTOR// VILLA ESFUERZO!NCASA// NO 23!NCALLE// JACOBO MAJLUTA !NREF// PROXIMO AL COLMADO ENRIQUILLO Y BAJO MUNDO VAPEDRINK!NTEL// 8094052056!NHORA// 8 AM A 2 PM!NNDONE!N | AQ92: 8094052056
A93: 46204 | B93: 4-13801590762 | C93: Cuentas | D93: Solicitud de Servicios | E93: Entrega Tarjeta Debito | F93: U52123 | G93: 22301425611 | H93: YUNY MORILLO SANCHEZ | I93: 196-OFICINA SAN VICENTE DE PAUL | J93: U33844 | K93: SANTO DOMINGO;SANTO DOMINGO ESTE;villa faro | L93: Santo Domingo-Santo Domingo Este-Santo Domingo Este-Villa faro-Higuey-20-20-30-Residencial bethel -C-8099622790-0-C-8096922710-0-0-0 | M93: Santo Domingo | N93: Santo Domingo Este | O93: Santo Domingo Este | P93: villa faro | Q93: higuey | R93: 20 | S93: 20 | T93: 30 | U93: Residencial Bethel | V93: C | W93: 8099622790 | X93: 0 | Y93: C | Z93: 8096922710 | AA93: 0 | AB93: 0 | AC93: 0 | AE93: APPPOPULAR | AF93: 46204.592 | AG93: En proceso | AH93: TD- ENTREGADO | AI93: Gabriel | AJ93: PRINCIPAL | AL93: 46209
A94: 46204 | B94: 4-13801582512 | C94: Cuentas | D94: Solicitud de Servicios | E94: Entrega Tarjeta Debito | F94: U52123 | G94: 40231025566 | H94: STARLING FRANCISCO MORETA | I94: OFICINA DOWNTOWN CENTER MALL | K94: Santo Domingo;Santo Domingo Este;Los mameyes | L94: SANTO DOMINGO-SANTO DOMINGO ESTE-SANTO DOMINGO ESTE-LOS MAMEYES-1BEROAMERICANO CASA SIN-128-0-0-Colmado Jasiel Siempre Frias-C-8296268602-0-C-8492794440-0 | M94: Santo Domingo | N94: Santo Domingo Este | O94: Santo Domingo Este | P94: Los mameyes | Q94: 1BEROAMERICANO CASA | R94: 128 | S94: 0 | T94: 0 | U94: Colmado Jasiel Siempre Frias | V94: C | W94: 8296268602 | X94: 0 | Y94: C | Z94: 8492794440 | AA94: 0 | AE94: APPPOPULAR | AF94: 46204.57 | AG94: En proceso | AH94: TD- ENTREGADO | AI94: Gabriel | AJ94: PRINCIPAL | AL94: 46207
A95: 46204 | B95: 4-13801368232 | C95: Cuentas | D95: Solicitud de Servicios | E95: Entrega Tarjeta Debito | F95: U52123 | G95: 40225691514 | H95: ALTAGRACIA YANETH HERNANDEZ ARIAS | I95: 163-OFICINA HIPER UNO ENSANCHE ISABELITA | J95: U50153 | K95: Santo Domingo;Santo Domingo Este;Alma Rosa I | L95: Santo Domingo-Santo Domingo Este-Santo Domingo Este-Alma Rosa I-Calle activo 20 30-145-Life Quiro -145-Frente a Gen Casa-C-8295172291-0-R-8099206141-0-0-0 | M95: Santo Domingo | N95: Santo Domingo Este | O95: Santo Domingo Este | P95: Alma Rosa I | Q95: Calle activo 20 30 | R95: 145 | S95: Life quiro | T95: 145 | U95: Frente a Gen Casa | V95: C | W95: 8295172291 | X95: 0 | Y95: R | Z95: 8099206141 | AA95: 0 | AB95: 0 | AC95: 0 | AE95: APPPOPULAR | AF95: 46204.556 | AG95: En proceso | AH95: TD- ENTREGADO | AI95: Brailin | AJ95: PRINCIPAL | AL95: 46206
A96: 46209 | B96: 4-13820211752 | C96: Cuentas | D96: Solicitud de Servicios | E96: Entrega Tarjeta Debito | F96: U52123 | G96: 03104286749 | H96: JULISSA ANTONIA LOPEZ ARACENA | I96: 349-OFICINA SANTIAGO CENTER | J96: U35759 | K96: SANTIAGO;SANTIAGO;jardines del este | L96: SANTIAGO-SANTIAGO-SANTIAGO-Jardines del Este-Jose jacintohenrique-5-Thomas IV-D5-bomba total Rafael vidal-C-8299887701-0-R-8093822613-0-C-0-0 | M96: Santiago | N96: Santiago | O96: Santiago | P96: jardines del este | Q96: Jose jacintohenrique | R96: 5 | S96: Thomas IV | T96: D5 | U96: bomba total Rafael vidal | V96: C | W96: 8299887701 | X96: 0 | Y96: R | Z96: 8093822613 | AA96: 0 | AB96: C | AC96: 0 | AD96: 0 | AE96: APPPOPULAR | AF96: 46206.861 | AG96: En proceso | AH96: TD- ENTREGADO | AJ96: PRINCIPAL | AL96: 46213
A97: 46204 | B97: 4-13800920832 | C97: Cuentas | D97: Solicitud de Servicios | E97: Entrega Tarjeta Debito | F97: U52123 | G97: 40233096888 | H97: JHOSMEILY VIZCAINO DE JESUS | I97: 293-OFICINA AGORA MALL | J97: U39325 | K97: SANTO DOMINGO;SANTO DOMINGO ESTE;Alma Rosa II | L97: Santo Domingo-Santo Domingo Este-Santo Domingo Este-Alma Rosa II-AvSanVicente de Paul-154-JDC inversiones -Recepcin-Plaza aventura segundo piso -C-8495771423-0-C-8097188788-0-0-0 | M97: Santo Domingo | N97: Santo Domingo Este | O97: Santo Domingo Este | P97: Alma Rosa II | Q97: AvSanVicente de Paul | R97: 154 | S97: JDC inversiones | T97: Recepcin | U97: Plaza aventura segundo piso | V97: C | W97: 8495771423 | X97: 0 | Y97: C | Z97: 8097188788 | AA97: 0 | AB97: 0 | AC97: 0 | AE97: APPPOPULAR | AF97: 46204.531 | AG97: En proceso | AH97: TD- ENTREGADO | AI97: Brailin | AJ97: PRINCIPAL | AL97: 46205
A98: 46204 | B98: 4-13800458322 | C98: Cuentas | D98: Solicitud de Servicios | E98: Entrega Tarjeta Debito | F98: U52123 | G98: 00114308885 | H98: CRISTINA DEL CARMEN ROMAN YNOA | I98: 209-OFICINA CHARLES DE GAULLE | J98: U28497 | K98: SANTO DOMINGO;SANTO DOMINGO ESTE;los trinitarios 2 | L98: SANTO DOMINGO-SANTO DOMINGO ESTE-SANTO DOMINGO ESTE-los trinitarios 2-A-7-0-0-colmado masiel-C-8494555354-0-R-8092311066-0-C-0-0 | M98: Santo Domingo | N98: Santo Domingo Este | O98: Santo Domingo Este | P98: los trinitarios 2 | Q98: A | R98: 7 | S98: 0 | T98: 0 | U98: colmado masiel | V98: C | W98: 8494555354 | X98: 0 | Y98: R | Z98: 8092311066 | AA98: 0 | AB98: C | AC98: 0 | AD98: 0 | AE98: APPPOPULAR | AF98: 46204.506 | AG98: En proceso | AH98: TD- ENTREGADO | AI98: Brailin | AJ98: PRINCIPAL | AL98: 46205
A99: 46204 | B99: 4-13799380872 | C99: Cuentas | D99: Solicitud de Servicios | E99: Entrega Tarjeta Debito | F99: U46603 | G99: 40237561002 | H99: FRANCISCA VERONICA CUEVAS | I99: OFICINA DOWNTOWN CENTER MALL | J99: U46569 | K99: Santo Domingo;Santo Domingo Este;Los frailes 2 | M99: Santo Domingo | N99: Santo Domingo Este | O99: Santo Domingo Este | P99: Los frailes 2 | Q99: malbella 4 | R99: 30 | S99: 0 | T99: 0 | U99: puerton maron | V99: C | W99: 8498834533 | X99: 0 | Y99: C | Z99: 8099582909 | AA99: 0 | AB99: C | AC99: 8092179209 | AD99: 0 | AE99: APPPOPULAR | AF99: 46204.475 | AG99: En proceso | AH99: TD- ENTREGADO | AI99: Brailin | AJ99: PRINCIPAL | AL99: 46205 | AN99: SI
A100: 46209 | B100: 4-13820062692 | C100: Cuentas | D100: Solicitud de Servicios | E100: Entrega Tarjeta Debito | F100: U52123 | G100: 40218537880 | H100: YARISA CABRERA ALVAREZ | I100: 258-OFICINA NAVARRETE | J100: U37830 | K100: SANTIAGO;BISONO;LOMA DE PERRO | L100: SANTIAGO-BISONO-BISONO-LOMA DE PERRO-calle 9 casa-35-0-0-0-C-8494730600-0-C-8292171373-0 | M100: Santiago | N100: Bisono | O100: Bisono | P100: LOMA DE PERRO | Q100: calle 9 casa | R100: 35 | S100: 0 | T100: 0 | U100: 0 | V100: C | W100: 8494730600 | X100: 0 | Y100: C | Z100: 8292171373 | AA100: 0 | AE100: APPPOPULAR | AF100: 46206.935 | AG100: En proceso | AH100: TD- ZONA FUERA DE COBERTURA
...

Sheet Sheet2
A2: ENTREGAS
A3: ZONAS | B3: QTY | C3: TARIFA | D3: Sub total
A4: Distrito Nacional | B4: 94 | C4: $ 4.02 | D4: $ 377.88
A5: GSD | B5: 216 | C5: $ 4.62 | D5: $ 997.92
A6: Santiago | B6: 166 | C6: $ 4.72 | D6: $ 783.52
A7: ZONA ESTE | B7: 129 | C7: $ 6.00 | D7: $ 774.00
A8: ZONA NORTE | B8: 1 | C8: $ 6.36 | D8: $ 6.36
A9: ZONA SUR | B9: 49 | C9: $ 6.13 | D9: $ 300.37
A10: Distrito Nacional - Areas Remotas | B10: - | C10: $ 5.89 | D10: $ -
A11: GSD - Areas Remotas | B11: - | C11: $ 6.47 | D11: $ -
A12: Santiago - Areas Remotas | B12: 8 | C12: $ 6.57 | D12: $ 52.56
A13: ZONA ESTE - Areas Remotas | B13: - | C13: $ 7.85 | D13: $ -
A14: ZONA NORTE - Areas Remotas | B14: - | C14: $ 8.26 | D14: $ -
A15: ZONA SUR - Areas Remotas | B15: 33 | C15: $ 8.00 | D15: $ 264.00
A16: Total | B16: 696 | D16: $ 3,556.61

Sheet TARIFAS
A1: Suplidor | B1: Zona | C1: Tarifa
A2: Suplidor | B2: Zona | C2: Cantidad: 1-35
A4: MailBoxes | B4: Distrito Nacional | C4: 4.1
B5: GSD | C5: 4.75
B6: Zona Norte | C6: 6.36
B7: Zona Este | C7: 6.15
B8: Zona Sur | C8: 6.21
B9: Areas Remotas | C9: 1.9
B10: Santiago (Centro) | C10: 4.75
B11: Santiago (Periferia) | C11: $ -
B12: Zona | C12: Cantidad: 36-100
B14: Distrito Nacional | C14: 4.02
B15: GSD | C15: 4.68
B16: Zona Norte | C16: 6.27
B17: Zona Este | C17: 6.08
B18: Zona Sur | C18: 6.13
B19: Areas Remotas | C19: 1.87
B20: Santiago (Centro) | C20: 4.72
B21: Santiago (Periferia) | C21: $ -
B22: Zona | C22: Cantidad: 100+
B24: Distrito Nacional | C24: 3.99
B25: GSD | C25: 4.62
B26: Zona Norte | C26: 6.17
B27: Zona Este | C27: 6
B28: Zona Sur | C28: 6.05
B29: Areas Remotas | C29: 1.85
B30: Santiago (Centro) | C30: 4.72
B31: Santiago (Periferia) | C31: $ -

Sheet LISTA
A1: EN PROCESO | C1: PRINCIPAL
A2: TD- ENTREGADO | C2: TERCERO
A3: TD- DEVUELTO DIRECCION IMCOMPLETA
A4: TD- DEVUELTO NO LOCALIZADO
A5: TD- NO APLICA PASAPORTE
A6: TD- NO LE INTERESA
A7: TD- RETIRADA EN OFICINA
A8: TD- SOLICITADA POR ERROR
A9: TD- ZONA FUERA DE COBERTURA
A10: NO LOCALIZADO
A11: CNT BPD - EN PROCESO
